Workbook

Sheet Parametri
A1: MODELLO QUANTITATIVO DELLA PROPOSTA DI RIFORMA PENSIONISTICA
A2: Foglio dei parametri — celle gialle = ipotesi chiave; celle verdi = parametri aggiunti rispetto a v1
A4: Parametro | B4: Valore | C4: Unità | D4: Note metodologiche | E4: Fonte
A5: DEMOGRAFIA E MACRO
A6: Anno iniziale | B6: 2027 | C6: anno | D6: Anno di partenza simulazione | E6: RGS 26/2025
A7: Orizzonte temporale | B7: 34 | C7: anni | D7: 2027-2060: copertura completa fino al picco demografico e discesa | E7: RGS 26/2025 — orizzonte a 2060
A8: Pensionati distinti (anno 0) | B8: 17 | C8: mln | D8: Pensionati fisici al 31/12/2026 ≈ 17.0 mln — crescita ~0.5 mln/anno da 16.3 (INPS flussi) | E8: INPS Osservatorio 2024 + stima flusso 2025-2026
A9: Pensioni vigenti (anno 0) | B9: 22.3 | C9: mln | D9: Pensioni vigenti al 1.1.2027 ≈ 22.3 mln (+1 mln da 21.3 nel 2024, flusso netto ~500k/anno) | E9: INPS Osservatorio Pensioni Vigenti 2024 + stima flusso
A10: Cumulo medio pensioni/pensionato | B10: =B9/B8 -> 1.3117647 | C10: n | D10: 21,3/16,3 = 1,31 — strutturale (vecchiaia+reversibilità) | E10: INPS Casellario 31/12/2024
A11: Occupati dipendenti privati (FPLD) | B11: 14 | C11: mln | D11: Perimetro Livello 1 base | E11: INPS-FPLD 2024
A12: Occupati dipendenti pubblici (CTPS) | B12: 3.5 | C12: mln | D12: Pubblici impiegati gestione separata CTPS | E12: INPS CTPS 2024
A13: Totale occupati Livello 1 | B13: 17.5 | C13: mln | D13: Dipendenti privati + pubblici — perimetro modello base | E13: Somma
A14: Crescita reale pensioni vigenti | B14: 0.006 | C14: %/anno | D14: AGGIORNATO +0.6%/anno: baby boom 2027-2036 acc. ingresso (AR2024: dep.ratio +7.2pp in 2022-2040) | E14: AR2024 Table 2 + RGS 26/2025 demografia
A15: Crescita reale occupati (al netto migrazione) | B15: -0.005 | C15: %/anno | D15: Trend demografico ISTAT base 2024 | E15: ISTAT
A16: Migrazione netta annua (scenario RGS) | B16: 176000 | C16: persone/anno | D16: AGGIORNATO: RGS 26/2025 usa 176k netti/anno scenario base (AR2024 Eurostat: 270k ottimistico) | E16: RGS 26/2025 scenario base migrazione
A17: Quota migranti in età lavorativa | B17: 0.7 | C17: % | D17: Stima Moressa: ~70% migranti sono 25-54 | E17: Moressa XV Rapporto 2025
A18: Effetto netto su occupati (mln/anno) | B18: 0.116 | C18: mln/anno | D18: 165k × 70% = 115,5k nuovi occupati lordi annui | E18: Derivato
A19: PIL reale anno 0 | B19: 2237 | C19: €mld | D19: PIL reale 2027 (€mld): 2184*(1.006)*(1.007)*(1.008)≈2237 — DEF 2025 g=0.8% in 2027 | E19: ISTAT contabilità nazionale 2024 + DEF 2025
A20: Crescita reale PIL (g) | B20: 0.008 | C20: %/anno | D20: CONFERMATA: DEF 2025 +0.8% nel 2027; AR2024 usa 0.8% trend produttività strutturale | E20: DEF 2025 + Ageing Report 2024 macro assumptions
A21: Salario imponibile medio | B21: 26700 | C21: €/anno | D21: AGGIORNATO: salario imponibile medio 2027 ≈ 26.700€ (26.000 nel 2024 + 3 anni × +0.2% reale) | E21: INPS FPLD 2024 + Eurostat ILC_DI03 growth trend
A22: Crescita reale salari (g_w) | B22: 0.002 | C22: %/anno | D22: CORRETTO dal +0,5% v1 a +0,05%: Eurostat ILC_DI03 mostra reale NEGATIVO per coorti attive 2005-2024 | E22: Eurostat ILC_DI03 + HICP 2005-2024
A24: SISTEMA ATTUALE (PAYG)
A25: Aliquota contributiva (dipendenti) | B25: 0.33 | C25: % | D25: 9,19% lavoratore + 23,81% datore | E25: INPS aliquote 2024
A26: Pensione media mensile (singola prestazione) | B26: 1218 | C26: €/mese | D26: AGGIORNATO: importo medio della SINGOLA prestazione (era 1.350 = pens. di vecchiaia) | E26: INPS Osservatorio 2024 — Q5 Bertonelli
A27: Reddito medio del pensionato | B27: 1718 | C27: €/mese | D27: 22.331 €/anno / 13 — somma 1,41 pensioni cumulate | E27: INPS Casellario 2024
A28: Mensilità annue | B28: 13 | C28: n | D28: Standard previdenziale italiano | E28: Norma
A29: Età pensionabile legale | B29: 67 | C29: anni | D29: Vecchiaia 2026 (Riforma Fornero) | E29: L. 214/2011
A30: Età pensionabile effettiva | B30: 64.8 | C30: anni | D30: AGGIUNTA: età effettiva media INPS 2024 (privati+autonomi) | E30: INPS XXIV Rapporto 2025
A31: Coefficiente trasformazione a 67 anni | B31: 0.05608 | C31: % | D31: AGGIORNATO 5,723%→5,608% biennio 2025-2026 | E31: DM MEF 20/11/2024
A32: Spesa PAYG/PIL anno 0 (status quo) | B32: 0.16 | C32: % | D32: AGGIORNATO 16.0% al 2027: interp. AR2024 15.4%(2024)→16.6%(2030), RGS conferma 15.4% 2024 | E32: AR2024 Table 6 + RGS 26/2025
A33: Spesa PAYG/PIL picco 2040 | B33: 0.171 | C33: % | D33: Picco 17.1% al 2040 CONFERMATO da RGS 26/2025; AR2024 mostra 17.3% al 2036 con schema diverso | E33: RGS 26/2025 + AR2024 Table 6
A34: Spesa PAYG/PIL fine orizzonte (2060) | B34: 0.141 | C34: % | D34: AGGIORNATO 14.1% al 2060: RGS 26/2025 esplicito (sostituisce 14.0% al 2070 della v3) | E34: RGS 26/2025 pag.14 esplicito
A35: Anno picco spesa/PIL | B35: 2040 | C35: anno | D35: Anno picco CONFERMATO 2040 per RGS 26/2025 (AR2024: 2036, schema leggermente diverso) | E35: RGS 26/2025
A36: Anno fine orizzonte | B36: 2060 | C36: anno | D36: Fine previsione: 2060 — raccordo con RGS 26/2025 (14.1% PIL) e AR2024 (13.7% PIL) | E36: RGS 26/2025 + AR2024
A38: PILASTRO 0 — SUSSIDIO UNIVERSALE
A39: P0 base mensile (B) | B39: 650 | C39: €/mese | D39: Sopra soglia povertà ISTAT (€598 Nord) | E39: Calibrazione propria
A40: Aliquota di taper (t) | B40: =B39/B41 -> 0.52 | C40: % | D40: EMRT 52% nella zona di taper | E40: Ingles-Stewart 2017 (Australia)
A41: Cap reddito totale | B41: 1250 | C41: €/mese | D41: P0=0 oltre B/t = 1.250 | E41: B/t
A42: Franchigia patrimoniale | B42: 50000 | C42: € | D42: Patrimonio escluso dal deemed rate | E42: Modello AU/UK
A43: Deemed rate | B43: 0.045 | C43: % | D43: Rendimento figurativo (era 7,8% AU post-2017, ridotto) | E43: Cilibrato vs AU
A44: P0 medio mensile a regime (calcolato) | B44: =MAX(0,B22-B23*(B46*B17*((1+B52)^B53-1)/B51)*B42/12) -> 0.002 | C44: €/mese | D44: Si aggiorna se cambi r_fondi | E44: Derivato
A45: Anni per phase-in P0 (sostituz. PAYG) | B45: 35 | C45: anni | D45: RIDOTTO 50→35: tasso flusso nuovi pensionati ~3,7%/anno | E45: Bilanciato su 600k/16 mln
A46: Nuovi pensionati l'anno (flusso) | B46: 550000 | C46: persone/anno | D46: 2026-2030 | E46: INPS Flussi Pensionamento
A47: Nuovi pensionati l'anno (flusso) | B47: 600000 | C47: persone/anno | D47: 2031-2037 | E47: INPS Flussi Pensionamento
A48: Nuovi pensionati l'anno (flusso) | B48: 480000 | C48: persone/anno | D48: 2038-2050 | E48: INPS Flussi Pensionamento
A50: PILASTRO 2 E BRDP — biforcazione contributiva
A51: Quota biforcazione Fase I (totale) | B51: 0.06 | C51: % | D51: Anni 1-10: 6% totale di cui 2 BRDP + 4 P2 | E51: Calibrazione propria
A52: Quota BRDP Fase I | B52: 0.02 | C52: % | D52: Anni 1-10 | E52: Calibrazione propria
A53: Quota P2 Fase I | B53: 0.04 | C53: % | D53: Anni 1-10 | E53: Calibrazione propria
A54: Quota biforcazione Fase II (totale) | B54: 0.08 | C54: % | D54: Anni 11-20: 8% totale di cui 2 BRDP + 6 P2 | E54: Calibrazione
A55: Quota BRDP Fase II | B55: 0.02 | C55: % | D55: Anni 11-20
A56: Quota P2 Fase II | B56: 0.06 | C56: % | D56: Anni 11-20
A57: Quota biforcazione Fase III | B57: 0.09 | C57: % | D57: Anni 21-30: 0 BRDP + 10 P2 (Save More Tomorrow escalation) | E57: Thaler-Benartzi 2004 framing
A58: Lavoratori under 40 (anno 1) | B58: 0.33 | C58: % | D58: % sulla forza lavoro perimetro | E58: ISTAT struttura forza lavoro 2024
A59: Lavoratori under 50 (dall'anno 5) | B59: 0.6 | C59: % | D59: % sulla forza lavoro perimetro | E59: ISTAT
A60: Tutti i lavoratori (anno 30) | B60: 1 | C60: % | D60: Coorti vecchie uscite | E60: Derivato
A61: Rendimento reale fondi P2 (r_fondi) — base | B61: 0.025 | C61: % | D61: RIDOTTO 5%→4%: realistico portafoglio 60/40 net of fees | E61: OECD Pensions at a Glance 2025
A62: Rendimento reale fondi P2 — scenario molto avverso | B62: 0.005 | C62: % | D62: Da modellare in sensitivity | E62: OECD
A63: Rendimento reale fondi P2 — scenario avverso | B63: 0.0125 | C63: % | D63: Da modellare in sensitivity | E63: OECD
A64: Rendimento reale fondi P2 — scenario ottimista | B64: 0.04 | C64: % | D64: Da modellare in sensitivity | E64: OECD
A65: Anni di carriera tipica P2 | B65: 40 | C65: anni | D65: Per calcolo montante lavoratore tipo | E65: INPS Osservatorio carriere
A66: Coefficiente trasformazione P2 (a 67) | B66: 0.05608 | C66: % | D66: Aggiornato DM MEF 11/2024 | E66: DM MEF 20/11/2024
A67: Spread reale BRDP (su HICP) | B67: 0.015 | C67: % | D67: AUMENTATO da 0,75% a 1,5% — necessario per appetibilità senza coercizione | E67: Confronto BTPi 25y
A68: Rendimento PAYG implicito (n+g_w) | B68: 0.0005 | C68: % | D68: AGGIORNATO: n≈0 + g_w 0,05% | E68: Aaron 1966 applicato a Italia 2024
A69: % portafoglio fondi assorbita da BRDP (coercitivo) | B69: 0.3 | C69: % | D69: AUMENTATO 20%→30% con quota OBBLIGATORIA modello PPM-svedese | E69: Tuo input + Cile 2008
A71: TASSAZIONE TEE / EET
A72: Aliquota IRPEF media (su contributi) | B72: 0.27 | C72: % | D72: Aliquota marginale media lavoratori | E72: MEF dichiarazioni 2024
A73: Imposta conversione una tantum | B73: 0.1 | C73: % | D73: Sotto 15% std EET (incentivo) | E73: Calibrazione propria
A74: % stock fondi che converte | B74: 0.3 | C74: % | D74: RIDOTTO 50%→30%: realistico data composizione anziani/giovani | E74: Stima conservativa
A75: Patrimonio fondi pensione anno 0 | B75: 244 | C75: €mld | D75: AGGIORNATO a fine 2024 | E75: COVIP Relazione 2024
A76: Anni finestra conversione | B76: 3 | C76: anni | D76: Periodo erogazione una tantum | E76: Calibrazione propria
A78: LEVA C — ETÀ PENSIONABILE
A79: Età pensionabile attuale | B79: 67 | C79: anni | D79: Vecchiaia 2026 | E79: L. 214/2011
A80: Età pensionabile target | B80: 69 | C80: anni | D80: +2 anni a 69 entro 2045 | E80: Calibrazione propria
A81: Risparmio chiusura deroghe | B81: 3.5 | C81: €mld/anno | D81: Quota 103, APe, Opzione Donna — immediato | E81: UPB-INPS 2022
A82: Risparmio età +2 a regime (anno 15+) | B82: 9 | C82: €mld/anno | D82: Stima 8-10 mld a regime | E82: RGS-UPB
A83: Anni per regime Leva C | B83: 15 | C83: anni | D83: Phase-in lineare | E83: Calibrazione propria
A85: LEVA E — CREDITI FIGLI
A86: Nascite annue | B86: 369000 | C86: n | D86: AGGIORNATO 380k→369k (ISTAT 2024) | E86: ISTAT 2024
A87: % famiglie reddito basso (<€25k) | B87: 0.55 | C87: % | D87: ISTAT distrib. redditi familiari | E87: ISTAT IT-SILC 2024
A88: % famiglie reddito medio (€25-50k) | B88: 0.3 | C88: % | D88: ISTAT distrib. redditi familiari | E88: ISTAT IT-SILC 2024
A89: % famiglie reddito alto (>€50k) | B89: 0.15 | C89: % | D89: ISTAT distrib. redditi familiari | E89: ISTAT IT-SILC 2024
A90: Credito reddito basso | B90: 2000 | C90: €/anno | D90: Per 5 anni per figlio | E90: Modello DE Kindererziehungszeiten
A91: Credito reddito medio | B91: 1200 | C91: €/anno | D91: Per 5 anni per figlio | E91: Modello DE
A92: Credito reddito alto | B92: 600 | C92: €/anno | D92: Per 5 anni per figlio | E92: Modello DE
A93: Anni di erogazione per figlio | B93: 5 | C93: anni | D93: Finestra di pagamento credito | E93: Calibrazione propria
A95: LEVA F — PILASTRO 0 SOSTITUTIVO (formula corretta)
A96: Pensione media nuova coorte (t=0) | B96: 1350 | C96: €/mese | D96: Pensione che il NUOVO pensionato avrebbe ricevuto da PAYG status quo | E96: INPS pens. vecchiaia 2024
A97: Quota P2 sulla pensione totale a regime | B97: 0.4 | C97: % | D97: A regime: P0 ~30%, P2 ~40-50%, complementare 10-20% | E97: Calibrato su 40 anni di P2 a 4% e r_fondi 4%
A98: Quota PAYG residuo (NUOVI pensionati t=0) | B98: 0.95 | C98: % | D98: Anno 1: nuovi pensionati hanno carriera quasi tutta in PAYG | E98: Derivato dalla coorte di transizione
A99: Decadimento PAYG residuo (anni) | B99: 30 | C99: anni | D99: Tempo perché nuovi pensionati abbiano carriera interamente nuova | E99: Modellistica
A101: LEVE NUOVE — RICALIBRAZIONE PARAMETRICA (Bertonelli Q18A)
A102: Leva G — Sotto-indicizzazione progressiva | B102: 6 | C102: €mld/anno | D102: MEDIA range 2-10 mld: soglia di protezione modulata (sentenza C.Cost. 167/2025) | E102: Bertonelli Q16+Q18A; sentenza 167/2025
A103: Leva G — Anno avvio | B103: 1 | C103: anno | D103: Immediato (LdB 2027) | E103: Operativo
A104: Leva H — Revisione reversibilità superstiti | B104: 5 | C104: €mld/anno | D104: MEDIA range 4-6 mld: aggancio attuariale a contributi de cuius | E104: Bertonelli Q18A — INPS spesa reversibilità 35-40 mld
A105: Leva H — Anno avvio | B105: 2 | C105: anno | D105: Anno 2 (richiede norma+attuariale) | E105: Operativo
A106: Leva I — Aggancio aspettativa di vita (riavvio) | B106: 2.75 | C106: €mld/anno | D106: MEDIA range 2,2-3,3 mld: adeguamento automatico requisiti | E106: Bertonelli Q18A — sospeso dal 2019
A107: Leva I — Anno avvio | B107: 2 | C107: anno | D107: Riavvio dal 2027 | E107: Operativo
A108: Leva J — Chiusura anticipazioni residue | B108: 1 | C108: €mld/anno | D108: MEDIA range 0,75-1,3 mld: stop rinnovo Quote/Opzione Donna/APe per casistiche non vincolate | E108: Bertonelli Q18A — INPS-UPB 2022
A109: Leva J — Anno avvio | B109: 1 | C109: anno | D109: Immediato (LdB 2027) | E109: Operativo
...

Sheet Modello
A1: MODELLO — PROIEZIONE ANNO PER ANNO (v2, 34 anni 2027-2060)
A2: Tutti i valori in termini reali (prezzi 2027). Flussi positivi = risparmi/entrate per lo Stato; negativi = costi/fabbisogno.
W3: Stock BRDP vivo — formula aggregata (interno+esterno) =SUM(Z)+SUM(AA). Rimborso AD include sia Z(t-15) sia AA(t-15) — v9.
A4: Anno | B4: t | C4: Pensioni vigenti (mln) | D4: Occupati L1 (mln) | E4: Att/Pens | F4: PIL reale (€mld) | G4: Salario medio (€) | H4: Spesa PAYG SQ (€mld) | I4: Spesa PAYG %PIL (RGS) | J4: Spesa rif. (€mld) | K4: Spesa rif./PIL | L4: %Lav in P2 | M4: Lav. in P2 (mln) | N4: Leva A (€mld) | O4: Leva B (€mld) | P4: Leva C (€mld) | Q4: Leva D gap (€mld) | R4: Leva D ai fondi | S4: Leva D fondi cum | T4: Leva E (€mld) | U4: Leva F CORRETTA | V4: Leva G (€mld) | W4: Leva H (€mld) | X4: Leva I (€mld) | Y4: Leva J (€mld) | Z4: BRDP emessi (€mld) | AA4: BRDP esterni (€mld) | AB4: Stock BRDP totale (€mld) | AC4: Interessi BRDP (€mld) | AD4: Rimborso cap. BRDP (€mld) | AE4: Saldo annuo (€mld) | AF4: Saldo cum. (€mld) | AG4: Debito tr./PIL | AH4: Stock BRDP interno (€mld) | AI4: Rimborso cap. BRDP interno (€mld)
A5: =Parametri!$B$6+B5 -> 2027 | B5: 0 | C5: =Parametri!$B$9 -> 22.3 | D5: =CHOOSE(Parametri!$B$143,Parametri!$B$13,Parametri!$B$13+Parametri!$B$146,Parametri!$B$13+Parametri!$B$146) -> 17.5 | E5: =D5/C5 -> 0.78475336 | F5: =Parametri!$B$19 -> 2237 | G5: =CHOOSE(Parametri!$B$143,Parametri!$B$21,Parametri!$B$155,Parametri!$B$155) -> 26700 | H5: =F5*I5 -> 357.92 | I5: =IF(B5<=(Parametri!$B$35-Parametri!$B$6),Parametri!$B$32+(Parametri!$B$33-Parametri!$B$32)*B5/(Parametri!$B$35-Parametri!$B$6),Parametri!$B$33+(Parametri!$B$34-Parametri!$B$33)*(B5-(Parametri!$B$35-Parametri!$B$6))/(Parametri!$B$36-Parametri!$B$35)) -> 0.16 | J5: =H5-AE5 -> 348.56105 | K5: =J5/F5 -> 0.1558163 | L5: =IF(B5<=5,Parametri!$B$58+(Parametri!$B$59-Parametri!$B$58)/5*B5,MIN(Parametri!$B$60,Parametri!$B$59+(Parametri!$B$60-Parametri!$B$59)/24*(B5-5))) -> 0.33 | M5: =L5*D5 -> 5.775 | N5: =IF(B5<Parametri!$B$76,Parametri!$B$75*Parametri!$B$74*Parametri!$B$73/Parametri!$B$76,0) -> 2.44 | O5: =IF(B5<10,Parametri!$B$53,IF(B5<20,Parametri!$B$56,Parametri!$B$57))*M5*G5*Parametri!$B$72/1000 -> 1.665279 | P5: =MIN(Parametri!$B$81+Parametri!$B$82, Parametri!$B$81+Parametri!$B$82*(B5+1)/Parametri!$B$83) -> 4.1 | Q5: =-IF(B5<10,Parametri!$B$51,IF(B5<20,Parametri!$B$54,Parametri!$B$57))*M5*G5/1000 -> -9.25155 | R5: =-Q5-Z5 -> 6.1677 | S5: =R5 -> 6.1677 | T5: =-(Parametri!$B$86*(Parametri!$B$87*Parametri!$B$90+Parametri!$B$88*Parametri!$B$91+Parametri!$B$89*Parametri!$B$92)/1000000000)*MIN(B5+1,Parametri!$B$93) -> -0.57195 | U5: =IF(B5<Parametri!$B$125,Parametri!$B$46,IF(B5<Parametri!$B$126,Parametri!$B$47,Parametri!$B$48))*Parametri!$B$96*13/1000000000*((B5+1)*Parametri!$B$121+B5*(B5+1)/2*Parametri!$B$122) -> 0.93957435 | V5: =IF(B5>=Parametri!$B$103-1,Parametri!$B$102*(1-Parametri!$B$127)^(B5-(Parametri!$B$103-1)),0) -> 6 | W5: =IF(B5>=Parametri!$B$105-1,Parametri!$B$104,0) -> 0 | X5: =IF(B5>=Parametri!$B$107-1,Parametri!$B$106+Parametri!$B$128*INT((B5-(Parametri!$B$107-1))/2),0) -> 0 | Y5: =IF(AND(B5>=Parametri!$B$109-1,B5<Parametri!$B$109-1+Parametri!$B$140),Parametri!$B$108,0) -> 1 | Z5: =IF(B5<10,Parametri!$B$52,IF(B5<20,Parametri!$B$55,0))*M5*G5/1000 -> 3.08385 | AA5: =Parametri!$B$159*Parametri!$B$160 -> 0 | AB5: =SUM(Z$5:Z5)+SUM(AA$5:AA5) -> 3.08385 | AC5: =-(Parametri!$B$67*SUM(Z$5:Z5)+Parametri!$B$161*SUM(AA$5:AA5)) -> -0.04625775 | AD5: =0 -> 0 | AE5: =Z5+AA5+N5+O5+P5+Q5+T5+U5+V5+W5+X5+Y5+AC5+AD5 -> 9.3589456 | AF5: =AE5 -> 9.3589456 | AG5: =-AF5/F5 -> -0.0041837039 | AH5: =SUM(Z$5:Z5) -> 3.08385 | AI5: 0
A6: =Parametri!$B$6+B6 -> 2028 | B6: 1 | C6: =C5*(1+Parametri!$B$14) -> 22.4338 | D6: =D5*(1+Parametri!$B$15)+Parametri!$B$145*(1-Parametri!$B$15)^B5 -> 17.5285 | E6: =D6/C6 -> 0.78134333 | F6: =F5*(1+Parametri!$B$20) -> 2254.896 | G6: =G5*(1+Parametri!$B$22) -> 26753.4 | H6: =F6*I6 -> 362.69135 | I6: =IF(B6<=(Parametri!$B$35-Parametri!$B$6),Parametri!$B$32+(Parametri!$B$33-Parametri!$B$32)*B6/(Parametri!$B$35-Parametri!$B$6),Parametri!$B$33+(Parametri!$B$34-Parametri!$B$33)*(B6-(Parametri!$B$35-Parametri!$B$6))/(Parametri!$B$36-Parametri!$B$35)) -> 0.16084615 | J6: =H6-AE6 -> 345.33862 | K6: =J6/F6 -> 0.15315058 | L6: =IF(B6<=5,Parametri!$B$58+(Parametri!$B$59-Parametri!$B$58)/5*B6,MIN(Parametri!$B$60,Parametri!$B$59+(Parametri!$B$60-Parametri!$B$59)/24*(B6-5))) -> 0.384 | M6: =L6*D6 -> 6.730944 | N6: =IF(B6<Parametri!$B$76,Parametri!$B$75*Parametri!$B$74*Parametri!$B$73/Parametri!$B$76,0) -> 2.44 | O6: =IF(B6<10,Parametri!$B$53,IF(B6<20,Parametri!$B$56,Parametri!$B$57))*M6*G6*Parametri!$B$72/1000 -> 1.9448169 | P6: =MIN(Parametri!$B$81+Parametri!$B$82, Parametri!$B$81+Parametri!$B$82*(B6+1)/Parametri!$B$83) -> 4.7 | Q6: =-IF(B6<10,Parametri!$B$51,IF(B6<20,Parametri!$B$54,Parametri!$B$57))*M6*G6/1000 -> -10.804538 | R6: =-Q6-Z6 -> 7.2030255 | S6: =S5+R6 -> 13.370725 | T6: =-(Parametri!$B$86*(Parametri!$B$87*Parametri!$B$90+Parametri!$B$88*Parametri!$B$91+Parametri!$B$89*Parametri!$B$92)/1000000000)*MIN(B6+1,Parametri!$B$93) -> -1.1439 | U6: =IF(B6<Parametri!$B$125,Parametri!$B$46,IF(B6<Parametri!$B$126,Parametri!$B$47,Parametri!$B$48))*Parametri!$B$96*13/1000000000*((B6+1)*Parametri!$B$121+B6*(B6+1)/2*Parametri!$B$122) -> 2.0551138 | V6: =IF(B6>=Parametri!$B$103-1,Parametri!$B$102*(1-Parametri!$B$127)^(B6-(Parametri!$B$103-1)),0) -> 5.91 | W6: =IF(B6>=Parametri!$B$105-1,Parametri!$B$104,0) -> 5 | X6: =IF(B6>=Parametri!$B$107-1,Parametri!$B$106+Parametri!$B$128*INT((B6-(Parametri!$B$107-1))/2),0) -> 2.75 | Y6: =IF(AND(B6>=Parametri!$B$109-1,B6<Parametri!$B$109-1+Parametri!$B$140),Parametri!$B$108,0) -> 1 | Z6: =IF(B6<10,Parametri!$B$52,IF(B6<20,Parametri!$B$55,0))*M6*G6/1000 -> 3.6015127 | AA6: =Parametri!$B$159*Parametri!$B$160 -> 0 | AB6: =SUM(Z$5:Z6)+SUM(AA$5:AA6) -> 6.6853627 | AC6: =-(Parametri!$B$67*SUM(Z$5:Z6)+Parametri!$B$161*SUM(AA$5:AA6)) -> -0.10028044 | AD6: =0 -> 0 | AE6: =Z6+AA6+N6+O6+P6+Q6+T6+U6+V6+W6+X6+Y6+AC6+AD6 -> 17.352725 | AF6: =AF5+AE6 -> 26.71167 | AG6: =-AF6/F6 -> -0.011846076 | AH6: =SUM(Z$5:Z6) -> 6.6853627 | AI6: 0
A7: =Parametri!$B$6+B7 -> 2029 | B7: 2 | C7: =C6*(1+Parametri!$B$14) -> 22.568403 | D7: =D6*(1+Parametri!$B$15)+Parametri!$B$145*(1-Parametri!$B$15)^B6 -> 17.557437 | E7: =D7/C7 -> 0.77796544 | F7: =F6*(1+Parametri!$B$20) -> 2272.9352 | G7: =G6*(1+Parametri!$B$22) -> 26806.907 | H7: =F7*I7 -> 367.51613 | I7: =IF(B7<=(Parametri!$B$35-Parametri!$B$6),Parametri!$B$32+(Parametri!$B$33-Parametri!$B$32)*B7/(Parametri!$B$35-Parametri!$B$6),Parametri!$B$33+(Parametri!$B$34-Parametri!$B$33)*(B7-(Parametri!$B$35-Parametri!$B$6))/(Parametri!$B$36-Parametri!$B$35)) -> 0.16169231 | J7: =H7-AE7 -> 349.7557 | K7: =J7/F7 -> 0.15387843 | L7: =IF(B7<=5,Parametri!$B$58+(Parametri!$B$59-Parametri!$B$58)/5*B7,MIN(Parametri!$B$60,Parametri!$B$59+(Parametri!$B$60-Parametri!$B$59)/24*(B7-5))) -> 0.438 | M7: =L7*D7 -> 7.6901576 | N7: =IF(B7<Parametri!$B$76,Parametri!$B$75*Parametri!$B$74*Parametri!$B$73/Parametri!$B$76,0) -> 2.44 | O7: =IF(B7<10,Parametri!$B$53,IF(B7<20,Parametri!$B$56,Parametri!$B$57))*M7*G7*Parametri!$B$72/1000 -> 2.2264129 | P7: =MIN(Parametri!$B$81+Parametri!$B$82, Parametri!$B$81+Parametri!$B$82*(B7+1)/Parametri!$B$83) -> 5.3 | Q7: =-IF(B7<10,Parametri!$B$51,IF(B7<20,Parametri!$B$54,Parametri!$B$57))*M7*G7/1000 -> -12.36896 | R7: =-Q7-Z7 -> 8.2459735 | S7: =S6+R7 -> 21.616699 | T7: =-(Parametri!$B$86*(Parametri!$B$87*Parametri!$B$90+Parametri!$B$88*Parametri!$B$91+Parametri!$B$89*Parametri!$B$92)/1000000000)*MIN(B7+1,Parametri!$B$93) -> -1.71585 | U7: =IF(B7<Parametri!$B$125,Parametri!$B$46,IF(B7<Parametri!$B$126,Parametri!$B$47,Parametri!$B$48))*Parametri!$B$96*13/1000000000*((B7+1)*Parametri!$B$121+B7*(B7+1)/2*Parametri!$B$122) -> 3.3466183 | V7: =IF(B7>=Parametri!$B$103-1,Parametri!$B$102*(1-Parametri!$B$127)^(B7-(Parametri!$B$103-1)),0) -> 5.82135 | W7: =IF(B7>=Parametri!$B$105-1,Parametri!$B$104,0) -> 5 | X7: =IF(B7>=Parametri!$B$107-1,Parametri!$B$106+Parametri!$B$128*INT((B7-(Parametri!$B$107-1))/2),0) -> 2.75 | Y7: =IF(AND(B7>=Parametri!$B$109-1,B7<Parametri!$B$109-1+Parametri!$B$140),Parametri!$B$108,0) -> 1 | Z7: =IF(B7<10,Parametri!$B$52,IF(B7<20,Parametri!$B$55,0))*M7*G7/1000 -> 4.1229868 | AA7: =Parametri!$B$159*Parametri!$B$160 -> 0 | AB7: =SUM(Z$5:Z7)+SUM(AA$5:AA7) -> 10.80835 | AC7: =-(Parametri!$B$67*SUM(Z$5:Z7)+Parametri!$B$161*SUM(AA$5:AA7)) -> -0.16212524 | AD7: =0 -> 0 | AE7: =Z7+AA7+N7+O7+P7+Q7+T7+U7+V7+W7+X7+Y7+AC7+AD7 -> 17.760432 | AF7: =AF6+AE7 -> 44.472103 | AG7: =-AF7/F7 -> -0.019565935 | AH7: =SUM(Z$5:Z7) -> 10.80835 | AI7: 0
A8: =Parametri!$B$6+B8 -> 2030 | B8: 3 | C8: =C7*(1+Parametri!$B$14) -> 22.703813 | D8: =D7*(1+Parametri!$B$15)+Parametri!$B$145*(1-Parametri!$B$15)^B7 -> 17.586813 | E8: =D8/C8 -> 0.77461936 | F8: =F7*(1+Parametri!$B$20) -> 2291.1186 | G8: =G7*(1+Parametri!$B$22) -> 26860.521 | H8: =F8*I8 -> 372.3949 | I8: =IF(B8<=(Parametri!$B$35-Parametri!$B$6),Parametri!$B$32+(Parametri!$B$33-Parametri!$B$32)*B8/(Parametri!$B$35-Parametri!$B$6),Parametri!$B$33+(Parametri!$B$34-Parametri!$B$33)*(B8-(Parametri!$B$35-Parametri!$B$6))/(Parametri!$B$36-Parametri!$B$35)) -> 0.16253846 | J8: =H8-AE8 -> 357.36299 | K8: =J8/F8 -> 0.15597751 | L8: =IF(B8<=5,Parametri!$B$58+(Parametri!$B$59-Parametri!$B$58)/5*B8,MIN(Parametri!$B$60,Parametri!$B$59+(Parametri!$B$60-Parametri!$B$59)/24*(B8-5))) -> 0.492 | M8: =L8*D8 -> 8.6527121 | N8: =IF(B8<Parametri!$B$76,Parametri!$B$75*Parametri!$B$74*Parametri!$B$73/Parametri!$B$76,0) -> 0 | O8: =IF(B8<10,Parametri!$B$53,IF(B8<20,Parametri!$B$56,Parametri!$B$57))*M8*G8*Parametri!$B$72/1000 -> 2.5100966 | P8: =MIN(Parametri!$B$81+Parametri!$B$82, Parametri!$B$81+Parametri!$B$82*(B8+1)/Parametri!$B$83) -> 5.9 | Q8: =-IF(B8<10,Parametri!$B$51,IF(B8<20,Parametri!$B$54,Parametri!$B$57))*M8*G8/1000 -> -13.944981 | R8: =-Q8-Z8 -> 9.2966541 | S8: =S7+R8 -> 30.913353 | T8: =-(Parametri!$B$86*(Parametri!$B$87*Parametri!$B$90+Parametri!$B$88*Parametri!$B$91+Parametri!$B$89*Parametri!$B$92)/1000000000)*MIN(B8+1,Parametri!$B$93) -> -2.2878 | U8: =IF(B8<Parametri!$B$125,Parametri!$B$46,IF(B8<Parametri!$B$126,Parametri!$B$47,Parametri!$B$48))*Parametri!$B$96*13/1000000000*((B8+1)*Parametri!$B$121+B8*(B8+1)/2*Parametri!$B$122) -> 4.8140878 | V8: =IF(B8>=Parametri!$B$103-1,Parametri!$B$102*(1-Parametri!$B$127)^(B8-(Parametri!$B$103-1)),0) -> 5.7340298 | W8: =IF(B8>=Parametri!$B$105-1,Parametri!$B$104,0) -> 5 | X8: =IF(B8>=Parametri!$B$107-1,Parametri!$B$106+Parametri!$B$128*INT((B8-(Parametri!$B$107-1))/2),0) -> 2.89 | Y8: =IF(AND(B8>=Parametri!$B$109-1,B8<Parametri!$B$109-1+Parametri!$B$140),Parametri!$B$108,0) -> 0 | Z8: =IF(B8<10,Parametri!$B$52,IF(B8<20,Parametri!$B$55,0))*M8*G8/1000 -> 4.648327 | AA8: =Parametri!$B$159*Parametri!$B$160 -> 0 | AB8: =SUM(Z$5:Z8)+SUM(AA$5:AA8) -> 15.456677 | AC8: =-(Parametri!$B$67*SUM(Z$5:Z8)+Parametri!$B$161*SUM(AA$5:AA8)) -> -0.23185015 | AD8: =0 -> 0 | AE8: =Z8+AA8+N8+O8+P8+Q8+T8+U8+V8+W8+X8+Y8+AC8+AD8 -> 15.03191 | AF8: =AF7+AE8 -> 59.504013 | AG8: =-AF8/F8 -> -0.025971598 | AH8: =SUM(Z$5:Z8) -> 15.456677 | AI8: 0
A9: =Parametri!$B$6+B9 -> 2031 | B9: 4 | C9: =C8*(1+Parametri!$B$14) -> 22.840036 | D9: =D8*(1+Parametri!$B$15)+Parametri!$B$145*(1-Parametri!$B$15)^B8 -> 17.616628 | E9: =D9/C9 -> 0.77130473 | F9: =F8*(1+Parametri!$B$20) -> 2309.4476 | G9: =G8*(1+Parametri!$B$22) -> 26914.242 | H9: =F9*I9 -> 377.32821 | I9: =IF(B9<=(Parametri!$B$35-Parametri!$B$6),Parametri!$B$32+(Parametri!$B$33-Parametri!$B$32)*B9/(Parametri!$B$35-Parametri!$B$6),Parametri!$B$33+(Parametri!$B$34-Parametri!$B$33)*(B9-(Parametri!$B$35-Parametri!$B$6))/(Parametri!$B$36-Parametri!$B$35)) -> 0.16338462 | J9: =H9-AE9 -> 360.97416 | K9: =J9/F9 -> 0.15630325 | L9: =IF(B9<=5,Parametri!$B$58+(Parametri!$B$59-Parametri!$B$58)/5*B9,MIN(Parametri!$B$60,Parametri!$B$59+(Parametri!$B$60-Parametri!$B$59)/24*(B9-5))) -> 0.546 | M9: =L9*D9 -> 9.6186788 | N9: =IF(B9<Parametri!$B$76,Parametri!$B$75*Parametri!$B$74*Parametri!$B$73/Parametri!$B$76,0) -> 0 | O9: =IF(B9<10,Parametri!$B$53,IF(B9<20,Parametri!$B$56,Parametri!$B$57))*M9*G9*Parametri!$B$72/1000 -> 2.795898 | P9: =MIN(Parametri!$B$81+Parametri!$B$82, Parametri!$B$81+Parametri!$B$82*(B9+1)/Parametri!$B$83) -> 6.5 | Q9: =-IF(B9<10,Parametri!$B$51,IF(B9<20,Parametri!$B$54,Parametri!$B$57))*M9*G9/1000 -> -15.532767 | R9: =-Q9-Z9 -> 10.355178 | S9: =S8+R9 -> 41.268531 | T9: =-(Parametri!$B$86*(Parametri!$B$87*Parametri!$B$90+Parametri!$B$88*Parametri!$B$91+Parametri!$B$89*Parametri!$B$92)/1000000000)*MIN(B9+1,Parametri!$B$93) -> -2.85975 | U9: =IF(B9<Parametri!$B$125,Parametri!$B$46,IF(B9<Parametri!$B$126,Parametri!$B$47,Parametri!$B$48))*Parametri!$B$96*13/1000000000*((B9+1)*Parametri!$B$121+B9*(B9+1)/2*Parametri!$B$122) -> 7.04457 | V9: =IF(B9>=Parametri!$B$103-1,Parametri!$B$102*(1-Parametri!$B$127)^(B9-(Parametri!$B$103-1)),0) -> 5.6480193 | W9: =IF(B9>=Parametri!$B$105-1,Parametri!$B$104,0) -> 5 | X9: =IF(B9>=Parametri!$B$107-1,Parametri!$B$106+Parametri!$B$128*INT((B9-(Parametri!$B$107-1))/2),0) -> 2.89 | Y9: =IF(AND(B9>=Parametri!$B$109-1,B9<Parametri!$B$109-1+Parametri!$B$140),Parametri!$B$108,0) -> 0 | Z9: =IF(B9<10,Parametri!$B$52,IF(B9<20,Parametri!$B$55,0))*M9*G9/1000 -> 5.1775889 | AA9: =Parametri!$B$159*Parametri!$B$160 -> 0 | AB9: =SUM(Z$5:Z9)+SUM(AA$5:AA9) -> 20.634265 | AC9: =-(Parametri!$B$67*SUM(Z$5:Z9)+Parametri!$B$161*SUM(AA$5:AA9)) -> -0.30951398 | AD9: =0 -> 0 | AE9: =Z9+AA9+N9+O9+P9+Q9+T9+U9+V9+W9+X9+Y9+AC9+AD9 -> 16.354045 | AF9: =AF8+AE9 -> 75.858058 | AG9: =-AF9/F9 -> -0.032846841 | AH9: =SUM(Z$5:Z9) -> 20.634265 | AI9: 0
A10: =Parametri!$B$6+B10 -> 2032 | B10: 5 | C10: =C9*(1+Parametri!$B$14) -> 22.977076 | D10: =D9*(1+Parametri!$B$15)+Parametri!$B$145*(1-Parametri!$B$15)^B9 -> 17.646882 | E10: =D10/C10 -> 0.76802122 | F10: =F9*(1+Parametri!$B$20) -> 2327.9232 | G10: =G9*(1+Parametri!$B$22) -> 26968.07 | H10: =F10*I10 -> 382.31661 | I10: =IF(B10<=(Parametri!$B$35-Parametri!$B$6),Parametri!$B$32+(Parametri!$B$33-Parametri!$B$32)*B10/(Parametri!$B$35-Parametri!$B$6),Parametri!$B$33+(Parametri!$B$34-Parametri!$B$33)*(B10-(Parametri!$B$35-Parametri!$B$6))/(Parametri!$B$36-Parametri!$B$35)) -> 0.16423077 | J10: =H10-AE10 -> 364.18668 | K10: =J10/F10 -> 0.15644274 | L10: =IF(B10<=5,Parametri!$B$58+(Parametri!$B$59-Parametri!$B$58)/5*B10,MIN(Parametri!$B$60,Parametri!$B$59+(Parametri!$B$60-Parametri!$B$59)/24*(B10-5))) -> 0.6 | M10: =L10*D10 -> 10.588129 | N10: =IF(B10<Parametri!$B$76,Parametri!$B$75*Parametri!$B$74*Parametri!$B$73/Parametri!$B$76,0) -> 0 | O10: =IF(B10<10,Parametri!$B$53,IF(B10<20,Parametri!$B$56,Parametri!$B$57))*M10*G10*Parametri!$B$72/1000 -> 3.0838473 | P10: =MIN(Parametri!$B$81+Parametri!$B$82, Parametri!$B$81+Parametri!$B$82*(B10+1)/Parametri!$B$83) -> 7.1 | Q10: =-IF(B10<10,Parametri!$B$51,IF(B10<20,Parametri!$B$54,Parametri!$B$57))*M10*G10/1000 -> -17.132485 | R10: =-Q10-Z10 -> 11.421657 | S10: =S9+R10 -> 52.690187 | T10: =-(Parametri!$B$86*(Parametri!$B$87*Parametri!$B$90+Parametri!$B$88*Parametri!$B$91+Parametri!$B$89*Parametri!$B$92)/1000000000)*MIN(B10+1,Parametri!$B$93) -> -2.85975 | U10: =IF(B10<Parametri!$B$125,Parametri!$B$46,IF(B10<Parametri!$B$126,Parametri!$B$47,Parametri!$B$48))*Parametri!$B$96*13/1000000000*((B10+1)*Parametri!$B$121+B10*(B10+1)/2*Parametri!$B$122) -> 9.0293697 | V10: =IF(B10>=Parametri!$B$103-1,Parametri!$B$102*(1-Parametri!$B$127)^(B10-(Parametri!$B$103-1)),0) -> 5.563299 | W10: =IF(B10>=Parametri!$B$105-1,Parametri!$B$104,0) -> 5 | X10: =IF(B10>=Parametri!$B$107-1,Parametri!$B$106+Parametri!$B$128*INT((B10-(Parametri!$B$107-1))/2),0) -> 3.03 | Y10: =IF(AND(B10>=Parametri!$B$109-1,B10<Parametri!$B$109-1+Parametri!$B$140),Parametri!$B$108,0) -> 0 | Z10: =IF(B10<10,Parametri!$B$52,IF(B10<20,Parametri!$B$55,0))*M10*G10/1000 -> 5.7108283 | AA10: =Parametri!$B$159*Parametri!$B$160 -> 0 | AB10: =SUM(Z$5:Z10)+SUM(AA$5:AA10) -> 26.345094 | AC10: =-(Parametri!$B$67*SUM(Z$5:Z10)+Parametri!$B$161*SUM(AA$5:AA10)) -> -0.39517641 | AD10: =0 -> 0 | AE10: =Z10+AA10+N10+O10+P10+Q10+T10+U10+V10+W10+X10+Y10+AC10+AD10 -> 18.129933 | AF10: =AF9+AE10 -> 93.987991 | AG10: =-AF10/F10 -> -0.040374181 | AH10: =SUM(Z$5:Z10) -> 26.345094 | AI10: 0
A11: =Parametri!$B$6+B11 -> 2033 | B11: 6 | C11: =C10*(1+Parametri!$B$14) -> 23.114939 | D11: =D10*(1+Parametri!$B$15)+Parametri!$B$145*(1-Parametri!$B$15)^B10 -> 17.677577 | E11: =D11/C11 -> 0.76476849 | F11: =F10*(1+Parametri!$B$20) -> 2346.5466 | G11: =G10*(1+Parametri!$B$22) -> 27022.006 | H11: =F11*I11 -> 387.36069 | I11: =IF(B11<=(Parametri!$B$35-Parametri!$B$6),Parametri!$B$32+(Parametri!$B$33-Parametri!$B$32)*B11/(Parametri!$B$35-Parametri!$B$6),Parametri!$B$33+(Parametri!$B$34-Parametri!$B$33)*(B11-(Parametri!$B$35-Parametri!$B$6))/(Parametri!$B$36-Parametri!$B$35)) -> 0.16507692 | J11: =H11-AE11 -> 366.88949 | K11: =J11/F11 -> 0.15635296 | L11: =IF(B11<=5,Parametri!$B$58+(Parametri!$B$59-Parametri!$B$58)/5*B11,MIN(Parametri!$B$60,Parametri!$B$59+(Parametri!$B$60-Parametri!$B$59)/24*(B11-5))) -> 0.61666667 | M11: =L11*D11 -> 10.901172 | N11: =IF(B11<Parametri!$B$76,Parametri!$B$75*Parametri!$B$74*Parametri!$B$73/Parametri!$B$76,0) -> 0 | O11: =IF(B11<10,Parametri!$B$53,IF(B11<20,Parametri!$B$56,Parametri!$B$57))*M11*G11*Parametri!$B$72/1000 -> 3.1813727 | P11: =MIN(Parametri!$B$81+Parametri!$B$82, Parametri!$B$81+Parametri!$B$82*(B11+1)/Parametri!$B$83) -> 7.7 | Q11: =-IF(B11<10,Parametri!$B$51,IF(B11<20,Parametri!$B$54,Parametri!$B$57))*M11*G11/1000 -> -17.674293 | R11: =-Q11-Z11 -> 11.782862 | S11: =S10+R11 -> 64.473049 | T11: =-(Parametri!$B$86*(Parametri!$B$87*Parametri!$B$90+Parametri!$B$88*Parametri!$B$91+Parametri!$B$89*Parametri!$B$92)/1000000000)*MIN(B11+1,Parametri!$B$93) -> -2.85975 | U11: =IF(B11<Parametri!$B$125,Parametri!$B$46,IF(B11<Parametri!$B$126,Parametri!$B$47,Parametri!$B$48))*Parametri!$B$96*13/1000000000*((B11+1)*Parametri!$B$121+B11*(B11+1)/2*Parametri!$B$122) -> 11.206131 | V11: =IF(B11>=Parametri!$B$103-1,Parametri!$B$102*(1-Parametri!$B$127)^(B11-(Parametri!$B$103-1)),0) -> 5.4798495 | W11: =IF(B11>=Parametri!$B$105-1,Parametri!$B$104,0) -> 5 | X11: =IF(B11>=Parametri!$B$107-1,Parametri!$B$106+Parametri!$B$128*INT((B11-(Parametri!$B$107-1))/2),0) -> 3.03 | Y11: =IF(AND(B11>=Parametri!$B$109-1,B11<Parametri!$B$109-1+Parametri!$B$140),Parametri!$B$108,0) -> 0 | Z11: =IF(B11<10,Parametri!$B$52,IF(B11<20,Parametri!$B$55,0))*M11*G11/1000 -> 5.891431 | AA11: =Parametri!$B$159*Parametri!$B$160 -> 0 | AB11: =SUM(Z$5:Z11)+SUM(AA$5:AA11) -> 32.236525 | AC11: =-(Parametri!$B$67*SUM(Z$5:Z11)+Parametri!$B$161*SUM(AA$5:AA11)) -> -0.48354787 | AD11: =0 -> 0 | AE11: =Z11+AA11+N11+O11+P11+Q11+T11+U11+V11+W11+X11+Y11+AC11+AD11 -> 20.471194 | AF11: =AF10+AE11 -> 114.45918 | AG11: =-AF11/F11 -> -0.048777717 | AH11: =SUM(Z$5:Z11) -> 32.236525 | AI11: 0
A12: =Parametri!$B$6+B12 -> 2034 | B12: 7 | C12: =C11*(1+Parametri!$B$14) -> 23.253628 | D12: =D11*(1+Parametri!$B$15)+Parametri!$B$145*(1-Parametri!$B$15)^B11 -> 17.708713 | E12: =D12/C12 -> 0.76154622 | F12: =F11*(1+Parametri!$B$20) -> 2365.3189 | G12: =G11*(1+Parametri!$B$22) -> 27076.05 | H12: =F12*I12 -> 392.461 | I12: =IF(B12<=(Parametri!$B$35-Parametri!$B$6),Parametri!$B$32+(Parametri!$B$33-Parametri!$B$32)*B12/(Parametri!$B$35-Parametri!$B$6),Parametri!$B$33+(Parametri!$B$34-Parametri!$B$33)*(B12-(Parametri!$B$35-Parametri!$B$6))/(Parametri!$B$36-Parametri!$B$35)) -> 0.16592308 | J12: =H12-AE12 -> 369.32011 | K12: =J12/F12 -> 0.15613967 | L12: =IF(B12<=5,Parametri!$B$58+(Parametri!$B$59-Parametri!$B$58)/5*B12,MIN(Parametri!$B$60,Parametri!$B$59+(Parametri!$B$60-Parametri!$B$59)/24*(B12-5))) -> 0.63333333 | M12: =L12*D12 -> 11.215518 | N12: =IF(B12<Parametri!$B$76,Parametri!$B$75*Parametri!$B$74*Parametri!$B$73/Parametri!$B$76,0) -> 0 | O12: =IF(B12<10,Parametri!$B$53,IF(B12<20,Parametri!$B$56,Parametri!$B$57))*M12*G12*Parametri!$B$72/1000 -> 3.2796569 | P12: =MIN(Parametri!$B$81+Parametri!$B$82, Parametri!$B$81+Parametri!$B$82*(B12+1)/Parametri!$B$83) -> 8.3 | Q12: =-IF(B12<10,Parametri!$B$51,IF(B12<20,Parametri!$B$54,Parametri!$B$57))*M12*G12/1000 -> -18.220316 | R12: =-Q12-Z12 -> 12.146877 | S12: =S11+R12 -> 76.619927 | T12: =-(Parametri!$B$86*(Parametri!$B$87*Parametri!$B$90+Parametri!$B$88*Parametri!$B$91+Parametri!$B$89*Parametri!$B$92)/1000000000)*MIN(B12+1,Parametri!$B$93) -> -2.85975 | U12: =IF(B12<Parametri!$B$125,Parametri!$B$46,IF(B12<Parametri!$B$126,Parametri!$B$47,Parametri!$B$48))*Parametri!$B$96*13/1000000000*((B12+1)*Parametri!$B$121+B12*(B12+1)/2*Parametri!$B$122) -> 13.574855 | V12: =IF(B12>=Parametri!$B$103-1,Parametri!$B$102*(1-Parametri!$B$127)^(B12-(Parametri!$B$103-1)),0) -> 5.3976518 | W12: =IF(B12>=Parametri!$B$105-1,Parametri!$B$104,0) -> 5 | X12: =IF(B12>=Parametri!$B$107-1,Parametri!$B$106+Parametri!$B$128*INT((B12-(Parametri!$B$107-1))/2),0) -> 3.17 | Y12: =IF(AND(B12>=Parametri!$B$109-1,B12<Parametri!$B$109-1+Parametri!$B$140),Parametri!$B$108,0) -> 0 | Z12: =IF(B12<10,Parametri!$B$52,IF(B12<20,Parametri!$B$55,0))*M12*G12/1000 -> 6.0734387 | AA12: =Parametri!$B$159*Parametri!$B$160 -> 0 | AB12: =SUM(Z$5:Z12)+SUM(AA$5:AA12) -> 38.309963 | AC12: =-(Parametri!$B$67*SUM(Z$5:Z12)+Parametri!$B$161*SUM(AA$5:AA12)) -> -0.57464945 | AD12: =0 -> 0 | AE12: =Z12+AA12+N12+O12+P12+Q12+T12+U12+V12+W12+X12+Y12+AC12+AD12 -> 23.140887 | AF12: =AF11+AE12 -> 137.60007 | AG12: =-AF12/F12 -> -0.058174003 | AH12: =SUM(Z$5:Z12) -> 38.309963 | AI12: 0
A13: =Parametri!$B$6+B13 -> 2035 | B13: 8 | C13: =C12*(1+Parametri!$B$14) -> 23.39315 | D13: =D12*(1+Parametri!$B$15)+Parametri!$B$145*(1-Parametri!$B$15)^B12 -> 17.740291 | E13: =D13/C13 -> 0.75835407 | F13: =F12*(1+Parametri!$B$20) -> 2384.2415 | G13: =G12*(1+Parametri!$B$22) -> 27130.202 | H13: =F13*I13 -> 397.61812 | I13: =IF(B13<=(Parametri!$B$35-Parametri!$B$6),Parametri!$B$32+(Parametri!$B$33-Parametri!$B$32)*B13/(Parametri!$B$35-Parametri!$B$6),Parametri!$B$33+(Parametri!$B$34-Parametri!$B$33)*(B13-(Parametri!$B$35-Parametri!$B$6))/(Parametri!$B$36-Parametri!$B$35)) -> 0.16676923 | J13: =H13-AE13 -> 371.75917 | K13: =J13/F13 -> 0.15592346 | L13: =IF(B13<=5,Parametri!$B$58+(Parametri!$B$59-Parametri!$B$58)/5*B13,MIN(Parametri!$B$60,Parametri!$B$59+(Parametri!$B$60-Parametri!$B$59)/24*(B13-5))) -> 0.65 | M13: =L13*D13 -> 11.531189 | N13: =IF(B13<Parametri!$B$76,Parametri!$B$75*Parametri!$B$74*Parametri!$B$73/Parametri!$B$76,0) -> 0 | O13: =IF(B13<10,Parametri!$B$53,IF(B13<20,Parametri!$B$56,Parametri!$B$57))*M13*G13*Parametri!$B$72/1000 -> 3.3787097 | P13: =MIN(Parametri!$B$81+Parametri!$B$82, Parametri!$B$81+Parametri!$B$82*(B13+1)/Parametri!$B$83) -> 8.9 | Q13: =-IF(B13<10,Parametri!$B$51,IF(B13<20,Parametri!$B$54,Parametri!$B$57))*M13*G13/1000 -> -18.770609 | R13: =-Q13-Z13 -> 12.51374 | S13: =S12+R13 -> 89.133666 | T13: =-(Parametri!$B$86*(Parametri!$B$87*Parametri!$B$90+Parametri!$B$88*Parametri!$B$91+Parametri!$B$89*Parametri!$B$92)/1000000000)*MIN(B13+1,Parametri!$B$93) -> -2.85975 | U13: =IF(B13<Parametri!$B$125,Parametri!$B$46,IF(B13<Parametri!$B$126,Parametri!$B$47,Parametri!$B$48))*Parametri!$B$96*13/1000000000*((B13+1)*Parametri!$B$121+B13*(B13+1)/2*Parametri!$B$122) -> 16.13554 | V13: =IF(B13>=Parametri!$B$103-1,Parametri!$B$102*(1-Parametri!$B$127)^(B13-(Parametri!$B$103-1)),0) -> 5.316687 | W13: =IF(B13>=Parametri!$B$105-1,Parametri!$B$104,0) -> 5 | X13: =IF(B13>=Parametri!$B$107-1,Parametri!$B$106+Parametri!$B$128*INT((B13-(Parametri!$B$107-1))/2),0) -> 3.17 | Y13: =IF(AND(B13>=Parametri!$B$109-1,B13<Parametri!$B$109-1+Parametri!$B$140),Parametri!$B$108,0) -> 0 | Z13: =IF(B13<10,Parametri!$B$52,IF(B13<20,Parametri!$B$55,0))*M13*G13/1000 -> 6.2568698 | AA13: =Parametri!$B$159*Parametri!$B$160 -> 0 | AB13: =SUM(Z$5:Z13)+SUM(AA$5:AA13) -> 44.566833 | AC13: =-(Parametri!$B$67*SUM(Z$5:Z13)+Parametri!$B$161*SUM(AA$5:AA13)) -> -0.6685025 | AD13: =0 -> 0 | AE13: =Z13+AA13+N13+O13+P13+Q13+T13+U13+V13+W13+X13+Y13+AC13+AD13 -> 25.858945 | AF13: =AF12+AE13 -> 163.45902 | AG13: =-AF13/F13 -> -0.068558079 | AH13: =SUM(Z$5:Z13) -> 44.566833 | AI13: 0
A14: =Parametri!$B$6+B14 -> 2036 | B14: 9 | C14: =C13*(1+Parametri!$B$14) -> 23.533509 | D14: =D13*(1+Parametri!$B$15)+Parametri!$B$145*(1-Parametri!$B$15)^B13 -> 17.772311 | E14: =D14/C14 -> 0.75519172 | F14: =F13*(1+Parametri!$B$20) -> 2403.3154 | G14: =G13*(1+Parametri!$B$22) -> 27184.463 | H14: =F14*I14 -> 402.83264 | I14: =IF(B14<=(Parametri!$B$35-Parametri!$B$6),Parametri!$B$32+(Parametri!$B$33-Parametri!$B$32)*B14/(Parametri!$B$35-Parametri!$B$6),Parametri!$B$33+(Parametri!$B$34-Parametri!$B$33)*(B14-(Parametri!$B$35-Parametri!$B$6))/(Parametri!$B$36-Parametri!$B$35)) -> 0.16761538 | J14: =H14-AE14 -> 373.92734 | K14: =J14/F14 -> 0.15558812 | L14: =IF(B14<=5,Parametri!$B$58+(Parametri!$B$59-Parametri!$B$58)/5*B14,MIN(Parametri!$B$60,Parametri!$B$59+(Parametri!$B$60-Parametri!$B$59)/24*(B14-5))) -> 0.66666667 | M14: =L14*D14 -> 11.848207 | N14: =IF(B14<Parametri!$B$76,Parametri!$B$75*Parametri!$B$74*Parametri!$B$73/Parametri!$B$76,0) -> 0 | O14: =IF(B14<10,Parametri!$B$53,IF(B14<20,Parametri!$B$56,Parametri!$B$57))*M14*G14*Parametri!$B$72/1000 -> 3.4785413 | P14: =MIN(Parametri!$B$81+Parametri!$B$82, Parametri!$B$81+Parametri!$B$82*(B14+1)/Parametri!$B$83) -> 9.5 | Q14: =-IF(B14<10,Parametri!$B$51,IF(B14<20,Parametri!$B$54,Parametri!$B$57))*M14*G14/1000 -> -19.325229 | R14: =-Q14-Z14 -> 12.883486 | S14: =S13+R14 -> 102.01715 | T14: =-(Parametri!$B$86*(Parametri!$B$87*Parametri!$B$90+Parametri!$B$88*Parametri!$B$91+Parametri!$B$89*Parametri!$B$92)/1000000000)*MIN(B14+1,Parametri!$B$93) -> -2.85975 | U14: =IF(B14<Parametri!$B$125,Parametri!$B$46,IF(B14<Parametri!$B$126,Parametri!$B$47,Parametri!$B$48))*Parametri!$B$96*13/1000000000*((B14+1)*Parametri!$B$121+B14*(B14+1)/2*Parametri!$B$122) -> 18.888187 | V14: =IF(B14>=Parametri!$B$103-1,Parametri!$B$102*(1-Parametri!$B$127)^(B14-(Parametri!$B$103-1)),0) -> 5.2369367 | W14: =IF(B14>=Parametri!$B$105-1,Parametri!$B$104,0) -> 5 | X14: =IF(B14>=Parametri!$B$107-1,Parametri!$B$106+Parametri!$B$128*INT((B14-(Parametri!$B$107-1))/2),0) -> 3.31 | Y14: =IF(AND(B14>=Parametri!$B$109-1,B14<Parametri!$B$109-1+Parametri!$B$140),Parametri!$B$108,0) -> 0 | Z14: =IF(B14<10,Parametri!$B$52,IF(B14<20,Parametri!$B$55,0))*M14*G14/1000 -> 6.4417431 | AA14: =Parametri!$B$159*Parametri!$B$160 -> 0 | AB14: =SUM(Z$5:Z14)+SUM(AA$5:AA14) -> 51.008576 | AC14: =-(Parametri!$B$67*SUM(Z$5:Z14)+Parametri!$B$161*SUM(AA$5:AA14)) -> -0.76512864 | AD14: =0 -> 0 | AE14: =Z14+AA14+N14+O14+P14+Q14+T14+U14+V14+W14+X14+Y14+AC14+AD14 -> 28.905301 | AF14: =AF13+AE14 -> 192.36432 | AG14: =-AF14/F14 -> -0.080041228 | AH14: =SUM(Z$5:Z14) -> 51.008576 | AI14: 0
A15: =Parametri!$B$6+B15 -> 2037 | B15: 10 | C15: =C14*(1+Parametri!$B$14) -> 23.67471 | D15: =D14*(1+Parametri!$B$15)+Parametri!$B$145*(1-Parametri!$B$15)^B14 -> 17.804775 | E15: =D15/C15 -> 0.75205885 | F15: =F14*(1+Parametri!$B$20) -> 2422.5419 | G15: =G14*(1+Parametri!$B$22) -> 27238.832 | H15: =F15*I15 -> 408.10514 | I15: =IF(B15<=(Parametri!$B$35-Parametri!$B$6),Parametri!$B$32+(Parametri!$B$33-Parametri!$B$32)*B15/(Parametri!$B$35-Parametri!$B$6),Parametri!$B$33+(Parametri!$B$34-Parametri!$B$33)*(B15-(Parametri!$B$35-Parametri!$B$6))/(Parametri!$B$36-Parametri!$B$35)) -> 0.16846154 | J15: =H15-AE15 -> 380.94375 | K15: =J15/F15 -> 0.1572496 | L15: =IF(B15<=5,Parametri!$B$58+(Parametri!$B$59-Parametri!$B$58)/5*B15,MIN(Parametri!$B$60,Parametri!$B$59+(Parametri!$B$60-Parametri!$B$59)/24*(B15-5))) -> 0.68333333 | M15: =L15*D15 -> 12.166596 | N15: =IF(B15<Parametri!$B$76,Parametri!$B$75*Parametri!$B$74*Parametri!$B$73/Parametri!$B$76,0) -> 0 | O15: =IF(B15<10,Parametri!$B$53,IF(B15<20,Parametri!$B$56,Parametri!$B$57))*M15*G15*Parametri!$B$72/1000 -> 5.3687428 | P15: =MIN(Parametri!$B$81+Parametri!$B$82, Parametri!$B$81+Parametri!$B$82*(B15+1)/Parametri!$B$83) -> 10.1 | Q15: =-IF(B15<10,Parametri!$B$51,IF(B15<20,Parametri!$B$54,Parametri!$B$57))*M15*G15/1000 -> -26.51231 | R15: =-Q15-Z15 -> 19.884232 | S15: =S14+R15 -> 121.90139 | T15: =-(Parametri!$B$86*(Parametri!$B$87*Parametri!$B$90+Parametri!$B$88*Parametri!$B$91+Parametri!$B$89*Parametri!$B$92)/1000000000)*MIN(B15+1,Parametri!$B$93) -> -2.85975 | U15: =IF(B15<Parametri!$B$125,Parametri!$B$46,IF(B15<Parametri!$B$126,Parametri!$B$47,Parametri!$B$48))*Parametri!$B$96*13/1000000000*((B15+1)*Parametri!$B$121+B15*(B15+1)/2*Parametri!$B$122) -> 21.832797 | V15: =IF(B15>=Parametri!$B$103-1,Parametri!$B$102*(1-Parametri!$B$127)^(B15-(Parametri!$B$103-1)),0) -> 5.1583827 | W15: =IF(B15>=Parametri!$B$105-1,Parametri!$B$104,0) -> 5 | X15: =IF(B15>=Parametri!$B$107-1,Parametri!$B$106+Parametri!$B$128*INT((B15-(Parametri!$B$107-1))/2),0) -> 3.31 | Y15: =IF(AND(B15>=Parametri!$B$109-1,B15<Parametri!$B$109-1+Parametri!$B$140),Parametri!$B$108,0) -> 0 | Z15: =IF(B15<10,Parametri!$B$52,IF(B15<20,Parametri!$B$55,0))*M15*G15/1000 -> 6.6280775 | AA15: =Parametri!$B$159*Parametri!$B$160 -> 0 | AB15: =SUM(Z$5:Z15)+SUM(AA$5:AA15) -> 57.636654 | AC15: =-(Parametri!$B$67*SUM(Z$5:Z15)+Parametri!$B$161*SUM(AA$5:AA15)) -> -0.86454981 | AD15: =0 -> 0 | AE15: =Z15+AA15+N15+O15+P15+Q15+T15+U15+V15+W15+X15+Y15+AC15+AD15 -> 27.16139 | AF15: =AF14+AE15 -> 219.52571 | AG15: =-AF15/F15 -> -0.090617918 | AH15: =SUM(Z$5:Z15) -> 57.636654 | AI15: 0
A16: =Parametri!$B$6+B16 -> 2038 | B16: 11 | C16: =C15*(1+Parametri!$B$14) -> 23.816758 | D16: =D15*(1+Parametri!$B$15)+Parametri!$B$145*(1-Parametri!$B$15)^B15 -> 17.837684 | E16: =D16/C16 -> 0.74895514 | F16: =F15*(1+Parametri!$B$20) -> 2441.9223 | G16: =G15*(1+Parametri!$B$22) -> 27293.309 | H16: =F16*I16 -> 413.43623 | I16: =IF(B16<=(Parametri!$B$35-Parametri!$B$6),Parametri!$B$32+(Parametri!$B$33-Parametri!$B$32)*B16/(Parametri!$B$35-Parametri!$B$6),Parametri!$B$33+(Parametri!$B$34-Parametri!$B$33)*(B16-(Parametri!$B$35-Parametri!$B$6))/(Parametri!$B$36-Parametri!$B$35)) -> 0.16930769 | J16: =H16-AE16 -> 387.98307 | K16: =J16/F16 -> 0.15888428 | L16: =IF(B16<=5,Parametri!$B$58+(Parametri!$B$59-Parametri!$B$58)/5*B16,MIN(Parametri!$B$60,Parametri!$B$59+(Parametri!$B$60-Parametri!$B$59)/24*(B16-5))) -> 0.7 | M16: =L16*D16 -> 12.486379 | N16: =IF(B16<Parametri!$B$76,Parametri!$B$75*Parametri!$B$74*Parametri!$B$73/Parametri!$B$76,0) -> 0 | O16: =IF(B16<10,Parametri!$B$53,IF(B16<20,Parametri!$B$56,Parametri!$B$57))*M16*G16*Parametri!$B$72/1000 -> 5.5208724 | P16: =MIN(Parametri!$B$81+Parametri!$B$82, Parametri!$B$81+Parametri!$B$82*(B16+1)/Parametri!$B$83) -> 10.7 | Q16: =-IF(B16<10,Parametri!$B$51,IF(B16<20,Parametri!$B$54,Parametri!$B$57))*M16*G16/1000 -> -27.263567 | R16: =-Q16-Z16 -> 20.447676 | S16: =S15+R16 -> 142.34906 | T16: =-(Parametri!$B$86*(Parametri!$B$87*Parametri!$B$90+Parametri!$B$88*Parametri!$B$91+Parametri!$B$89*Parametri!$B$92)/1000000000)*MIN(B16+1,Parametri!$B$93) -> -2.85975 | U16: =IF(B16<Parametri!$B$125,Parametri!$B$46,IF(B16<Parametri!$B$126,Parametri!$B$47,Parametri!$B$48))*Parametri!$B$96*13/1000000000*((B16+1)*Parametri!$B$121+B16*(B16+1)/2*Parametri!$B$122) -> 19.975494 | V16: =IF(B16>=Parametri!$B$103-1,Parametri!$B$102*(1-Parametri!$B$127)^(B16-(Parametri!$B$103-1)),0) -> 5.0810069 | W16: =IF(B16>=Parametri!$B$105-1,Parametri!$B$104,0) -> 5 | X16: =IF(B16>=Parametri!$B$107-1,Parametri!$B$106+Parametri!$B$128*INT((B16-(Parametri!$B$107-1))/2),0) -> 3.45 | Y16: =IF(AND(B16>=Parametri!$B$109-1,B16<Parametri!$B$109-1+Parametri!$B$140),Parametri!$B$108,0) -> 0 | Z16: =IF(B16<10,Parametri!$B$52,IF(B16<20,Parametri!$B$55,0))*M16*G16/1000 -> 6.8158919 | AA16: =Parametri!$B$159*Parametri!$B$160 -> 0 | AB16: =SUM(Z$5:Z16)+SUM(AA$5:AA16) -> 64.452546 | AC16: =-(Parametri!$B$67*SUM(Z$5:Z16)+Parametri!$B$161*SUM(AA$5:AA16)) -> -0.96678818 | AD16: =0 -> 0 | AE16: =Z16+AA16+N16+O16+P16+Q16+T16+U16+V16+W16+X16+Y16+AC16+AD16 -> 25.45316 | AF16: =AF15+AE16 -> 244.97887 | AG16: =-AF16/F16 -> -0.10032214 | AH16: =SUM(Z$5:Z16) -> 64.452546 | AI16: 0
A17: =Parametri!$B$6+B17 -> 2039 | B17: 12 | C17: =C16*(1+Parametri!$B$14) -> 23.959659 | D17: =D16*(1+Parametri!$B$15)+Parametri!$B$145*(1-Parametri!$B$15)^B16 -> 17.871037 | E17: =D17/C17 -> 0.74588028 | F17: =F16*(1+Parametri!$B$20) -> 2461.4577 | G17: =G16*(1+Parametri!$B$22) -> 27347.896 | H17: =F17*I17 -> 418.82649 | I17: =IF(B17<=(Parametri!$B$35-Parametri!$B$6),Parametri!$B$32+(Parametri!$B$33-Parametri!$B$32)*B17/(Parametri!$B$35-Parametri!$B$6),Parametri!$B$33+(Parametri!$B$34-Parametri!$B$33)*(B17-(Parametri!$B$35-Parametri!$B$6))/(Parametri!$B$36-Parametri!$B$35)) -> 0.17015385 | J17: =H17-AE17 -> 390.70639 | K17: =J17/F17 -> 0.15872968 | L17: =IF(B17<=5,Parametri!$B$58+(Parametri!$B$59-Parametri!$B$58)/5*B17,MIN(Parametri!$B$60,Parametri!$B$59+(Parametri!$B$60-Parametri!$B$59)/24*(B17-5))) -> 0.71666667 | M17: =L17*D17 -> 12.807577 | N17: =IF(B17<Parametri!$B$76,Parametri!$B$75*Parametri!$B$74*Parametri!$B$73/Parametri!$B$76,0) -> 0 | O17: =IF(B17<10,Parametri!$B$53,IF(B17<20,Parametri!$B$56,Parametri!$B$57))*M17*G17*Parametri!$B$72/1000 -> 5.6742164 | P17: =MIN(Parametri!$B$81+Parametri!$B$82, Parametri!$B$81+Parametri!$B$82*(B17+1)/Parametri!$B$83) -> 11.3 | Q17: =-IF(B17<10,Parametri!$B$51,IF(B17<20,Parametri!$B$54,Parametri!$B$57))*M17*G17/1000 -> -28.020822 | R17: =-Q17-Z17 -> 21.015616 | S17: =S16+R17 -> 163.36468 | T17: =-(Parametri!$B$86*(Parametri!$B$87*Parametri!$B$90+Parametri!$B$88*Parametri!$B$91+Parametri!$B$89*Parametri!$B$92)/1000000000)*MIN(B17+1,Parametri!$B$93) -> -2.85975 | U17: =IF(B17<Parametri!$B$125,Parametri!$B$46,IF(B17<Parametri!$B$126,Parametri!$B$47,Parametri!$B$48))*Parametri!$B$96*13/1000000000*((B17+1)*Parametri!$B$121+B17*(B17+1)/2*Parametri!$B$122) -> 22.638321 | V17: =IF(B17>=Parametri!$B$103-1,Parametri!$B$102*(1-Parametri!$B$127)^(B17-(Parametri!$B$103-1)),0) -> 5.0047918 | W17: =IF(B17>=Parametri!$B$105-1,Parametri!$B$104,0) -> 5 | X17: =IF(B17>=Parametri!$B$107-1,Parametri!$B$106+Parametri!$B$128*INT((B17-(Parametri!$B$107-1))/2),0) -> 3.45 | Y17: =IF(AND(B17>=Parametri!$B$109-1,B17<Parametri!$B$109-1+Parametri!$B$140),Parametri!$B$108,0) -> 0 | Z17: =IF(B17<10,Parametri!$B$52,IF(B17<20,Parametri!$B$55,0))*M17*G17/1000 -> 7.0052055 | AA17: =Parametri!$B$159*Parametri!$B$160 -> 0 | AB17: =SUM(Z$5:Z17)+SUM(AA$5:AA17) -> 71.457751 | AC17: =-(Parametri!$B$67*SUM(Z$5:Z17)+Parametri!$B$161*SUM(AA$5:AA17)) -> -1.0718663 | AD17: =0 -> 0 | AE17: =Z17+AA17+N17+O17+P17+Q17+T17+U17+V17+W17+X17+Y17+AC17+AD17 -> 28.120096 | AF17: =AF16+AE17 -> 273.09896 | AG17: =-AF17/F17 -> -0.1109501 | AH17: =SUM(Z$5:Z17) -> 71.457751 | AI17: 0
... A19: =Parametri!$B$6+B19 -> 2041 | B19: 14 | C19: =C18*(1+Parametri!$B$14) -> 24.248037 | D19: =D18*(1+Parametri!$B$15)+Parametri!$B$145*(1-Parametri!$B$15)^B18 -> 17.939083 | E19: =D19/C19 -> 0.73981587 | F19: =F18*(1+Parametri!$B$20) -> 2500.9985 | G19: =G18*(1+Parametri!$B$22) -> 27457.397 | H19: =F19*I19 -> 423.91925 | I19: =IF(B19<=(Parametri!$B$35-Parametri!$B$6),Parametri!$B$32+(Parametri!$B$33-Parametri!$B$32)*B19/(Parametri!$B$35-Parametri!$B$6),Parametri!$B$33+(Parametri!$B$34-Parametri!$B$33)*(B19-(Parametri!$B$35-Parametri!$B$6))/(Parametri!$B$36-Parametri!$B$35)) -> 0.1695 | J19: =H19-AE19 -> 389.87979 | K19: =J19/F19 -> 0.15588965 | L19: =IF(B19<=5,Parametri!$B$58+(Parametri!$B$59-Parametri!$B$58)/5*B19,MIN(Parametri!$B$60,Parametri!$B$59+(Parametri!$B$60-Parametri!$B$59)/24*(B19-5))) -> 0.75 | M19: =L19*D19 -> 13.454312 | N19: =IF(B19<Parametri!$B$76,Parametri!$B$75*Parametri!$B$74*Parametri!$B$73/Parametri!$B$76,0) -> 0 | O19: =IF(B19<10,Parametri!$B$53,IF(B19<20,Parametri!$B$56,Parametri!$B$57))*M19*G19*Parametri!$B$72/1000 -> 5.9846103 | P19: =MIN(Parametri!$B$81+Parametri!$B$82, Parametri!$B$81+Parametri!$B$82*(B19+1)/Parametri!$B$83) -> 12.5 | Q19: =-IF(B19<10,Parametri!$B$51,IF(B19<20,Parametri!$B$54,Parametri!$B$57))*M19*G19/1000 -> -29.553631 | R19: =-Q19-Z19 -> 22.165223 | S19: =S18+R19 -> 207.11801 | T19: =-(Parametri!$B$86*(Parametri!$B$87*Parametri!$B$90+Parametri!$B$88*Parametri!$B$91+Parametri!$B$89*Parametri!$B$92)/1000000000)*MIN(B19+1,Parametri!$B$93) -> -2.85975 | U19: =IF(B19<Parametri!$B$125,Parametri!$B$46,IF(B19<Parametri!$B$126,Parametri!$B$47,Parametri!$B$48))*Parametri!$B$96*13/1000000000*((B19+1)*Parametri!$B$121+B19*(B19+1)/2*Parametri!$B$122) -> 28.424682 | V19: =IF(B19>=Parametri!$B$103-1,Parametri!$B$102*(1-Parametri!$B$127)^(B19-(Parametri!$B$103-1)),0) -> 4.8557741 | W19: =IF(B19>=Parametri!$B$105-1,Parametri!$B$104,0) -> 5 | X19: =IF(B19>=Parametri!$B$107-1,Parametri!$B$106+Parametri!$B$128*INT((B19-(Parametri!$B$107-1))/2),0) -> 3.59 | Y19: =IF(AND(B19>=Parametri!$B$109-1,B19<Parametri!$B$109-1+Parametri!$B$140),Parametri!$B$108,0) -> 0 | Z19: =IF(B19<10,Parametri!$B$52,IF(B19<20,Parametri!$B$55,0))*M19*G19/1000 -> 7.3884078 | AA19: =Parametri!$B$159*Parametri!$B$160 -> 0 | AB19: =SUM(Z$5:Z19)+SUM(AA$5:AA19) -> 86.042197 | AC19: =-(Parametri!$B$67*SUM(Z$5:Z19)+Parametri!$B$161*SUM(AA$5:AA19)) -> -1.2906329 | AD19: =0 -> 0 | AE19: =Z19+AA19+N19+O19+P19+Q19+T19+U19+V19+W19+X19+Y19+AC19+AD19 -> 34.03946 | AF19: =AF18+AE19 -> 338.21398 | AG19: =-AF19/F19 -> -0.13523158 | AH19: =SUM(Z$5:Z19) -> 86.042197 | AI19: 0
A20: =Parametri!$B$6+B20 -> 2042 | B20: 15 | C20: =C19*(1+Parametri!$B$14) -> 24.393526 | D20: =D19*(1+Parametri!$B$15)+Parametri!$B$145*(1-Parametri!$B$15)^B19 -> 17.973777 | E20: =D20/C20 -> 0.7368257 | F20: =F19*(1+Parametri!$B$20) -> 2521.0065 | G20: =G19*(1+Parametri!$B$22) -> 27512.312 | H20: =F20*I20 -> 423.52909 | I20: =IF(B20<=(Parametri!$B$35-Parametri!$B$6),Parametri!$B$32+(Parametri!$B$33-Parametri!$B$32)*B20/(Parametri!$B$35-Parametri!$B$6),Parametri!$B$33+(Parametri!$B$34-Parametri!$B$33)*(B20-(Parametri!$B$35-Parametri!$B$6))/(Parametri!$B$36-Parametri!$B$35)) -> 0.168 | J20: =H20-AE20 -> 389.92122 | K20: =J20/F20 -> 0.15466887 | L20: =IF(B20<=5,Parametri!$B$58+(Parametri!$B$59-Parametri!$B$58)/5*B20,MIN(Parametri!$B$60,Parametri!$B$59+(Parametri!$B$60-Parametri!$B$59)/24*(B20-5))) -> 0.76666667 | M20: =L20*D20 -> 13.779895 | N20: =IF(B20<Parametri!$B$76,Parametri!$B$75*Parametri!$B$74*Parametri!$B$73/Parametri!$B$76,0) -> 0 | O20: =IF(B20<10,Parametri!$B$53,IF(B20<20,Parametri!$B$56,Parametri!$B$57))*M20*G20*Parametri!$B$72/1000 -> 6.1416918 | P20: =MIN(Parametri!$B$81+Parametri!$B$82, Parametri!$B$81+Parametri!$B$82*(B20+1)/Parametri!$B$83) -> 12.5 | Q20: =-IF(B20<10,Parametri!$B$51,IF(B20<20,Parametri!$B$54,Parametri!$B$57))*M20*G20/1000 -> -30.329342 | R20: =-Q20-Z20 -> 22.747007 | S20: =S19+R20 -> 229.86502 | T20: =-(Parametri!$B$86*(Parametri!$B$87*Parametri!$B$90+Parametri!$B$88*Parametri!$B$91+Parametri!$B$89*Parametri!$B$92)/1000000000)*MIN(B20+1,Parametri!$B$93) -> -2.85975 | U20: =IF(B20<Parametri!$B$125,Parametri!$B$46,IF(B20<Parametri!$B$126,Parametri!$B$47,Parametri!$B$48))*Parametri!$B$96*13/1000000000*((B20+1)*Parametri!$B$121+B20*(B20+1)/2*Parametri!$B$122) -> 31.548217 | V20: =IF(B20>=Parametri!$B$103-1,Parametri!$B$102*(1-Parametri!$B$127)^(B20-(Parametri!$B$103-1)),0) -> 4.7829375 | W20: =IF(B20>=Parametri!$B$105-1,Parametri!$B$104,0) -> 5 | X20: =IF(B20>=Parametri!$B$107-1,Parametri!$B$106+Parametri!$B$128*INT((B20-(Parametri!$B$107-1))/2),0) -> 3.73 | Y20: =IF(AND(B20>=Parametri!$B$109-1,B20<Parametri!$B$109-1+Parametri!$B$140),Parametri!$B$108,0) -> 0 | Z20: =IF(B20<10,Parametri!$B$52,IF(B20<20,Parametri!$B$55,0))*M20*G20/1000 -> 7.5823356 | AA20: =Parametri!$B$159*Parametri!$B$160 -> 0 | AB20: =(SUM(Z$5:Z20)+SUM(AA$5:AA20)-SUM(Z$5:Z5)-SUM(AA$5:AA5)) -> 90.540682 | AC20: =-(Parametri!$B$67*SUM(Z$5:Z20)+Parametri!$B$161*SUM(AA$5:AA20)) -> -1.404368 | AD20: =-Z5-AA5 -> -3.08385 | AE20: =Z20+AA20+N20+O20+P20+Q20+T20+U20+V20+W20+X20+Y20+AC20+AD20 -> 33.607872 | AF20: =AF19+AE20 -> 371.82185 | AG20: =-AF20/F20 -> -0.14748945 | AH20: =SUM(Z$5:Z20)-SUM(Z$5:Z5) -> 90.540682 | AI20: =-Z5 -> -3.08385
A21: =Parametri!$B$6+B21 -> 2043 | B21: 16 | C21: =C20*(1+Parametri!$B$14) -> 24.539887 | D21: =D20*(1+Parametri!$B$15)+Parametri!$B$145*(1-Parametri!$B$15)^B20 -> 18.008919 | E21: =D21/C21 -> 0.73386317 | F21: =F20*(1+Parametri!$B$20) -> 2541.1746 | G21: =G20*(1+Parametri!$B$22) -> 27567.336 | H21: =F21*I21 -> 423.10556 | I21: =IF(B21<=(Parametri!$B$35-Parametri!$B$6),Parametri!$B$32+(Parametri!$B$33-Parametri!$B$32)*B21/(Parametri!$B$35-Parametri!$B$6),Parametri!$B$33+(Parametri!$B$34-Parametri!$B$33)*(B21-(Parametri!$B$35-Parametri!$B$6))/(Parametri!$B$36-Parametri!$B$35)) -> 0.1665 | J21: =H21-AE21 -> 387.35482 | K21: =J21/F21 -> 0.15243141 | L21: =IF(B21<=5,Parametri!$B$58+(Parametri!$B$59-Parametri!$B$58)/5*B21,MIN(Parametri!$B$60,Parametri!$B$59+(Parametri!$B$60-Parametri!$B$59)/24*(B21-5))) -> 0.78333333 | M21: =L21*D21 -> 14.106987 | N21: =IF(B21<Parametri!$B$76,Parametri!$B$75*Parametri!$B$74*Parametri!$B$73/Parametri!$B$76,0) -> 0 | O21: =IF(B21<10,Parametri!$B$53,IF(B21<20,Parametri!$B$56,Parametri!$B$57))*M21*G21*Parametri!$B$72/1000 -> 6.3000511 | P21: =MIN(Parametri!$B$81+Parametri!$B$82, Parametri!$B$81+Parametri!$B$82*(B21+1)/Parametri!$B$83) -> 12.5 | Q21: =-IF(B21<10,Parametri!$B$51,IF(B21<20,Parametri!$B$54,Parametri!$B$57))*M21*G21/1000 -> -31.111363 | R21: =-Q21-Z21 -> 23.333523 | S21: =S20+R21 -> 253.19854 | T21: =-(Parametri!$B$86*(Parametri!$B$87*Parametri!$B$90+Parametri!$B$88*Parametri!$B$91+Parametri!$B$89*Parametri!$B$92)/1000000000)*MIN(B21+1,Parametri!$B$93) -> -2.85975 | U21: =IF(B21<Parametri!$B$125,Parametri!$B$46,IF(B21<Parametri!$B$126,Parametri!$B$47,Parametri!$B$48))*Parametri!$B$96*13/1000000000*((B21+1)*Parametri!$B$121+B21*(B21+1)/2*Parametri!$B$122) -> 34.825321 | V21: =IF(B21>=Parametri!$B$103-1,Parametri!$B$102*(1-Parametri!$B$127)^(B21-(Parametri!$B$103-1)),0) -> 4.7111935 | W21: =IF(B21>=Parametri!$B$105-1,Parametri!$B$104,0) -> 5 | X21: =IF(B21>=Parametri!$B$107-1,Parametri!$B$106+Parametri!$B$128*INT((B21-(Parametri!$B$107-1))/2),0) -> 3.73 | Y21: =IF(AND(B21>=Parametri!$B$109-1,B21<Parametri!$B$109-1+Parametri!$B$140),Parametri!$B$108,0) -> 0 | Z21: =IF(B21<10,Parametri!$B$52,IF(B21<20,Parametri!$B$55,0))*M21*G21/1000 -> 7.7778409 | AA21: =Parametri!$B$159*Parametri!$B$160 -> 0 | AB21: =(SUM(Z$5:Z21)+SUM(AA$5:AA21)-SUM(Z$5:Z6)-SUM(AA$5:AA6)) -> 94.71701 | AC21: =-(Parametri!$B$67*SUM(Z$5:Z21)+Parametri!$B$161*SUM(AA$5:AA21)) -> -1.5210356 | AD21: =-Z6-AA6 -> -3.6015127 | AE21: =Z21+AA21+N21+O21+P21+Q21+T21+U21+V21+W21+X21+Y21+AC21+AD21 -> 35.750745 | AF21: =AF20+AE21 -> 407.5726 | AG21: =-AF21/F21 -> -0.16038749 | AH21: =SUM(Z$5:Z21)-SUM(Z$5:Z6) -> 94.71701 | AI21: =-Z6 -> -3.6015127
A22: =Parametri!$B$6+B22 -> 2044 | B22: 17 | C22: =C21*(1+Parametri!$B$14) -> 24.687126 | D22: =D21*(1+Parametri!$B$15)+Parametri!$B$145*(1-Parametri!$B$15)^B21 -> 18.044511 | E22: =D22/C22 -> 0.73092796 | F22: =F21*(1+Parametri!$B$20) -> 2561.504 | G22: =G21*(1+Parametri!$B$22) -> 27622.471 | H22: =F22*I22 -> 422.64815 | I22: =IF(B22<=(Parametri!$B$35-Parametri!$B$6),Parametri!$B$32+(Parametri!$B$33-Parametri!$B$32)*B22/(Parametri!$B$35-Parametri!$B$6),Parametri!$B$33+(Parametri!$B$34-Parametri!$B$33)*(B22-(Parametri!$B$35-Parametri!$B$6))/(Parametri!$B$36-Parametri!$B$35)) -> 0.165 | J22: =H22-AE22 -> 384.47015 | K22: =J22/F22 -> 0.15009548 | L22: =IF(B22<=5,Parametri!$B$58+(Parametri!$B$59-Parametri!$B$58)/5*B22,MIN(Parametri!$B$60,Parametri!$B$59+(Parametri!$B$60-Parametri!$B$59)/24*(B22-5))) -> 0.8 | M22: =L22*D22 -> 14.435609 | N22: =IF(B22<Parametri!$B$76,Parametri!$B$75*Parametri!$B$74*Parametri!$B$73/Parametri!$B$76,0) -> 0 | O22: =IF(B22<10,Parametri!$B$53,IF(B22<20,Parametri!$B$56,Parametri!$B$57))*M22*G22*Parametri!$B$72/1000 -> 6.4597043 | P22: =MIN(Parametri!$B$81+Parametri!$B$82, Parametri!$B$81+Parametri!$B$82*(B22+1)/Parametri!$B$83) -> 12.5 | Q22: =-IF(B22<10,Parametri!$B$51,IF(B22<20,Parametri!$B$54,Parametri!$B$57))*M22*G22/1000 -> -31.899774 | R22: =-Q22-Z22 -> 23.924831 | S22: =S21+R22 -> 277.12337 | T22: =-(Parametri!$B$86*(Parametri!$B$87*Parametri!$B$90+Parametri!$B$88*Parametri!$B$91+Parametri!$B$89*Parametri!$B$92)/1000000000)*MIN(B22+1,Parametri!$B$93) -> -2.85975 | U22: =IF(B22<Parametri!$B$125,Parametri!$B$46,IF(B22<Parametri!$B$126,Parametri!$B$47,Parametri!$B$48))*Parametri!$B$96*13/1000000000*((B22+1)*Parametri!$B$121+B22*(B22+1)/2*Parametri!$B$122) -> 38.255995 | V22: =IF(B22>=Parametri!$B$103-1,Parametri!$B$102*(1-Parametri!$B$127)^(B22-(Parametri!$B$103-1)),0) -> 4.6405256 | W22: =IF(B22>=Parametri!$B$105-1,Parametri!$B$104,0) -> 5 | X22: =IF(B22>=Parametri!$B$107-1,Parametri!$B$106+Parametri!$B$128*INT((B22-(Parametri!$B$107-1))/2),0) -> 3.87 | Y22: =IF(AND(B22>=Parametri!$B$109-1,B22<Parametri!$B$109-1+Parametri!$B$140),Parametri!$B$108,0) -> 0 | Z22: =IF(B22<10,Parametri!$B$52,IF(B22<20,Parametri!$B$55,0))*M22*G22/1000 -> 7.9749436 | AA22: =Parametri!$B$159*Parametri!$B$160 -> 0 | AB22: =(SUM(Z$5:Z22)+SUM(AA$5:AA22)-SUM(Z$5:Z7)-SUM(AA$5:AA7)) -> 98.568967 | AC22: =-(Parametri!$B$67*SUM(Z$5:Z22)+Parametri!$B$161*SUM(AA$5:AA22)) -> -1.6406597 | AD22: =-Z7-AA7 -> -4.1229868 | AE22: =Z22+AA22+N22+O22+P22+Q22+T22+U22+V22+W22+X22+Y22+AC22+AD22 -> 38.177998 | AF22: =AF21+AE22 -> 445.75059 | AG22: =-AF22/F22 -> -0.17401909 | AH22: =SUM(Z$5:Z22)-SUM(Z$5:Z7) -> 98.568967 | AI22: =-Z7 -> -4.1229868
A23: =Parametri!$B$6+B23 -> 2045 | B23: 18 | C23: =C22*(1+Parametri!$B$14) -> 24.835249 | D23: =D22*(1+Parametri!$B$15)+Parametri!$B$145*(1-Parametri!$B$15)^B22 -> 18.080553 | E23: =D23/C23 -> 0.72801978 | F23: =F22*(1+Parametri!$B$20) -> 2581.996 | G23: =G22*(1+Parametri!$B$22) -> 27677.716 | H23: =F23*I23 -> 422.15634 | I23: =IF(B23<=(Parametri!$B$35-Parametri!$B$6),Parametri!$B$32+(Parametri!$B$33-Parametri!$B$32)*B23/(Parametri!$B$35-Parametri!$B$6),Parametri!$B$33+(Parametri!$B$34-Parametri!$B$33)*(B23-(Parametri!$B$35-Parametri!$B$6))/(Parametri!$B$36-Parametri!$B$35)) -> 0.1635 | J23: =H23-AE23 -> 381.54685 | K23: =J23/F23 -> 0.14777205 | L23: =IF(B23<=5,Parametri!$B$58+(Parametri!$B$59-Parametri!$B$58)/5*B23,MIN(Parametri!$B$60,Parametri!$B$59+(Parametri!$B$60-Parametri!$B$59)/24*(B23-5))) -> 0.81666667 | M23: =L23*D23 -> 14.765785 | N23: =IF(B23<Parametri!$B$76,Parametri!$B$75*Parametri!$B$74*Parametri!$B$73/Parametri!$B$76,0) -> 0 | O23: =IF(B23<10,Parametri!$B$53,IF(B23<20,Parametri!$B$56,Parametri!$B$57))*M23*G23*Parametri!$B$72/1000 -> 6.6206677 | P23: =MIN(Parametri!$B$81+Parametri!$B$82, Parametri!$B$81+Parametri!$B$82*(B23+1)/Parametri!$B$83) -> 12.5 | Q23: =-IF(B23<10,Parametri!$B$51,IF(B23<20,Parametri!$B$54,Parametri!$B$57))*M23*G23/1000 -> -32.694655 | R23: =-Q23-Z23 -> 24.520992 | S23: =S22+R23 -> 301.64436 | T23: =-(Parametri!$B$86*(Parametri!$B$87*Parametri!$B$90+Parametri!$B$88*Parametri!$B$91+Parametri!$B$89*Parametri!$B$92)/1000000000)*MIN(B23+1,Parametri!$B$93) -> -2.85975 | U23: =IF(B23<Parametri!$B$125,Parametri!$B$46,IF(B23<Parametri!$B$126,Parametri!$B$47,Parametri!$B$48))*Parametri!$B$96*13/1000000000*((B23+1)*Parametri!$B$121+B23*(B23+1)/2*Parametri!$B$122) -> 41.840239 | V23: =IF(B23>=Parametri!$B$103-1,Parametri!$B$102*(1-Parametri!$B$127)^(B23-(Parametri!$B$103-1)),0) -> 4.5709177 | W23: =IF(B23>=Parametri!$B$105-1,Parametri!$B$104,0) -> 5 | X23: =IF(B23>=Parametri!$B$107-1,Parametri!$B$106+Parametri!$B$128*INT((B23-(Parametri!$B$107-1))/2),0) -> 3.87 | Y23: =IF(AND(B23>=Parametri!$B$109-1,B23<Parametri!$B$109-1+Parametri!$B$140),Parametri!$B$108,0) -> 0 | Z23: =IF(B23<10,Parametri!$B$52,IF(B23<20,Parametri!$B$55,0))*M23*G23/1000 -> 8.1736638 | AA23: =Parametri!$B$159*Parametri!$B$160 -> 0 | AB23: =(SUM(Z$5:Z23)+SUM(AA$5:AA23)-SUM(Z$5:Z8)-SUM(AA$5:AA8)) -> 102.0943 | AC23: =-(Parametri!$B$67*SUM(Z$5:Z23)+Parametri!$B$161*SUM(AA$5:AA23)) -> -1.7632647 | AD23: =-Z8-AA8 -> -4.648327 | AE23: =Z23+AA23+N23+O23+P23+Q23+T23+U23+V23+W23+X23+Y23+AC23+AD23 -> 40.609491 | AF23: =AF22+AE23 -> 486.36009 | AG23: =-AF23/F23 -> -0.18836593 | AH23: =SUM(Z$5:Z23)-SUM(Z$5:Z8) -> 102.0943 | AI23: =-Z8 -> -4.648327
A24: =Parametri!$B$6+B24 -> 2046 | B24: 19 | C24: =C23*(1+Parametri!$B$14) -> 24.98426 | D24: =D23*(1+Parametri!$B$15)+Parametri!$B$145*(1-Parametri!$B$15)^B23 -> 18.117046 | E24: =D24/C24 -> 0.72513836 | F24: =F23*(1+Parametri!$B$20) -> 2602.6519 | G24: =G23*(1+Parametri!$B$22) -> 27733.071 | H24: =F24*I24 -> 421.62962 | I24: =IF(B24<=(Parametri!$B$35-Parametri!$B$6),Parametri!$B$32+(Parametri!$B$33-Parametri!$B$32)*B24/(Parametri!$B$35-Parametri!$B$6),Parametri!$B$33+(Parametri!$B$34-Parametri!$B$33)*(B24-(Parametri!$B$35-Parametri!$B$6))/(Parametri!$B$36-Parametri!$B$35)) -> 0.162 | J24: =H24-AE24 -> 378.30453 | K24: =J24/F24 -> 0.14535349 | L24: =IF(B24<=5,Parametri!$B$58+(Parametri!$B$59-Parametri!$B$58)/5*B24,MIN(Parametri!$B$60,Parametri!$B$59+(Parametri!$B$60-Parametri!$B$59)/24*(B24-5))) -> 0.83333333 | M24: =L24*D24 -> 15.097538 | N24: =IF(B24<Parametri!$B$76,Parametri!$B$75*Parametri!$B$74*Parametri!$B$73/Parametri!$B$76,0) -> 0 | O24: =IF(B24<10,Parametri!$B$53,IF(B24<20,Parametri!$B$56,Parametri!$B$57))*M24*G24*Parametri!$B$72/1000 -> 6.7829578 | P24: =MIN(Parametri!$B$81+Parametri!$B$82, Parametri!$B$81+Parametri!$B$82*(B24+1)/Parametri!$B$83) -> 12.5 | Q24: =-IF(B24<10,Parametri!$B$51,IF(B24<20,Parametri!$B$54,Parametri!$B$57))*M24*G24/1000 -> -33.496088 | R24: =-Q24-Z24 -> 25.122066 | S24: =S23+R24 -> 326.76643 | T24: =-(Parametri!$B$86*(Parametri!$B$87*Parametri!$B$90+Parametri!$B$88*Parametri!$B$91+Parametri!$B$89*Parametri!$B$92)/1000000000)*MIN(B24+1,Parametri!$B$93) -> -2.85975 | U24: =IF(B24<Parametri!$B$125,Parametri!$B$46,IF(B24<Parametri!$B$126,Parametri!$B$47,Parametri!$B$48))*Parametri!$B$96*13/1000000000*((B24+1)*Parametri!$B$121+B24*(B24+1)/2*Parametri!$B$122) -> 45.578052 | V24: =IF(B24>=Parametri!$B$103-1,Parametri!$B$102*(1-Parametri!$B$127)^(B24-(Parametri!$B$103-1)),0) -> 4.5023539 | W24: =IF(B24>=Parametri!$B$105-1,Parametri!$B$104,0) -> 5 | X24: =IF(B24>=Parametri!$B$107-1,Parametri!$B$106+Parametri!$B$128*INT((B24-(Parametri!$B$107-1))/2),0) -> 4.01 | Y24: =IF(AND(B24>=Parametri!$B$109-1,B24<Parametri!$B$109-1+Parametri!$B$140),Parametri!$B$108,0) -> 0 | Z24: =IF(B24<10,Parametri!$B$52,IF(B24<20,Parametri!$B$55,0))*M24*G24/1000 -> 8.374022 | AA24: =Parametri!$B$159*Parametri!$B$160 -> 0 | AB24: =(SUM(Z$5:Z24)+SUM(AA$5:AA24)-SUM(Z$5:Z9)-SUM(AA$5:AA9)) -> 105.29074 | AC24: =-(Parametri!$B$67*SUM(Z$5:Z24)+Parametri!$B$161*SUM(AA$5:AA24)) -> -1.888875 | AD24: =-Z9-AA9 -> -5.1775889 | AE24: =Z24+AA24+N24+O24+P24+Q24+T24+U24+V24+W24+X24+Y24+AC24+AD24 -> 43.325084 | AF24: =AF23+AE24 -> 529.68517 | AG24: =-AF24/F24 -> -0.20351748 | AH24: =SUM(Z$5:Z24)-SUM(Z$5:Z9) -> 105.29074 | AI24: =-Z9 -> -5.1775889
A25: =Parametri!$B$6+B25 -> 2047 | B25: 20 | C25: =C24*(1+Parametri!$B$14) -> 25.134166 | D25: =D24*(1+Parametri!$B$15)+Parametri!$B$145*(1-Parametri!$B$15)^B24 -> 18.153991 | E25: =D25/C25 -> 0.72228339 | F25: =F24*(1+Parametri!$B$20) -> 2623.4732 | G25: =G24*(1+Parametri!$B$22) -> 27788.538 | H25: =F25*I25 -> 421.06744 | I25: =IF(B25<=(Parametri!$B$35-Parametri!$B$6),Parametri!$B$32+(Parametri!$B$33-Parametri!$B$32)*B25/(Parametri!$B$35-Parametri!$B$6),Parametri!$B$33+(Parametri!$B$34-Parametri!$B$33)*(B25-(Parametri!$B$35-Parametri!$B$6))/(Parametri!$B$36-Parametri!$B$35)) -> 0.1605 | J25: =H25-AE25 -> 384.28493 | K25: =J25/F25 -> 0.14647946 | L25: =IF(B25<=5,Parametri!$B$58+(Parametri!$B$59-Parametri!$B$58)/5*B25,MIN(Parametri!$B$60,Parametri!$B$59+(Parametri!$B$60-Parametri!$B$59)/24*(B25-5))) -> 0.85 | M25: =L25*D25 -> 15.430892 | N25: =IF(B25<Parametri!$B$76,Parametri!$B$75*Parametri!$B$74*Parametri!$B$73/Parametri!$B$76,0) -> 0 | O25: =IF(B25<10,Parametri!$B$53,IF(B25<20,Parametri!$B$56,Parametri!$B$57))*M25*G25*Parametri!$B$72/1000 -> 10.419887 | P25: =MIN(Parametri!$B$81+Parametri!$B$82, Parametri!$B$81+Parametri!$B$82*(B25+1)/Parametri!$B$83) -> 12.5 | Q25: =-IF(B25<10,Parametri!$B$51,IF(B25<20,Parametri!$B$54,Parametri!$B$57))*M25*G25/1000 -> -38.592173 | R25: =-Q25-Z25 -> 38.592173 | S25: =S24+R25 -> 365.3586 | T25: =-(Parametri!$B$86*(Parametri!$B$87*Parametri!$B$90+Parametri!$B$88*Parametri!$B$91+Parametri!$B$89*Parametri!$B$92)/1000000000)*MIN(B25+1,Parametri!$B$93) -> -2.85975 | U25: =IF(B25<Parametri!$B$125,Parametri!$B$46,IF(B25<Parametri!$B$126,Parametri!$B$47,Parametri!$B$48))*Parametri!$B$96*13/1000000000*((B25+1)*Parametri!$B$121+B25*(B25+1)/2*Parametri!$B$122) -> 49.469435 | V25: =IF(B25>=Parametri!$B$103-1,Parametri!$B$102*(1-Parametri!$B$127)^(B25-(Parametri!$B$103-1)),0) -> 4.4348186 | W25: =IF(B25>=Parametri!$B$105-1,Parametri!$B$104,0) -> 5 | X25: =IF(B25>=Parametri!$B$107-1,Parametri!$B$106+Parametri!$B$128*INT((B25-(Parametri!$B$107-1))/2),0) -> 4.01 | Y25: =IF(AND(B25>=Parametri!$B$109-1,B25<Parametri!$B$109-1+Parametri!$B$140),Parametri!$B$108,0) -> 0 | Z25: =IF(B25<10,Parametri!$B$52,IF(B25<20,Parametri!$B$55,0))*M25*G25/1000 -> 0 | AA25: =Parametri!$B$159*Parametri!$B$160 -> 0 | AB25: =(SUM(Z$5:Z25)+SUM(AA$5:AA25)-SUM(Z$5:Z10)-SUM(AA$5:AA10)) -> 99.579909 | AC25: =-(Parametri!$B$67*SUM(Z$5:Z25)+Parametri!$B$161*SUM(AA$5:AA25)) -> -1.888875 | AD25: =-Z10-AA10 -> -5.7108283 | AE25: =Z25+AA25+N25+O25+P25+Q25+T25+U25+V25+W25+X25+Y25+AC25+AD25 -> 36.782514 | AF25: =AF24+AE25 -> 566.46768 | AG25: =-AF25/F25 -> -0.2159228 | AH25: =SUM(Z$5:Z25)-SUM(Z$5:Z10) -> 99.579909 | AI25: =-Z10 -> -5.7108283
A26: =Parametri!$B$6+B26 -> 2048 | B26: 21 | C26: =C25*(1+Parametri!$B$14) -> 25.284971 | D26: =D25*(1+Parametri!$B$15)+Parametri!$B$145*(1-Parametri!$B$15)^B25 -> 18.191388 | E26: =D26/C26 -> 0.71945459 | F26: =F25*(1+Parametri!$B$20) -> 2644.461 | G26: =G25*(1+Parametri!$B$22) -> 27844.115 | H26: =F26*I26 -> 420.46929 | I26: =IF(B26<=(Parametri!$B$35-Parametri!$B$6),Parametri!$B$32+(Parametri!$B$33-Parametri!$B$32)*B26/(Parametri!$B$35-Parametri!$B$6),Parametri!$B$33+(Parametri!$B$34-Parametri!$B$33)*(B26-(Parametri!$B$35-Parametri!$B$6))/(Parametri!$B$36-Parametri!$B$35)) -> 0.159 | J26: =H26-AE26 -> 380.41809 | K26: =J26/F26 -> 0.14385468 | L26: =IF(B26<=5,Parametri!$B$58+(Parametri!$B$59-Parametri!$B$58)/5*B26,MIN(Parametri!$B$60,Parametri!$B$59+(Parametri!$B$60-Parametri!$B$59)/24*(B26-5))) -> 0.86666667 | M26: =L26*D26 -> 15.76587 | N26: =IF(B26<Parametri!$B$76,Parametri!$B$75*Parametri!$B$74*Parametri!$B$73/Parametri!$B$76,0) -> 0 | O26: =IF(B26<10,Parametri!$B$53,IF(B26<20,Parametri!$B$56,Parametri!$B$57))*M26*G26*Parametri!$B$72/1000 -> 10.667377 | P26: =MIN(Parametri!$B$81+Parametri!$B$82, Parametri!$B$81+Parametri!$B$82*(B26+1)/Parametri!$B$83) -> 12.5 | Q26: =-IF(B26<10,Parametri!$B$51,IF(B26<20,Parametri!$B$54,Parametri!$B$57))*M26*G26/1000 -> -39.508802 | R26: =-Q26-Z26 -> 39.508802 | S26: =S25+R26 -> 404.86741 | T26: =-(Parametri!$B$86*(Parametri!$B$87*Parametri!$B$90+Parametri!$B$88*Parametri!$B$91+Parametri!$B$89*Parametri!$B$92)/1000000000)*MIN(B26+1,Parametri!$B$93) -> -2.85975 | U26: =IF(B26<Parametri!$B$125,Parametri!$B$46,IF(B26<Parametri!$B$126,Parametri!$B$47,Parametri!$B$48))*Parametri!$B$96*13/1000000000*((B26+1)*Parametri!$B$121+B26*(B26+1)/2*Parametri!$B$122) -> 53.514387 | V26: =IF(B26>=Parametri!$B$103-1,Parametri!$B$102*(1-Parametri!$B$127)^(B26-(Parametri!$B$103-1)),0) -> 4.3682963 | W26: =IF(B26>=Parametri!$B$105-1,Parametri!$B$104,0) -> 5 | X26: =IF(B26>=Parametri!$B$107-1,Parametri!$B$106+Parametri!$B$128*INT((B26-(Parametri!$B$107-1))/2),0) -> 4.15 | Y26: =IF(AND(B26>=Parametri!$B$109-1,B26<Parametri!$B$109-1+Parametri!$B$140),Parametri!$B$108,0) -> 0 | Z26: =IF(B26<10,Parametri!$B$52,IF(B26<20,Parametri!$B$55,0))*M26*G26/1000 -> 0 | AA26: =Parametri!$B$159*Parametri!$B$160 -> 0 | AB26: =(SUM(Z$5:Z26)+SUM(AA$5:AA26)-SUM(Z$5:Z11)-SUM(AA$5:AA11)) -> 93.688478 | AC26: =-(Parametri!$B$67*SUM(Z$5:Z26)+Parametri!$B$161*SUM(AA$5:AA26)) -> -1.888875 | AD26: =-Z11-AA11 -> -5.891431 | AE26: =Z26+AA26+N26+O26+P26+Q26+T26+U26+V26+W26+X26+Y26+AC26+AD26 -> 40.051201 | AF26: =AF25+AE26 -> 606.51888 | AG26: =-AF26/F26 -> -0.22935445 | AH26: =SUM(Z$5:Z26)-SUM(Z$5:Z11) -> 93.688478 | AI26: =-Z11 -> -5.891431
A27: =Parametri!$B$6+B27 -> 2049 | B27: 22 | C27: =C26*(1+Parametri!$B$14) -> 25.436681 | D27: =D26*(1+Parametri!$B$15)+Parametri!$B$145*(1-Parametri!$B$15)^B26 -> 18.22924 | E27: =D27/C27 -> 0.71665169 | F27: =F26*(1+Parametri!$B$20) -> 2665.6166 | G27: =G26*(1+Parametri!$B$22) -> 27899.803 | H27: =F27*I27 -> 419.83462 | I27: =IF(B27<=(Parametri!$B$35-Parametri!$B$6),Parametri!$B$32+(Parametri!$B$33-Parametri!$B$32)*B27/(Parametri!$B$35-Parametri!$B$6),Parametri!$B$33+(Parametri!$B$34-Parametri!$B$33)*(B27-(Parametri!$B$35-Parametri!$B$6))/(Parametri!$B$36-Parametri!$B$35)) -> 0.1575 | J27: =H27-AE27 -> 376.50715 | K27: =J27/F27 -> 0.1412458 | L27: =IF(B27<=5,Parametri!$B$58+(Parametri!$B$59-Parametri!$B$58)/5*B27,MIN(Parametri!$B$60,Parametri!$B$59+(Parametri!$B$60-Parametri!$B$59)/24*(B27-5))) -> 0.88333333 | M27: =L27*D27 -> 16.102496 | N27: =IF(B27<Parametri!$B$76,Parametri!$B$75*Parametri!$B$74*Parametri!$B$73/Parametri!$B$76,0) -> 0 | O27: =IF(B27<10,Parametri!$B$53,IF(B27<20,Parametri!$B$56,Parametri!$B$57))*M27*G27*Parametri!$B$72/1000 -> 10.916932 | P27: =MIN(Parametri!$B$81+Parametri!$B$82, Parametri!$B$81+Parametri!$B$82*(B27+1)/Parametri!$B$83) -> 12.5 | Q27: =-IF(B27<10,Parametri!$B$51,IF(B27<20,Parametri!$B$54,Parametri!$B$57))*M27*G27/1000 -> -40.433081 | R27: =-Q27-Z27 -> 40.433081 | S27: =S26+R27 -> 445.30049 | T27: =-(Parametri!$B$86*(Parametri!$B$87*Parametri!$B$90+Parametri!$B$88*Parametri!$B$91+Parametri!$B$89*Parametri!$B$92)/1000000000)*MIN(B27+1,Parametri!$B$93) -> -2.85975 | U27: =IF(B27<Parametri!$B$125,Parametri!$B$46,IF(B27<Parametri!$B$126,Parametri!$B$47,Parametri!$B$48))*Parametri!$B$96*13/1000000000*((B27+1)*Parametri!$B$121+B27*(B27+1)/2*Parametri!$B$122) -> 57.712908 | V27: =IF(B27>=Parametri!$B$103-1,Parametri!$B$102*(1-Parametri!$B$127)^(B27-(Parametri!$B$103-1)),0) -> 4.3027719 | W27: =IF(B27>=Parametri!$B$105-1,Parametri!$B$104,0) -> 5 | X27: =IF(B27>=Parametri!$B$107-1,Parametri!$B$106+Parametri!$B$128*INT((B27-(Parametri!$B$107-1))/2),0) -> 4.15 | Y27: =IF(AND(B27>=Parametri!$B$109-1,B27<Parametri!$B$109-1+Parametri!$B$140),Parametri!$B$108,0) -> 0 | Z27: =IF(B27<10,Parametri!$B$52,IF(B27<20,Parametri!$B$55,0))*M27*G27/1000 -> 0 | AA27: =Parametri!$B$159*Parametri!$B$160 -> 0 | AB27: =(SUM(Z$5:Z27)+SUM(AA$5:AA27)-SUM(Z$5:Z12)-SUM(AA$5:AA12)) -> 87.615039 | AC27: =-(Parametri!$B$67*SUM(Z$5:Z27)+Parametri!$B$161*SUM(AA$5:AA27)) -> -1.888875 | AD27: =-Z12-AA12 -> -6.0734387 | AE27: =Z27+AA27+N27+O27+P27+Q27+T27+U27+V27+W27+X27+Y27+AC27+AD27 -> 43.327468 | AF27: =AF26+AE27 -> 649.84635 | AG27: =-AF27/F27 -> -0.24378838 | AH27: =SUM(Z$5:Z27)-SUM(Z$5:Z12) -> 87.615039 | AI27: =-Z12 -> -6.0734387
A28: =Parametri!$B$6+B28 -> 2050 | B28: 23 | C28: =C27*(1+Parametri!$B$14) -> 25.589301 | D28: =D27*(1+Parametri!$B$15)+Parametri!$B$145*(1-Parametri!$B$15)^B27 -> 18.267547 | E28: =D28/C28 -> 0.7138744 | F28: =F27*(1+Parametri!$B$20) -> 2686.9416 | G28: =G27*(1+Parametri!$B$22) -> 27955.602 | H28: =F28*I28 -> 419.16289 | I28: =IF(B28<=(Parametri!$B$35-Parametri!$B$6),Parametri!$B$32+(Parametri!$B$33-Parametri!$B$32)*B28/(Parametri!$B$35-Parametri!$B$6),Parametri!$B$33+(Parametri!$B$34-Parametri!$B$33)*(B28-(Parametri!$B$35-Parametri!$B$6))/(Parametri!$B$36-Parametri!$B$35)) -> 0.156 | J28: =H28-AE28 -> 372.27168 | K28: =J28/F28 -> 0.13854848 | L28: =IF(B28<=5,Parametri!$B$58+(Parametri!$B$59-Parametri!$B$58)/5*B28,MIN(Parametri!$B$60,Parametri!$B$59+(Parametri!$B$60-Parametri!$B$59)/24*(B28-5))) -> 0.9 | M28: =L28*D28 -> 16.440792 | N28: =IF(B28<Parametri!$B$76,Parametri!$B$75*Parametri!$B$74*Parametri!$B$73/Parametri!$B$76,0) -> 0 | O28: =IF(B28<10,Parametri!$B$53,IF(B28<20,Parametri!$B$56,Parametri!$B$57))*M28*G28*Parametri!$B$72/1000 -> 11.168578 | P28: =MIN(Parametri!$B$81+Parametri!$B$82, Parametri!$B$81+Parametri!$B$82*(B28+1)/Parametri!$B$83) -> 12.5 | Q28: =-IF(B28<10,Parametri!$B$51,IF(B28<20,Parametri!$B$54,Parametri!$B$57))*M28*G28/1000 -> -41.365102 | R28: =-Q28-Z28 -> 41.365102 | S28: =S27+R28 -> 486.66559 | T28: =-(Parametri!$B$86*(Parametri!$B$87*Parametri!$B$90+Parametri!$B$88*Parametri!$B$91+Parametri!$B$89*Parametri!$B$92)/1000000000)*MIN(B28+1,Parametri!$B$93) -> -2.85975 | U28: =IF(B28<Parametri!$B$125,Parametri!$B$46,IF(B28<Parametri!$B$126,Parametri!$B$47,Parametri!$B$48))*Parametri!$B$96*13/1000000000*((B28+1)*Parametri!$B$121+B28*(B28+1)/2*Parametri!$B$122) -> 62.064999 | V28: =IF(B28>=Parametri!$B$103-1,Parametri!$B$102*(1-Parametri!$B$127)^(B28-(Parametri!$B$103-1)),0) -> 4.2382303 | W28: =IF(B28>=Parametri!$B$105-1,Parametri!$B$104,0) -> 5 | X28: =IF(B28>=Parametri!$B$107-1,Parametri!$B$106+Parametri!$B$128*INT((B28-(Parametri!$B$107-1))/2),0) -> 4.29 | Y28: =IF(AND(B28>=Parametri!$B$109-1,B28<Parametri!$B$109-1+Parametri!$B$140),Parametri!$B$108,0) -> 0 | Z28: =IF(B28<10,Parametri!$B$52,IF(B28<20,Parametri!$B$55,0))*M28*G28/1000 -> 0 | AA28: =Parametri!$B$159*Parametri!$B$160 -> 0 | AB28: =(SUM(Z$5:Z28)+SUM(AA$5:AA28)-SUM(Z$5:Z13)-SUM(AA$5:AA13)) -> 81.358169 | AC28: =-(Parametri!$B$67*SUM(Z$5:Z28)+Parametri!$B$161*SUM(AA$5:AA28)) -> -1.888875 | AD28: =-Z13-AA13 -> -6.2568698 | AE28: =Z28+AA28+N28+O28+P28+Q28+T28+U28+V28+W28+X28+Y28+AC28+AD28 -> 46.89121 | AF28: =AF27+AE28 -> 696.73756 | AG28: =-AF28/F28 -> -0.25930507 | AH28: =SUM(Z$5:Z28)-SUM(Z$5:Z13) -> 81.358169 | AI28: =-Z13 -> -6.2568698
A29: =Parametri!$B$6+B29 -> 2051 | B29: 24 | C29: =C28*(1+Parametri!$B$14) -> 25.742837 | D29: =D28*(1+Parametri!$B$15)+Parametri!$B$145*(1-Parametri!$B$15)^B28 -> 18.306309 | E29: =D29/C29 -> 0.71112245 | F29: =F28*(1+Parametri!$B$20) -> 2708.4371 | G29: =G28*(1+Parametri!$B$22) -> 28011.514 | H29: =F29*I29 -> 418.45353 | I29: =IF(B29<=(Parametri!$B$35-Parametri!$B$6),Parametri!$B$32+(Parametri!$B$33-Parametri!$B$32)*B29/(Parametri!$B$35-Parametri!$B$6),Parametri!$B$33+(Parametri!$B$34-Parametri!$B$33)*(B29-(Parametri!$B$35-Parametri!$B$6))/(Parametri!$B$36-Parametri!$B$35)) -> 0.1545 | J29: =H29-AE29 -> 367.99121 | K29: =J29/F29 -> 0.13586847 | L29: =IF(B29<=5,Parametri!$B$58+(Parametri!$B$59-Parametri!$B$58)/5*B29,MIN(Parametri!$B$60,Parametri!$B$59+(Parametri!$B$60-Parametri!$B$59)/24*(B29-5))) -> 0.91666667 | M29: =L29*D29 -> 16.780783 | N29: =IF(B29<Parametri!$B$76,Parametri!$B$75*Parametri!$B$74*Parametri!$B$73/Parametri!$B$76,0) -> 0 | O29: =IF(B29<10,Parametri!$B$53,IF(B29<20,Parametri!$B$56,Parametri!$B$57))*M29*G29*Parametri!$B$72/1000 -> 11.42234 | P29: =MIN(Parametri!$B$81+Parametri!$B$82, Parametri!$B$81+Parametri!$B$82*(B29+1)/Parametri!$B$83) -> 12.5 | Q29: =-IF(B29<10,Parametri!$B$51,IF(B29<20,Parametri!$B$54,Parametri!$B$57))*M29*G29/1000 -> -42.304963 | R29: =-Q29-Z29 -> 42.304963 | S29: =S28+R29 -> 528.97055 | T29: =-(Parametri!$B$86*(Parametri!$B$87*Parametri!$B$90+Parametri!$B$88*Parametri!$B$91+Parametri!$B$89*Parametri!$B$92)/1000000000)*MIN(B29+1,Parametri!$B$93) -> -2.85975 | U29: =IF(B29<Parametri!$B$125,Parametri!$B$46,IF(B29<Parametri!$B$126,Parametri!$B$47,Parametri!$B$48))*Parametri!$B$96*13/1000000000*((B29+1)*Parametri!$B$121+B29*(B29+1)/2*Parametri!$B$122) -> 66.57066 | V29: =IF(B29>=Parametri!$B$103-1,Parametri!$B$102*(1-Parametri!$B$127)^(B29-(Parametri!$B$103-1)),0) -> 4.1746568 | W29: =IF(B29>=Parametri!$B$105-1,Parametri!$B$104,0) -> 5 | X29: =IF(B29>=Parametri!$B$107-1,Parametri!$B$106+Parametri!$B$128*INT((B29-(Parametri!$B$107-1))/2),0) -> 4.29 | Y29: =IF(AND(B29>=Parametri!$B$109-1,B29<Parametri!$B$109-1+Parametri!$B$140),Parametri!$B$108,0) -> 0 | Z29: =IF(B29<10,Parametri!$B$52,IF(B29<20,Parametri!$B$55,0))*M29*G29/1000 -> 0 | AA29: =Parametri!$B$159*Parametri!$B$160 -> 0 | AB29: =(SUM(Z$5:Z29)+SUM(AA$5:AA29)-SUM(Z$5:Z14)-SUM(AA$5:AA14)) -> 74.916426 | AC29: =-(Parametri!$B$67*SUM(Z$5:Z29)+Parametri!$B$161*SUM(AA$5:AA29)) -> -1.888875 | AD29: =-Z14-AA14 -> -6.4417431 | AE29: =Z29+AA29+N29+O29+P29+Q29+T29+U29+V29+W29+X29+Y29+AC29+AD29 -> 50.462326 | AF29: =AF28+AE29 -> 747.19989 | AG29: =-AF29/F29 -> -0.27587862 | AH29: =SUM(Z$5:Z29)-SUM(Z$5:Z14) -> 74.916426 | AI29: =-Z14 -> -6.4417431
A30: =Parametri!$B$6+B30 -> 2052 | B30: 25 | C30: =C29*(1+Parametri!$B$14) -> 25.897294 | D30: =D29*(1+Parametri!$B$15)+Parametri!$B$145*(1-Parametri!$B$15)^B29 -> 18.345528 | E30: =D30/C30 -> 0.70839557 | F30: =F29*(1+Parametri!$B$20) -> 2730.1046 | G30: =G29*(1+Parametri!$B$22) -> 28067.537 | H30: =F30*I30 -> 417.706 | I30: =IF(B30<=(Parametri!$B$35-Parametri!$B$6),Parametri!$B$32+(Parametri!$B$33-Parametri!$B$32)*B30/(Parametri!$B$35-Parametri!$B$6),Parametri!$B$33+(Parametri!$B$34-Parametri!$B$33)*(B30-(Parametri!$B$35-Parametri!$B$6))/(Parametri!$B$36-Parametri!$B$35)) -> 0.153 | J30: =H30-AE30 -> 363.38529 | K30: =J30/F30 -> 0.13310307 | L30: =IF(B30<=5,Parametri!$B$58+(Parametri!$B$59-Parametri!$B$58)/5*B30,MIN(Parametri!$B$60,Parametri!$B$59+(Parametri!$B$60-Parametri!$B$59)/24*(B30-5))) -> 0.93333333 | M30: =L30*D30 -> 17.122493 | N30: =IF(B30<Parametri!$B$76,Parametri!$B$75*Parametri!$B$74*Parametri!$B$73/Parametri!$B$76,0) -> 0 | O30: =IF(B30<10,Parametri!$B$53,IF(B30<20,Parametri!$B$56,Parametri!$B$57))*M30*G30*Parametri!$B$72/1000 -> 11.678245 | P30: =MIN(Parametri!$B$81+Parametri!$B$82, Parametri!$B$81+Parametri!$B$82*(B30+1)/Parametri!$B$83) -> 12.5 | Q30: =-IF(B30<10,Parametri!$B$51,IF(B30<20,Parametri!$B$54,Parametri!$B$57))*M30*G30/1000 -> -43.252758 | R30: =-Q30-Z30 -> 43.252758 | S30: =S29+R30 -> 572.22331 | T30: =-(Parametri!$B$86*(Parametri!$B$87*Parametri!$B$90+Parametri!$B$88*Parametri!$B$91+Parametri!$B$89*Parametri!$B$92)/1000000000)*MIN(B30+1,Parametri!$B$93) -> -2.85975 | U30: =IF(B30<Parametri!$B$125,Parametri!$B$46,IF(B30<Parametri!$B$126,Parametri!$B$47,Parametri!$B$48))*Parametri!$B$96*13/1000000000*((B30+1)*Parametri!$B$121+B30*(B30+1)/2*Parametri!$B$122) -> 71.22989 | V30: =IF(B30>=Parametri!$B$103-1,Parametri!$B$102*(1-Parametri!$B$127)^(B30-(Parametri!$B$103-1)),0) -> 4.112037 | W30: =IF(B30>=Parametri!$B$105-1,Parametri!$B$104,0) -> 5 | X30: =IF(B30>=Parametri!$B$107-1,Parametri!$B$106+Parametri!$B$128*INT((B30-(Parametri!$B$107-1))/2),0) -> 4.43 | Y30: =IF(AND(B30>=Parametri!$B$109-1,B30<Parametri!$B$109-1+Parametri!$B$140),Parametri!$B$108,0) -> 0 | Z30: =IF(B30<10,Parametri!$B$52,IF(B30<20,Parametri!$B$55,0))*M30*G30/1000 -> 0 | AA30: =Parametri!$B$159*Parametri!$B$160 -> 0 | AB30: =(SUM(Z$5:Z30)+SUM(AA$5:AA30)-SUM(Z$5:Z15)-SUM(AA$5:AA15)) -> 68.288349 | AC30: =-(Parametri!$B$67*SUM(Z$5:Z30)+Parametri!$B$161*SUM(AA$5:AA30)) -> -1.888875 | AD30: =-Z15-AA15 -> -6.6280775 | AE30: =Z30+AA30+N30+O30+P30+Q30+T30+U30+V30+W30+X30+Y30+AC30+AD30 -> 54.320711 | AF30: =AF29+AE30 -> 801.5206 | AG30: =-AF30/F30 -> -0.29358604 | AH30: =SUM(Z$5:Z30)-SUM(Z$5:Z15) -> 68.288349 | AI30: =-Z15 -> -6.6280775
A31: =Parametri!$B$6+B31 -> 2053 | B31: 26 | C31: =C30*(1+Parametri!$B$14) -> 26.052677 | D31: =D30*(1+Parametri!$B$15)+Parametri!$B$145*(1-Parametri!$B$15)^B30 -> 18.385205 | E31: =D31/C31 -> 0.70569349 | F31: =F30*(1+Parametri!$B$20) -> 2751.9454 | G31: =G30*(1+Parametri!$B$22) -> 28123.672 | H31: =F31*I31 -> 416.91973 | I31: =IF(B31<=(Parametri!$B$35-Parametri!$B$6),Parametri!$B$32+(Parametri!$B$33-Parametri!$B$32)*B31/(Parametri!$B$35-Parametri!$B$6),Parametri!$B$33+(Parametri!$B$34-Parametri!$B$33)*(B31-(Parametri!$B$35-Parametri!$B$6))/(Parametri!$B$36-Parametri!$B$35)) -> 0.1515 | J31: =H31-AE31 -> 358.73347 | K31: =J31/F31 -> 0.13035632 | L31: =IF(B31<=5,Parametri!$B$58+(Parametri!$B$59-Parametri!$B$58)/5*B31,MIN(Parametri!$B$60,Parametri!$B$59+(Parametri!$B$60-Parametri!$B$59)/24*(B31-5))) -> 0.95 | M31: =L31*D31 -> 17.465945 | N31: =IF(B31<Parametri!$B$76,Parametri!$B$75*Parametri!$B$74*Parametri!$B$73/Parametri!$B$76,0) -> 0 | O31: =IF(B31<10,Parametri!$B$53,IF(B31<20,Parametri!$B$56,Parametri!$B$57))*M31*G31*Parametri!$B$72/1000 -> 11.936318 | P31: =MIN(Parametri!$B$81+Parametri!$B$82, Parametri!$B$81+Parametri!$B$82*(B31+1)/Parametri!$B$83) -> 12.5 | Q31: =-IF(B31<10,Parametri!$B$51,IF(B31<20,Parametri!$B$54,Parametri!$B$57))*M31*G31/1000 -> -44.208584 | R31: =-Q31-Z31 -> 44.208584 | S31: =S30+R31 -> 616.43189 | T31: =-(Parametri!$B$86*(Parametri!$B$87*Parametri!$B$90+Parametri!$B$88*Parametri!$B$91+Parametri!$B$89*Parametri!$B$92)/1000000000)*MIN(B31+1,Parametri!$B$93) -> -2.85975 | U31: =IF(B31<Parametri!$B$125,Parametri!$B$46,IF(B31<Parametri!$B$126,Parametri!$B$47,Parametri!$B$48))*Parametri!$B$96*13/1000000000*((B31+1)*Parametri!$B$121+B31*(B31+1)/2*Parametri!$B$122) -> 76.04269 | V31: =IF(B31>=Parametri!$B$103-1,Parametri!$B$102*(1-Parametri!$B$127)^(B31-(Parametri!$B$103-1)),0) -> 4.0503564 | W31: =IF(B31>=Parametri!$B$105-1,Parametri!$B$104,0) -> 5 | X31: =IF(B31>=Parametri!$B$107-1,Parametri!$B$106+Parametri!$B$128*INT((B31-(Parametri!$B$107-1))/2),0) -> 4.43 | Y31: =IF(AND(B31>=Parametri!$B$109-1,B31<Parametri!$B$109-1+Parametri!$B$140),Parametri!$B$108,0) -> 0 | Z31: =IF(B31<10,Parametri!$B$52,IF(B31<20,Parametri!$B$55,0))*M31*G31/1000 -> 0 | AA31: =Parametri!$B$159*Parametri!$B$160 -> 0 | AB31: =(SUM(Z$5:Z31)+SUM(AA$5:AA31)-SUM(Z$5:Z16)-SUM(AA$5:AA16)) -> 61.472457 | AC31: =-(Parametri!$B$67*SUM(Z$5:Z31)+Parametri!$B$161*SUM(AA$5:AA31)) -> -1.888875 | AD31: =-Z16-AA16 -> -6.8158919 | AE31: =Z31+AA31+N31+O31+P31+Q31+T31+U31+V31+W31+X31+Y31+AC31+AD31 -> 58.186263 | AF31: =AF30+AE31 -> 859.70686 | AG31: =-AF31/F31 -> -0.31239968 | AH31: =SUM(Z$5:Z31)-SUM(Z$5:Z16) -> 61.472457 | AI31: =-Z16 -> -6.8158919
... A38: =Parametri!$B$6+B38 -> 2060 | B38: 33 | C38: =C37*(1+Parametri!$B$14) -> 27.166784 | D38: =D37*(1+Parametri!$B$15)+Parametri!$B$145*(1-Parametri!$B$15)^B37 -> 18.675839 | E38: =D38/C38 -> 0.68745125 | F38: =F37*(1+Parametri!$B$20) -> 2909.8027 | G38: =G37*(1+Parametri!$B$22) -> 28519.773 | H38: =F38*I38 -> 410.28218 | I38: =IF(B38<=(Parametri!$B$35-Parametri!$B$6),Parametri!$B$32+(Parametri!$B$33-Parametri!$B$32)*B38/(Parametri!$B$35-Parametri!$B$6),Parametri!$B$33+(Parametri!$B$34-Parametri!$B$33)*(B38-(Parametri!$B$35-Parametri!$B$6))/(Parametri!$B$36-Parametri!$B$35)) -> 0.141 | J38: =H38-AE38 -> 318.03234 | K38: =J38/F38 -> 0.10929687 | L38: =IF(B38<=5,Parametri!$B$58+(Parametri!$B$59-Parametri!$B$58)/5*B38,MIN(Parametri!$B$60,Parametri!$B$59+(Parametri!$B$60-Parametri!$B$59)/24*(B38-5))) -> 1 | M38: =L38*D38 -> 18.675839 | N38: =IF(B38<Parametri!$B$76,Parametri!$B$75*Parametri!$B$74*Parametri!$B$73/Parametri!$B$76,0) -> 0 | O38: =IF(B38<10,Parametri!$B$53,IF(B38<20,Parametri!$B$56,Parametri!$B$57))*M38*G38*Parametri!$B$72/1000 -> 12.942926 | P38: =MIN(Parametri!$B$81+Parametri!$B$82, Parametri!$B$81+Parametri!$B$82*(B38+1)/Parametri!$B$83) -> 12.5 | Q38: =-IF(B38<10,Parametri!$B$51,IF(B38<20,Parametri!$B$54,Parametri!$B$57))*M38*G38/1000 -> -47.936764 | R38: =-Q38-Z38 -> 47.936764 | S38: =S37+R38 -> 945.39511 | T38: =-(Parametri!$B$86*(Parametri!$B$87*Parametri!$B$90+Parametri!$B$88*Parametri!$B$91+Parametri!$B$89*Parametri!$B$92)/1000000000)*MIN(B38+1,Parametri!$B$93) -> -2.85975 | U38: =IF(B38<Parametri!$B$125,Parametri!$B$46,IF(B38<Parametri!$B$126,Parametri!$B$47,Parametri!$B$48))*Parametri!$B$96*13/1000000000*((B38+1)*Parametri!$B$121+B38*(B38+1)/2*Parametri!$B$122) -> 114.03223 | V38: =IF(B38>=Parametri!$B$103-1,Parametri!$B$102*(1-Parametri!$B$127)^(B38-(Parametri!$B$103-1)),0) -> 3.6437356 | W38: =IF(B38>=Parametri!$B$105-1,Parametri!$B$104,0) -> 5 | X38: =IF(B38>=Parametri!$B$107-1,Parametri!$B$106+Parametri!$B$128*INT((B38-(Parametri!$B$107-1))/2),0) -> 4.99 | Y38: =IF(AND(B38>=Parametri!$B$109-1,B38<Parametri!$B$109-1+Parametri!$B$140),Parametri!$B$108,0) -> 0 | Z38: =IF(B38<10,Parametri!$B$52,IF(B38<20,Parametri!$B$55,0))*M38*G38/1000 -> 0 | AA38: =Parametri!$B$159*Parametri!$B$160 -> 0 | AB38: =(SUM(Z$5:Z38)+SUM(AA$5:AA38)-SUM(Z$5:Z23)-SUM(AA$5:AA23)) -> 8.374022 | AC38: =-(Parametri!$B$67*SUM(Z$5:Z38)+Parametri!$B$161*SUM(AA$5:AA38)) -> -1.888875 | AD38: =-Z23-AA23 -> -8.1736638 | AE38: =Z38+AA38+N38+O38+P38+Q38+T38+U38+V38+W38+X38+Y38+AC38+AD38 -> 92.249843 | AF38: =AF37+AE38 -> 1395.6334 | AG38: =-AF38/F38 -> -0.47963162 | AH38: =SUM(Z$5:Z38)-SUM(Z$5:Z23) -> 8.374022 | AI38: =-Z23 -> -8.1736638

Sheet Dinamica
A1: Foglio Dinamica — scenari reali (€ 2027)
A2: Unità: €miliardi reali (prezzi 2027)
A3: Col A = — | Col B = r_BRDP_r | Col C = rf_r
A4: Scenario | B4: r_BRDP_r | C4: rf_r | D4: 2027 | E4: 2028 | F4: 2029 | G4: 2030 | H4: 2031 | I4: 2032 | J4: 2033 | K4: 2034 | L4: 2035 | M4: 2036 | N4: 2037 | O4: 2038 | P4: 2039 | Q4: 2040 | R4: 2041 | S4: 2042 | T4: 2043 | U4: 2044 | V4: 2045 | W4: 2046 | X4: 2047 | Y4: 2048 | Z4: 2049 | AA4: 2050 | AB4: 2051 | AC4: 2052 | AD4: 2053 | AE4: 2054 | AF4: 2055 | AG4: 2056 | AH4: 2057 | AI4: 2058 | AJ4: 2059 | AK4: 2060
A5: FP_reale (=Modello!R) | D5: =Modello!$R5 -> 6.1677 | E5: =Modello!$R6 -> 7.2030255 | F5: =Modello!$R7 -> 8.2459735 | G5: =Modello!$R8 -> 9.2966541 | H5: =Modello!$R9 -> 10.355178 | I5: =Modello!$R10 -> 11.421657 | J5: =Modello!$R11 -> 11.782862 | K5: =Modello!$R12 -> 12.146877 | L5: =Modello!$R13 -> 12.51374 | M5: =Modello!$R14 -> 12.883486 | N5: =Modello!$R15 -> 19.884232 | O5: =Modello!$R16 -> 20.447676 | P5: =Modello!$R17 -> 21.015616 | Q5: =Modello!$R18 -> 21.588113 | R5: =Modello!$R19 -> 22.165223 | S5: =Modello!$R20 -> 22.747007 | T5: =Modello!$R21 -> 23.333523 | U5: =Modello!$R22 -> 23.924831 | V5: =Modello!$R23 -> 24.520992 | W5: =Modello!$R24 -> 25.122066 | X5: =Modello!$R25 -> 38.592173 | Y5: =Modello!$R26 -> 39.508802 | Z5: =Modello!$R27 -> 40.433081 | AA5: =Modello!$R28 -> 41.365102 | AB5: =Modello!$R29 -> 42.304963 | AC5: =Modello!$R30 -> 43.252758 | AD5: =Modello!$R31 -> 44.208584 | AE5: =Modello!$R32 -> 45.17254 | AF5: =Modello!$R33 -> 46.144722 | AG5: =Modello!$R34 -> 47.125232 | AH5: =Modello!$R35 -> 47.325411 | AI5: =Modello!$R36 -> 47.527385 | AJ5: =Modello!$R37 -> 47.731165 | AK5: =Modello!$R38 -> 47.936764
A6: SK_reale (=Modello!Z) | D6: =Modello!Z5 -> 3.08385 | E6: =Modello!Z6 -> 3.6015127 | F6: =Modello!Z7 -> 4.1229868 | G6: =Modello!Z8 -> 4.648327 | H6: =Modello!Z9 -> 5.1775889 | I6: =Modello!Z10 -> 5.7108283 | J6: =Modello!Z11 -> 5.891431 | K6: =Modello!Z12 -> 6.0734387 | L6: =Modello!Z13 -> 6.2568698 | M6: =Modello!Z14 -> 6.4417431 | N6: =Modello!Z15 -> 6.6280775 | O6: =Modello!Z16 -> 6.8158919 | P6: =Modello!Z17 -> 7.0052055 | Q6: =Modello!Z18 -> 7.1960376 | R6: =Modello!Z19 -> 7.3884078 | S6: =Modello!Z20 -> 7.5823356 | T6: =Modello!Z21 -> 7.7778409 | U6: =Modello!Z22 -> 7.9749436 | V6: =Modello!Z23 -> 8.1736638 | W6: =Modello!Z24 -> 8.374022 | X6: =Modello!Z25 -> 0 | Y6: =Modello!Z26 -> 0 | Z6: =Modello!Z27 -> 0 | AA6: =Modello!Z28 -> 0 | AB6: =Modello!Z29 -> 0 | AC6: =Modello!Z30 -> 0 | AD6: =Modello!Z31 -> 0 | AE6: =Modello!Z32 -> 0 | AF6: =Modello!Z33 -> 0 | AG6: =Modello!Z34 -> 0 | AH6: =Modello!Z35 -> 0 | AI6: =Modello!Z36 -> 0 | AJ6: =Modello!Z37 -> 0 | AK6: =Modello!Z38 -> 0
A8: SEZIONE I — Montante fondi pensione P2 (€mld reali €2027)
A9: Ia: Montante P2 (scenario r_BRDP_r, rf_r) | B9: r_BRDP_r | C9: rf_r | D9: 2027 | E9: 2028 | F9: 2029 | G9: 2030 | H9: 2031 | I9: 2032 | J9: 2033 | K9: 2034 | L9: 2035 | M9: 2036 | N9: 2037 | O9: 2038 | P9: 2039 | Q9: 2040 | R9: 2041 | S9: 2042 | T9: 2043 | U9: 2044 | V9: 2045 | W9: 2046 | X9: 2047 | Y9: 2048 | Z9: 2049 | AA9: 2050 | AB9: 2051 | AC9: 2052 | AD9: 2053 | AE9: 2054 | AF9: 2055 | AG9: 2056 | AH9: 2057 | AI9: 2058 | AJ9: 2059 | AK9: 2060
A10: r_BRDP=0.75%, rf=0.500% | B10: 0.0075 | C10: 0.005 | D10: =D5 -> 6.1677 | E10: =D10*(1+$C10)+E5+Modello!AH5*$B10-Modello!AI6 -> 13.424693 | F10: =E10*(1+$C10)+F5+Modello!AH6*$B10-Modello!AI7 -> 21.78793 | G10: =F10*(1+$C10)+G5+Modello!AH7*$B10-Modello!AI8 -> 31.274586 | H10: =G10*(1+$C10)+H5+Modello!AH8*$B10-Modello!AI9 -> 41.902062 | I10: =H10*(1+$C10)+I5+Modello!AH9*$B10-Modello!AI10 -> 53.687986 | J10: =I10*(1+$C10)+J5+Modello!AH10*$B10-Modello!AI11 -> 65.936876 | K10: =J10*(1+$C10)+K5+Modello!AH11*$B10-Modello!AI12 -> 78.655212 | L10: =K10*(1+$C10)+L5+Modello!AH12*$B10-Modello!AI13 -> 91.849552 | M10: =L10*(1+$C10)+M5+Modello!AH13*$B10-Modello!AI14 -> 105.52654 | N10: =M10*(1+$C10)+N5+Modello!AH14*$B10-Modello!AI15 -> 126.32097 | O10: =N10*(1+$C10)+O5+Modello!AH15*$B10-Modello!AI16 -> 147.83252 | P10: =O10*(1+$C10)+P5+Modello!AH16*$B10-Modello!AI17 -> 170.0707 | Q10: =P10*(1+$C10)+Q5+Modello!AH17*$B10-Modello!AI18 -> 193.04509 | R10: =Q10*(1+$C10)+R5+Modello!AH18*$B10-Modello!AI19 -> 216.76545 | S10: =R10*(1+$C10)+S5+Modello!AH19*$B10-Modello!AI20 -> 244.32545 | T10: =S10*(1+$C10)+T5+Modello!AH20*$B10-Modello!AI21 -> 273.16117 | U10: =T10*(1+$C10)+U5+Modello!AH21*$B10-Modello!AI22 -> 303.28517 | V10: =U10*(1+$C10)+V5+Modello!AH22*$B10-Modello!AI23 -> 334.71018 | W10: =V10*(1+$C10)+W5+Modello!AH23*$B10-Modello!AI24 -> 367.44909 | X10: =W10*(1+$C10)+X5+Modello!AH24*$B10-Modello!AI25 -> 414.37902 | Y10: =X10*(1+$C10)+Y5+Modello!AH25*$B10-Modello!AI26 -> 462.598 | Z10: =Y10*(1+$C10)+Z5+Modello!AH26*$B10-Modello!AI27 -> 512.12017 | AA10: =Z10*(1+$C10)+AA5+Modello!AH27*$B10-Modello!AI28 -> 562.95985 | AB10: =AA10*(1+$C10)+AB5+Modello!AH28*$B10-Modello!AI29 -> 615.13155 | AC10: =AB10*(1+$C10)+AC5+Modello!AH29*$B10-Modello!AI30 -> 668.64991 | AD10: =AC10*(1+$C10)+AD5+Modello!AH30*$B10-Modello!AI31 -> 723.5298 | AE10: =AD10*(1+$C10)+AE5+Modello!AH31*$B10-Modello!AI32 -> 779.78624 | AF10: =AE10*(1+$C10)+AF5+Modello!AH32*$B10-Modello!AI33 -> 837.43443 | AG10: =AF10*(1+$C10)+AG5+Modello!AH33*$B10-Modello!AI34 -> 896.48978 | AH10: =AG10*(1+$C10)+AH5+Modello!AH34*$B10-Modello!AI35 -> 956.1791 | AI10: =AH10*(1+$C10)+AI5+Modello!AH35*$B10-Modello!AI36 -> 1016.5075 | AJ10: =AI10*(1+$C10)+AJ5+Modello!AH36*$B10-Modello!AI37 -> 1077.48 | AK10: =AJ10*(1+$C10)+AK5+Modello!AH37*$B10-Modello!AI38 -> 1139.102
A11: r_BRDP=0.75%, rf=1.250% | B11: 0.0075 | C11: 0.0125 | D11: =D5 -> 6.1677 | E11: =D11*(1+$C11)+E5+Modello!AH5*$B11-Modello!AI6 -> 13.470951 | F11: =E11*(1+$C11)+F5+Modello!AH6*$B11-Modello!AI7 -> 21.935451 | G11: =F11*(1+$C11)+G5+Modello!AH7*$B11-Modello!AI8 -> 31.587361 | H11: =G11*(1+$C11)+H5+Modello!AH8*$B11-Modello!AI9 -> 42.453306 | I11: =H11*(1+$C11)+I5+Modello!AH9*$B11-Modello!AI10 -> 54.560386 | J11: =I11*(1+$C11)+J5+Modello!AH10*$B11-Modello!AI11 -> 67.222841 | K11: =J11*(1+$C11)+K5+Modello!AH11*$B11-Modello!AI12 -> 80.451778 | L11: =K11*(1+$C11)+L5+Modello!AH12*$B11-Modello!AI13 -> 94.258489 | M11: =L11*(1+$C11)+M5+Modello!AH13*$B11-Modello!AI14 -> 108.65446 | N11: =M11*(1+$C11)+N5+Modello!AH14*$B11-Modello!AI15 -> 130.27944 | O11: =N11*(1+$C11)+O5+Modello!AH15*$B11-Modello!AI16 -> 152.78788 | P11: =O11*(1+$C11)+P5+Modello!AH16*$B11-Modello!AI17 -> 176.19674 | Q11: =P11*(1+$C11)+Q5+Modello!AH17*$B11-Modello!AI18 -> 200.52324 | R11: =Q11*(1+$C11)+R5+Modello!AH18*$B11-Modello!AI19 -> 225.78491 | S11: =R11*(1+$C11)+S5+Modello!AH19*$B11-Modello!AI20 -> 255.08339 | T11: =S11*(1+$C11)+T5+Modello!AH20*$B11-Modello!AI21 -> 285.88603 | U11: =T11*(1+$C11)+U5+Modello!AH21*$B11-Modello!AI22 -> 318.2178 | V11: =U11*(1+$C11)+V5+Modello!AH22*$B11-Modello!AI23 -> 352.10411 | W11: =V11*(1+$C11)+W5+Modello!AH23*$B11-Modello!AI24 -> 387.57077 | X11: =W11*(1+$C11)+X5+Modello!AH24*$B11-Modello!AI25 -> 437.50809 | Y11: =X11*(1+$C11)+Y5+Modello!AH25*$B11-Modello!AI26 -> 489.12402 | Z11: =Y11*(1+$C11)+Z5+Modello!AH26*$B11-Modello!AI27 -> 542.44725 | AA11: =Z11*(1+$C11)+AA5+Modello!AH27*$B11-Modello!AI28 -> 597.50693 | AB11: =AA11*(1+$C11)+AB5+Modello!AH28*$B11-Modello!AI29 -> 654.33266 | AC11: =AB11*(1+$C11)+AC5+Modello!AH29*$B11-Modello!AI30 -> 712.95452 | AD11: =AC11*(1+$C11)+AD5+Modello!AH30*$B11-Modello!AI31 -> 773.40309 | AE11: =AD11*(1+$C11)+AE5+Modello!AH31*$B11-Modello!AI32 -> 835.70942 | AF11: =AE11*(1+$C11)+AF5+Modello!AH32*$B11-Modello!AI33 -> 899.90505 | AG11: =AF11*(1+$C11)+AG5+Modello!AH33*$B11-Modello!AI34 -> 966.02204 | AH11: =AG11*(1+$C11)+AH5+Modello!AH34*$B11-Modello!AI35 -> 1033.3042 | AI11: =AH11*(1+$C11)+AI5+Modello!AH35*$B11-Modello!AI36 -> 1101.768 | AJ11: =AI11*(1+$C11)+AJ5+Modello!AH36*$B11-Modello!AI37 -> 1171.4301 | AK11: =AJ11*(1+$C11)+AK5+Modello!AH37*$B11-Modello!AI38 -> 1242.3075
A12: r_BRDP=0.75%, rf=2.500% | B12: 0.0075 | C12: 0.025 | D12: =D5 -> 6.1677 | E12: =D12*(1+$C12)+E5+Modello!AH5*$B12-Modello!AI6 -> 13.548047 | F12: =E12*(1+$C12)+F5+Modello!AH6*$B12-Modello!AI7 -> 22.182862 | G12: =F12*(1+$C12)+G5+Modello!AH7*$B12-Modello!AI8 -> 32.11515 | H12: =G12*(1+$C12)+H5+Modello!AH8*$B12-Modello!AI9 -> 43.389132 | I12: =H12*(1+$C12)+I5+Modello!AH9*$B12-Modello!AI10 -> 56.050274 | J12: =I12*(1+$C12)+J5+Modello!AH10*$B12-Modello!AI11 -> 69.431981 | K12: =J12*(1+$C12)+K5+Modello!AH11*$B12-Modello!AI12 -> 83.556431 | L12: =K12*(1+$C12)+L5+Modello!AH12*$B12-Modello!AI13 -> 98.446406 | M12: =L12*(1+$C12)+M5+Modello!AH13*$B12-Modello!AI14 -> 114.1253 | N12: =M12*(1+$C12)+N5+Modello!AH14*$B12-Modello!AI15 -> 137.24523 | O12: =N12*(1+$C12)+O5+Modello!AH15*$B12-Modello!AI16 -> 161.55631 | P12: =O12*(1+$C12)+P5+Modello!AH16*$B12-Modello!AI17 -> 187.09423 | Q12: =P12*(1+$C12)+Q5+Modello!AH17*$B12-Modello!AI18 -> 213.89563 | R12: =Q12*(1+$C12)+R5+Modello!AH18*$B12-Modello!AI19 -> 241.99815 | S12: =R12*(1+$C12)+S5+Modello!AH19*$B12-Modello!AI20 -> 274.52428 | T12: =S12*(1+$C12)+T5+Modello!AH20*$B12-Modello!AI21 -> 309.00148 | U12: =T12*(1+$C12)+U5+Modello!AH21*$B12-Modello!AI22 -> 345.48471 | V12: =U12*(1+$C12)+V5+Modello!AH22*$B12-Modello!AI23 -> 384.03041 | W12: =V12*(1+$C12)+W5+Modello!AH23*$B12-Modello!AI24 -> 424.69654 | X12: =W12*(1+$C12)+X5+Modello!AH24*$B12-Modello!AI25 -> 480.40663 | Y12: =X12*(1+$C12)+Y5+Modello!AH25*$B12-Modello!AI26 -> 538.56388 | Z12: =Y12*(1+$C12)+Z5+Modello!AH26*$B12-Modello!AI27 -> 599.23716 | AA12: =Z12*(1+$C12)+AA5+Modello!AH27*$B12-Modello!AI28 -> 662.49717 | AB12: =AA12*(1+$C12)+AB5+Modello!AH28*$B12-Modello!AI29 -> 728.41649 | AC12: =AB12*(1+$C12)+AC5+Modello!AH29*$B12-Modello!AI30 -> 797.06961 | AD12: =AC12*(1+$C12)+AD5+Modello!AH30*$B12-Modello!AI31 -> 868.53299 | AE12: =AD12*(1+$C12)+AE5+Modello!AH31*$B12-Modello!AI32 -> 942.88511 | AF12: =AE12*(1+$C12)+AF5+Modello!AH32*$B12-Modello!AI33 -> 1020.2065 | AG12: =AF12*(1+$C12)+AG5+Modello!AH33*$B12-Modello!AI34 -> 1100.5798 | AH12: =AG12*(1+$C12)+AH5+Modello!AH34*$B12-Modello!AI35 -> 1183.3012 | AI12: =AH12*(1+$C12)+AI5+Modello!AH35*$B12-Modello!AI36 -> 1268.4312 | AJ12: =AI12*(1+$C12)+AJ5+Modello!AH36*$B12-Modello!AI37 -> 1356.032 | AK12: =AJ12*(1+$C12)+AK5+Modello!AH37*$B12-Modello!AI38 -> 1446.1674
A13: r_BRDP=0.75%, rf=4.000% | B13: 0.0075 | C13: 0.04 | D13: =D5 -> 6.1677 | E13: =D13*(1+$C13)+E5+Modello!AH5*$B13-Modello!AI6 -> 13.640562 | F13: =E13*(1+$C13)+F5+Modello!AH6*$B13-Modello!AI7 -> 22.482299 | G13: =F13*(1+$C13)+G5+Modello!AH7*$B13-Modello!AI8 -> 32.759307 | H13: =G13*(1+$C13)+H5+Modello!AH8*$B13-Modello!AI9 -> 44.540782 | I13: =H13*(1+$C13)+I5+Modello!AH9*$B13-Modello!AI10 -> 57.898827 | J13: =I13*(1+$C13)+J5+Modello!AH10*$B13-Modello!AI11 -> 72.195231 | K13: =J13*(1+$C13)+K5+Modello!AH11*$B13-Modello!AI12 -> 87.471691 | L13: =K13*(1+$C13)+L5+Modello!AH12*$B13-Modello!AI13 -> 103.77162 | M13: =L13*(1+$C13)+M5+Modello!AH13*$B13-Modello!AI14 -> 121.14023 | N13: =M13*(1+$C13)+N5+Modello!AH14*$B13-Modello!AI15 -> 146.25263 | O13: =N13*(1+$C13)+O5+Modello!AH15*$B13-Modello!AI16 -> 172.98269 | P13: =O13*(1+$C13)+P5+Modello!AH16*$B13-Modello!AI17 -> 201.401 | Q13: =P13*(1+$C13)+Q5+Modello!AH17*$B13-Modello!AI18 -> 231.58109 | R13: =Q13*(1+$C13)+R5+Modello!AH18*$B13-Modello!AI19 -> 263.59946 | S13: =R13*(1+$C13)+S5+Modello!AH19*$B13-Modello!AI20 -> 300.61961 | T13: =S13*(1+$C13)+T5+Modello!AH20*$B13-Modello!AI21 -> 340.25849 | U13: =T13*(1+$C13)+U5+Modello!AH21*$B13-Modello!AI22 -> 382.62702 | V13: =U13*(1+$C13)+V5+Modello!AH22*$B13-Modello!AI23 -> 427.84069 | W13: =V13*(1+$C13)+W5+Modello!AH23*$B13-Modello!AI24 -> 476.01968 | X13: =W13*(1+$C13)+X5+Modello!AH24*$B13-Modello!AI25 -> 540.15315 | Y13: =X13*(1+$C13)+Y5+Modello!AH25*$B13-Modello!AI26 -> 607.90636 | Z13: =Y13*(1+$C13)+Z5+Modello!AH26*$B13-Modello!AI27 -> 679.43179 | AA13: =Z13*(1+$C13)+AA5+Modello!AH27*$B13-Modello!AI28 -> 754.88815 | AB13: =AA13*(1+$C13)+AB5+Modello!AH28*$B13-Modello!AI29 -> 834.44057 | AC13: =AB13*(1+$C13)+AC5+Modello!AH29*$B13-Modello!AI30 -> 918.2609 | AD13: =AC13*(1+$C13)+AD5+Modello!AH30*$B13-Modello!AI31 -> 1006.528 | AE13: =AD13*(1+$C13)+AE5+Modello!AH31*$B13-Modello!AI32 -> 1099.4279 | AF13: =AE13*(1+$C13)+AF5+Modello!AH32*$B13-Modello!AI33 -> 1197.1543 | AG13: =AF13*(1+$C13)+AG5+Modello!AH33*$B13-Modello!AI34 -> 1299.9086 | AH13: =AG13*(1+$C13)+AH5+Modello!AH34*$B13-Modello!AI35 -> 1407.1118 | AI13: =AH13*(1+$C13)+AI5+Modello!AH35*$B13-Modello!AI36 -> 1518.9438 | AJ13: =AI13*(1+$C13)+AJ5+Modello!AH36*$B13-Modello!AI37 -> 1635.5915 | AK13: =AJ13*(1+$C13)+AK5+Modello!AH37*$B13-Modello!AI38 -> 1757.2497
A14: r_BRDP=1.50%, rf=0.500% | B14: 0.015 | C14: 0.005 | D14: =D5 -> 6.1677 | E14: =D14*(1+$C14)+E5+Modello!AH5*$B14-Modello!AI6 -> 13.447822 | F14: =E14*(1+$C14)+F5+Modello!AH6*$B14-Modello!AI7 -> 21.861315 | G14: =F14*(1+$C14)+G5+Modello!AH7*$B14-Modello!AI8 -> 31.429401 | H14: =G14*(1+$C14)+H5+Modello!AH8*$B14-Modello!AI9 -> 42.173576 | I14: =H14*(1+$C14)+I5+Modello!AH9*$B14-Modello!AI10 -> 54.115614 | J14: =I14*(1+$C14)+J5+Modello!AH10*$B14-Modello!AI11 -> 66.564231 | K14: =J14*(1+$C14)+K5+Modello!AH11*$B14-Modello!AI12 -> 79.527477 | L14: =K14*(1+$C14)+L5+Modello!AH12*$B14-Modello!AI13 -> 93.013503 | M14: =L14*(1+$C14)+M5+Modello!AH13*$B14-Modello!AI14 -> 107.03056 | N14: =M14*(1+$C14)+N5+Modello!AH14*$B14-Modello!AI15 -> 128.21507 | O14: =N14*(1+$C14)+O5+Modello!AH15*$B14-Modello!AI16 -> 150.16837 | P14: =O14*(1+$C14)+P5+Modello!AH16*$B14-Modello!AI17 -> 172.90162 | Q14: =P14*(1+$C14)+Q5+Modello!AH17*$B14-Modello!AI18 -> 196.42611 | R14: =Q14*(1+$C14)+R5+Modello!AH18*$B14-Modello!AI19 -> 220.75327 | S14: =R14*(1+$C14)+S5+Modello!AH19*$B14-Modello!AI20 -> 248.97852 | T14: =S14*(1+$C14)+T5+Modello!AH20*$B14-Modello!AI21 -> 278.51656 | U14: =T14*(1+$C14)+U5+Modello!AH21*$B14-Modello!AI22 -> 309.37772 | V14: =U14*(1+$C14)+V5+Modello!AH22*$B14-Modello!AI23 -> 341.57246 | W14: =V14*(1+$C14)+W5+Modello!AH23*$B14-Modello!AI24 -> 375.11139 | X14: =W14*(1+$C14)+X5+Modello!AH24*$B14-Modello!AI25 -> 422.86931 | Y14: =X14*(1+$C14)+Y5+Modello!AH25*$B14-Modello!AI26 -> 471.87759 | Z14: =Y14*(1+$C14)+Z5+Modello!AH26*$B14-Modello!AI27 -> 522.14882 | AA14: =Z14*(1+$C14)+AA5+Modello!AH27*$B14-Modello!AI28 -> 573.69577 | AB14: =AA14*(1+$C14)+AB5+Modello!AH28*$B14-Modello!AI29 -> 626.53132 | AC14: =AB14*(1+$C14)+AC5+Modello!AH29*$B14-Modello!AI30 -> 680.66856 | AD14: =AC14*(1+$C14)+AD5+Modello!AH30*$B14-Modello!AI31 -> 736.12071 | AE14: =AD14*(1+$C14)+AE5+Modello!AH31*$B14-Modello!AI32 -> 792.90114 | AF14: =AE14*(1+$C14)+AF5+Modello!AH32*$B14-Modello!AI33 -> 851.02342 | AG14: =AF14*(1+$C14)+AG5+Modello!AH33*$B14-Modello!AI34 -> 910.50124 | AH14: =AG14*(1+$C14)+AH5+Modello!AH34*$B14-Modello!AI35 -> 970.55973 | AI14: =AH14*(1+$C14)+AI5+Modello!AH35*$B14-Modello!AI36 -> 1031.2023 | AJ14: =AI14*(1+$C14)+AJ5+Modello!AH36*$B14-Modello!AI37 -> 1092.4322 | AK14: =AJ14*(1+$C14)+AK5+Modello!AH37*$B14-Modello!AI38 -> 1154.253
A15: r_BRDP=1.50%, rf=1.250% | B15: 0.015 | C15: 0.0125 | D15: =D5 -> 6.1677 | E15: =D15*(1+$C15)+E5+Modello!AH5*$B15-Modello!AI6 -> 13.494079 | F15: =E15*(1+$C15)+F5+Modello!AH6*$B15-Modello!AI7 -> 22.009009 | G15: =F15*(1+$C15)+G5+Modello!AH7*$B15-Modello!AI8 -> 31.742901 | H15: =G15*(1+$C15)+H5+Modello!AH8*$B15-Modello!AI9 -> 42.726716 | I15: =H15*(1+$C15)+I5+Modello!AH9*$B15-Modello!AI10 -> 54.99197 | J15: =I15*(1+$C15)+J5+Modello!AH10*$B15-Modello!AI11 -> 67.857408 | K15: =J15*(1+$C15)+K5+Modello!AH11*$B15-Modello!AI12 -> 81.336051 | L15: =K15*(1+$C15)+L5+Modello!AH12*$B15-Modello!AI13 -> 95.441141 | M15: =L15*(1+$C15)+M5+Modello!AH13*$B15-Modello!AI14 -> 110.18614 | N15: =M15*(1+$C15)+N5+Modello!AH14*$B15-Modello!AI15 -> 132.21283 | O15: =N15*(1+$C15)+O5+Modello!AH15*$B15-Modello!AI16 -> 155.17772 | P15: =O15*(1+$C15)+P5+Modello!AH16*$B15-Modello!AI17 -> 179.09984 | Q15: =P15*(1+$C15)+Q5+Modello!AH17*$B15-Modello!AI18 -> 203.99857 | R15: =Q15*(1+$C15)+R5+Modello!AH18*$B15-Modello!AI19 -> 229.89358 | S15: =R15*(1+$C15)+S5+Modello!AH19*$B15-Modello!AI20 -> 259.88874 | T15: =S15*(1+$C15)+T5+Modello!AH20*$B15-Modello!AI21 -> 291.4305 | U15: =T15*(1+$C15)+U5+Modello!AH21*$B15-Modello!AI22 -> 324.54195 | V15: =U15*(1+$C15)+V5+Modello!AH22*$B15-Modello!AI23 -> 359.24658 | W15: =V15*(1+$C15)+W5+Modello!AH23*$B15-Modello!AI24 -> 395.56823 | X15: =W15*(1+$C15)+X5+Modello!AH24*$B15-Modello!AI25 -> 446.3952 | Y15: =X15*(1+$C15)+Y5+Modello!AH25*$B15-Modello!AI26 -> 498.86907 | Z15: =Y15*(1+$C15)+Z5+Modello!AH26*$B15-Modello!AI27 -> 553.01678 | AA15: =Z15*(1+$C15)+AA5+Modello!AH27*$B15-Modello!AI28 -> 608.86568 | AB15: =AA15*(1+$C15)+AB5+Modello!AH28*$B15-Modello!AI29 -> 666.44358 | AC15: =AB15*(1+$C15)+AC5+Modello!AH29*$B15-Modello!AI30 -> 725.77871 | AD15: =AC15*(1+$C15)+AD5+Modello!AH30*$B15-Modello!AI31 -> 786.89975 | AE15: =AD15*(1+$C15)+AE5+Modello!AH31*$B15-Modello!AI32 -> 849.83582 | AF15: =AE15*(1+$C15)+AF5+Modello!AH32*$B15-Modello!AI33 -> 914.61654 | AG15: =AF15*(1+$C15)+AG5+Modello!AH33*$B15-Modello!AI34 -> 981.27196 | AH15: =AG15*(1+$C15)+AH5+Modello!AH34*$B15-Modello!AI35 -> 1049.0438 | AI15: =AH15*(1+$C15)+AI5+Modello!AH35*$B15-Modello!AI36 -> 1117.9466 | AJ15: =AI15*(1+$C15)+AJ5+Modello!AH36*$B15-Modello!AI37 -> 1187.9949 | AK15: =AJ15*(1+$C15)+AK5+Modello!AH37*$B15-Modello!AI38 -> 1259.2035
A16: r_BRDP=1.50%, rf=2.500% | B16: 0.015 | C16: 0.025 | D16: =D5 -> 6.1677 | E16: =D16*(1+$C16)+E5+Modello!AH5*$B16-Modello!AI6 -> 13.571176 | F16: =E16*(1+$C16)+F5+Modello!AH6*$B16-Modello!AI7 -> 22.256709 | G16: =F16*(1+$C16)+G5+Modello!AH7*$B16-Modello!AI8 -> 32.271906 | H16: =G16*(1+$C16)+H5+Modello!AH8*$B16-Modello!AI9 -> 43.665732 | I16: =H16*(1+$C16)+I5+Modello!AH9*$B16-Modello!AI10 -> 56.488546 | J16: =I16*(1+$C16)+J5+Modello!AH10*$B16-Modello!AI11 -> 70.078798 | K16: =J16*(1+$C16)+K5+Modello!AH11*$B16-Modello!AI12 -> 84.461193 | L16: =K16*(1+$C16)+L5+Modello!AH12*$B16-Modello!AI13 -> 99.661112 | M16: =L16*(1+$C16)+M5+Modello!AH13*$B16-Modello!AI14 -> 115.70463 | N16: =M16*(1+$C16)+N5+Modello!AH14*$B16-Modello!AI15 -> 139.2466 | O16: =N16*(1+$C16)+O5+Modello!AH15*$B16-Modello!AI16 -> 164.04 | P16: =O16*(1+$C16)+P5+Modello!AH16*$B16-Modello!AI17 -> 190.1234 | Q16: =P16*(1+$C16)+Q5+Modello!AH17*$B16-Modello!AI18 -> 217.53646 | R16: =Q16*(1+$C16)+R5+Modello!AH18*$B16-Modello!AI19 -> 246.31991 | S16: =R16*(1+$C16)+S5+Modello!AH19*$B16-Modello!AI20 -> 279.59939 | T16: =S16*(1+$C16)+T5+Modello!AH20*$B16-Modello!AI21 -> 314.88252 | U16: =T16*(1+$C16)+U5+Modello!AH21*$B16-Modello!AI22 -> 352.22316 | V16: =U16*(1+$C16)+V5+Modello!AH22*$B16-Modello!AI23 -> 391.67659 | W16: =V16*(1+$C16)+W5+Modello!AH23*$B16-Modello!AI24 -> 433.29958 | X16: =W16*(1+$C16)+X5+Modello!AH24*$B16-Modello!AI25 -> 490.01443 | Y16: =X16*(1+$C16)+Y5+Modello!AH25*$B16-Modello!AI26 -> 549.15872 | Z16: =Y16*(1+$C16)+Z5+Modello!AH26*$B16-Modello!AI27 -> 610.79953 | AA16: =Z16*(1+$C16)+AA5+Modello!AH27*$B16-Modello!AI28 -> 675.00572 | AB16: =AA16*(1+$C16)+AB5+Modello!AH28*$B16-Modello!AI29 -> 741.84794 | AC16: =AB16*(1+$C16)+AC5+Modello!AH29*$B16-Modello!AI30 -> 811.39872 | AD16: =AC16*(1+$C16)+AD5+Modello!AH30*$B16-Modello!AI31 -> 883.73249 | AE16: =AD16*(1+$C16)+AE5+Modello!AH31*$B16-Modello!AI32 -> 958.92564 | AF16: =AE16*(1+$C16)+AF5+Modello!AH32*$B16-Modello!AI33 -> 1037.0565 | AG16: =AF16*(1+$C16)+AG5+Modello!AH33*$B16-Modello!AI34 -> 1118.2057 | AH16: =AG16*(1+$C16)+AH5+Modello!AH34*$B16-Modello!AI35 -> 1201.6668 | AI16: =AH16*(1+$C16)+AI5+Modello!AH35*$B16-Modello!AI36 -> 1287.4982 | AJ16: =AI16*(1+$C16)+AJ5+Modello!AH36*$B16-Modello!AI37 -> 1375.7596 | AK16: =AJ16*(1+$C16)+AK5+Modello!AH37*$B16-Modello!AI38 -> 1466.5122
A17: r_BRDP=1.50%, rf=4.000% | B17: 0.015 | C17: 0.04 | D17: =D5 -> 6.1677 | E17: =D17*(1+$C17)+E5+Modello!AH5*$B17-Modello!AI6 -> 13.663691 | F17: =E17*(1+$C17)+F5+Modello!AH6*$B17-Modello!AI7 -> 22.556493 | G17: =F17*(1+$C17)+G5+Modello!AH7*$B17-Modello!AI8 -> 32.917532 | H17: =G17*(1+$C17)+H5+Modello!AH8*$B17-Modello!AI9 -> 44.821261 | I17: =H17*(1+$C17)+I5+Modello!AH9*$B17-Modello!AI10 -> 58.345282 | J17: =I17*(1+$C17)+J5+Modello!AH10*$B17-Modello!AI11 -> 72.857132 | K17: =J17*(1+$C17)+K5+Modello!AH11*$B17-Modello!AI12 -> 88.401842 | L17: =K17*(1+$C17)+L5+Modello!AH12*$B17-Modello!AI13 -> 105.02631 | M17: =L17*(1+$C17)+M5+Modello!AH13*$B17-Modello!AI14 -> 122.77935 | N17: =M17*(1+$C17)+N5+Modello!AH14*$B17-Modello!AI15 -> 148.33988 | O17: =N17*(1+$C17)+O5+Modello!AH15*$B17-Modello!AI16 -> 175.5857 | P17: =O17*(1+$C17)+P5+Modello!AH16*$B17-Modello!AI17 -> 204.59153 | Q17: =P17*(1+$C17)+Q5+Modello!AH17*$B17-Modello!AI18 -> 235.43517 | R17: =Q17*(1+$C17)+R5+Modello!AH18*$B17-Modello!AI19 -> 268.19761 | S17: =R17*(1+$C17)+S5+Modello!AH19*$B17-Modello!AI20 -> 306.04701 | T17: =S17*(1+$C17)+T5+Modello!AH20*$B17-Modello!AI21 -> 346.58203 | U17: =T17*(1+$C17)+U5+Modello!AH21*$B17-Modello!AI22 -> 389.91389 | V17: =U17*(1+$C17)+V5+Modello!AH22*$B17-Modello!AI23 -> 436.15829 | W17: =V17*(1+$C17)+W5+Modello!AH23*$B17-Modello!AI24 -> 485.4357 | X17: =W17*(1+$C17)+X5+Modello!AH24*$B17-Modello!AI25 -> 550.73549 | Y17: =X17*(1+$C17)+Y5+Modello!AH25*$B17-Modello!AI26 -> 619.65884 | Z17: =Y17*(1+$C17)+Z5+Modello!AH26*$B17-Modello!AI27 -> 692.35704 | AA17: =Z17*(1+$C17)+AA5+Modello!AH27*$B17-Modello!AI28 -> 768.98752 | AB17: =AA17*(1+$C17)+AB5+Modello!AH28*$B17-Modello!AI29 -> 849.7141 | AC17: =AB17*(1+$C17)+AC5+Modello!AH29*$B17-Modello!AI30 -> 934.70724 | AD17: =AC17*(1+$C17)+AD5+Modello!AH30*$B17-Modello!AI31 -> 1024.1443 | AE17: =AD17*(1+$C17)+AE5+Modello!AH31*$B17-Modello!AI32 -> 1118.2099 | AF17: =AE17*(1+$C17)+AF5+Modello!AH32*$B17-Modello!AI33 -> 1217.0961 | AG17: =AF17*(1+$C17)+AG5+Modello!AH33*$B17-Modello!AI34 -> 1321.0027 | AH17: =AG17*(1+$C17)+AH5+Modello!AH34*$B17-Modello!AI35 -> 1429.3487 | AI17: =AH17*(1+$C17)+AI5+Modello!AH35*$B17-Modello!AI36 -> 1542.3124 | AJ17: =AI17*(1+$C17)+AJ5+Modello!AH36*$B17-Modello!AI37 -> 1660.0789 | AK17: =AJ17*(1+$C17)+AK5+Modello!AH37*$B17-Modello!AI38 -> 1782.8407
A18: r_BRDP=2.50%, rf=0.500% | B18: 0.025 | C18: 0.005 | D18: =D5 -> 6.1677 | E18: =D18*(1+$C18)+E5+Modello!AH5*$B18-Modello!AI6 -> 13.47866 | F18: =E18*(1+$C18)+F5+Modello!AH6*$B18-Modello!AI7 -> 21.959161 | G18: =F18*(1+$C18)+G5+Modello!AH7*$B18-Modello!AI8 -> 31.63582 | H18: =G18*(1+$C18)+H5+Modello!AH8*$B18-Modello!AI9 -> 42.535594 | I18: =H18*(1+$C18)+I5+Modello!AH9*$B18-Modello!AI10 -> 54.685785 | J18: =I18*(1+$C18)+J5+Modello!AH10*$B18-Modello!AI11 -> 67.400703 | K18: =J18*(1+$C18)+K5+Modello!AH11*$B18-Modello!AI12 -> 80.690497 | L18: =K18*(1+$C18)+L5+Modello!AH12*$B18-Modello!AI13 -> 94.565438 | M18: =L18*(1+$C18)+M5+Modello!AH13*$B18-Modello!AI14 -> 109.03592 | N18: =M18*(1+$C18)+N5+Modello!AH14*$B18-Modello!AI15 -> 130.74055 | O18: =N18*(1+$C18)+O5+Modello!AH15*$B18-Modello!AI16 -> 153.28284 | P18: =O18*(1+$C18)+P5+Modello!AH16*$B18-Modello!AI17 -> 176.67619 | Q18: =P18*(1+$C18)+Q5+Modello!AH17*$B18-Modello!AI18 -> 200.93413 | R18: =Q18*(1+$C18)+R5+Modello!AH18*$B18-Modello!AI19 -> 226.07036 | S18: =R18*(1+$C18)+S5+Modello!AH19*$B18-Modello!AI20 -> 255.18263 | T18: =S18*(1+$C18)+T5+Modello!AH20*$B18-Modello!AI21 -> 285.65709 | U18: =T18*(1+$C18)+U5+Modello!AH21*$B18-Modello!AI22 -> 317.50112 | V18: =U18*(1+$C18)+V5+Modello!AH22*$B18-Modello!AI23 -> 350.72217 | W18: =V18*(1+$C18)+W5+Modello!AH23*$B18-Modello!AI24 -> 385.32779 | X18: =W18*(1+$C18)+X5+Modello!AH24*$B18-Modello!AI25 -> 434.1897 | Y18: =X18*(1+$C18)+Y5+Modello!AH25*$B18-Modello!AI26 -> 484.25038 | Z18: =Y18*(1+$C18)+Z5+Modello!AH26*$B18-Modello!AI27 -> 535.52036 | AA18: =Z18*(1+$C18)+AA5+Modello!AH27*$B18-Modello!AI28 -> 588.01031 | AB18: =AA18*(1+$C18)+AB5+Modello!AH28*$B18-Modello!AI29 -> 641.73103 | AC18: =AB18*(1+$C18)+AC5+Modello!AH29*$B18-Modello!AI30 -> 696.69343 | AD18: =AC18*(1+$C18)+AD5+Modello!AH30*$B18-Modello!AI31 -> 752.90858 | AE18: =AD18*(1+$C18)+AE5+Modello!AH31*$B18-Modello!AI32 -> 810.38768 | AF18: =AE18*(1+$C18)+AF5+Modello!AH32*$B18-Modello!AI33 -> 869.14206 | AG18: =AF18*(1+$C18)+AG5+Modello!AH33*$B18-Modello!AI34 -> 929.18319 | AH18: =AG18*(1+$C18)+AH5+Modello!AH34*$B18-Modello!AI35 -> 989.73392 | AI18: =AH18*(1+$C18)+AI5+Modello!AH35*$B18-Modello!AI36 -> 1050.7953 | AJ18: =AI18*(1+$C18)+AJ5+Modello!AH36*$B18-Modello!AI37 -> 1112.3685 | AK18: =AJ18*(1+$C18)+AK5+Modello!AH37*$B18-Modello!AI38 -> 1174.4544
A19: r_BRDP=2.50%, rf=1.250% | B19: 0.025 | C19: 0.0125 | D19: =D5 -> 6.1677 | E19: =D19*(1+$C19)+E5+Modello!AH5*$B19-Modello!AI6 -> 13.524918 | F19: =E19*(1+$C19)+F5+Modello!AH6*$B19-Modello!AI7 -> 22.107087 | G19: =F19*(1+$C19)+G5+Modello!AH7*$B19-Modello!AI8 -> 31.950288 | H19: =G19*(1+$C19)+H5+Modello!AH8*$B19-Modello!AI9 -> 43.091262 | I19: =H19*(1+$C19)+I5+Modello!AH9*$B19-Modello!AI10 -> 55.567416 | J19: =I19*(1+$C19)+J5+Modello!AH10*$B19-Modello!AI11 -> 68.703498 | K19: =J19*(1+$C19)+K5+Modello!AH11*$B19-Modello!AI12 -> 82.515082 | L19: =K19*(1+$C19)+L5+Modello!AH12*$B19-Modello!AI13 -> 97.018009 | M19: =L19*(1+$C19)+M5+Modello!AH13*$B19-Modello!AI14 -> 112.22839 | N19: =M19*(1+$C19)+N5+Modello!AH14*$B19-Modello!AI15 -> 134.79069 | O19: =N19*(1+$C19)+O5+Modello!AH15*$B19-Modello!AI16 -> 158.36417 | P19: =O19*(1+$C19)+P5+Modello!AH16*$B19-Modello!AI17 -> 182.97065 | Q19: =P19*(1+$C19)+Q5+Modello!AH17*$B19-Modello!AI18 -> 208.63234 | R19: =Q19*(1+$C19)+R5+Modello!AH18*$B19-Modello!AI19 -> 235.37181 | S19: =R19*(1+$C19)+S5+Modello!AH19*$B19-Modello!AI20 -> 266.29587 | T19: =S19*(1+$C19)+T5+Modello!AH20*$B19-Modello!AI21 -> 298.82312 | U19: =T19*(1+$C19)+U5+Modello!AH21*$B19-Modello!AI22 -> 332.97415 | V19: =U19*(1+$C19)+V5+Modello!AH22*$B19-Modello!AI23 -> 368.76987 | W19: =V19*(1+$C19)+W5+Modello!AH23*$B19-Modello!AI24 -> 406.23151 | X19: =W19*(1+$C19)+X5+Modello!AH24*$B19-Modello!AI25 -> 458.24467 | Y19: =X19*(1+$C19)+Y5+Modello!AH25*$B19-Modello!AI26 -> 511.86246 | Z19: =Y19*(1+$C19)+Z5+Modello!AH26*$B19-Modello!AI27 -> 567.10948 | AA19: =Z19*(1+$C19)+AA5+Modello!AH27*$B19-Modello!AI28 -> 624.01069 | AB19: =AA19*(1+$C19)+AB5+Modello!AH28*$B19-Modello!AI29 -> 682.59149 | AC19: =AB19*(1+$C19)+AC5+Modello!AH29*$B19-Modello!AI30 -> 742.87763 | AD19: =AC19*(1+$C19)+AD5+Modello!AH30*$B19-Modello!AI31 -> 804.89528 | AE19: =AD19*(1+$C19)+AE5+Modello!AH31*$B19-Modello!AI32 -> 868.67103 | AF19: =AE19*(1+$C19)+AF5+Modello!AH32*$B19-Modello!AI33 -> 934.23186 | AG19: =AF19*(1+$C19)+AG5+Modello!AH33*$B19-Modello!AI34 -> 1001.6052 | AH19: =AG19*(1+$C19)+AH5+Modello!AH34*$B19-Modello!AI35 -> 1070.0301 | AI19: =AH19*(1+$C19)+AI5+Modello!AH35*$B19-Modello!AI36 -> 1139.5182 | AJ19: =AI19*(1+$C19)+AJ5+Modello!AH36*$B19-Modello!AI37 -> 1210.0813 | AK19: =AJ19*(1+$C19)+AK5+Modello!AH37*$B19-Modello!AI38 -> 1281.7315
A20: r_BRDP=2.50%, rf=2.500% | B20: 0.025 | C20: 0.025 | D20: =D5 -> 6.1677 | E20: =D20*(1+$C20)+E5+Modello!AH5*$B20-Modello!AI6 -> 13.602014 | F20: =E20*(1+$C20)+F5+Modello!AH6*$B20-Modello!AI7 -> 22.355172 | G20: =F20*(1+$C20)+G5+Modello!AH7*$B20-Modello!AI8 -> 32.480914 | H20: =G20*(1+$C20)+H5+Modello!AH8*$B20-Modello!AI9 -> 44.034532 | I20: =H20*(1+$C20)+I5+Modello!AH9*$B20-Modello!AI10 -> 57.072908 | J20: =I20*(1+$C20)+J5+Modello!AH10*$B20-Modello!AI11 -> 70.94122 | K20: =J20*(1+$C20)+K5+Modello!AH11*$B20-Modello!AI12 -> 85.667541 | L20: =K20*(1+$C20)+L5+Modello!AH12*$B20-Modello!AI13 -> 101.28072 | M20: =L20*(1+$C20)+M5+Modello!AH13*$B20-Modello!AI14 -> 117.81039 | N20: =M20*(1+$C20)+N5+Modello!AH14*$B20-Modello!AI15 -> 141.9151 | O20: =N20*(1+$C20)+O5+Modello!AH15*$B20-Modello!AI16 -> 167.35157 | P20: =O20*(1+$C20)+P5+Modello!AH16*$B20-Modello!AI17 -> 194.16229 | Q20: =P20*(1+$C20)+Q5+Modello!AH17*$B20-Modello!AI18 -> 222.3909 | R20: =Q20*(1+$C20)+R5+Modello!AH18*$B20-Modello!AI19 -> 252.08224 | S20: =R20*(1+$C20)+S5+Modello!AH19*$B20-Modello!AI20 -> 286.36621 | T20: =S20*(1+$C20)+T5+Modello!AH20*$B20-Modello!AI21 -> 322.72392 | U20: =T20*(1+$C20)+U5+Modello!AH21*$B20-Modello!AI22 -> 361.20776 | V20: =U20*(1+$C20)+V5+Modello!AH22*$B20-Modello!AI23 -> 401.8715 | W20: =V20*(1+$C20)+W5+Modello!AH23*$B20-Modello!AI24 -> 444.7703 | X20: =W20*(1+$C20)+X5+Modello!AH24*$B20-Modello!AI25 -> 502.82482 | Y20: =X20*(1+$C20)+Y5+Modello!AH25*$B20-Modello!AI26 -> 563.28517 | Z20: =Y20*(1+$C20)+Z5+Modello!AH26*$B20-Modello!AI27 -> 626.21604 | AA20: =Z20*(1+$C20)+AA5+Modello!AH27*$B20-Modello!AI28 -> 691.68378 | AB20: =AA20*(1+$C20)+AB5+Modello!AH28*$B20-Modello!AI29 -> 759.75654 | AC20: =AB20*(1+$C20)+AC5+Modello!AH29*$B20-Modello!AI30 -> 830.5042 | AD20: =AC20*(1+$C20)+AD5+Modello!AH30*$B20-Modello!AI31 -> 903.99849 | AE20: =AD20*(1+$C20)+AE5+Modello!AH31*$B20-Modello!AI32 -> 980.31301 | AF20: =AE20*(1+$C20)+AF5+Modello!AH32*$B20-Modello!AI33 -> 1059.5233 | AG20: =AF20*(1+$C20)+AG5+Modello!AH33*$B20-Modello!AI34 -> 1141.7068 | AH20: =AG20*(1+$C20)+AH5+Modello!AH34*$B20-Modello!AI35 -> 1226.1543 | AI20: =AH20*(1+$C20)+AI5+Modello!AH35*$B20-Modello!AI36 -> 1312.9209 | AJ20: =AI20*(1+$C20)+AJ5+Modello!AH36*$B20-Modello!AI37 -> 1402.0631 | AK20: =AJ20*(1+$C20)+AK5+Modello!AH37*$B20-Modello!AI38 -> 1493.6387
A21: r_BRDP=2.50%, rf=4.000% | B21: 0.025 | C21: 0.04 | D21: =D5 -> 6.1677 | E21: =D21*(1+$C21)+E5+Modello!AH5*$B21-Modello!AI6 -> 13.69453 | F21: =E21*(1+$C21)+F5+Modello!AH6*$B21-Modello!AI7 -> 22.655419 | G21: =F21*(1+$C21)+G5+Modello!AH7*$B21-Modello!AI8 -> 33.128498 | H21: =G21*(1+$C21)+H5+Modello!AH8*$B21-Modello!AI9 -> 45.195233 | I21: =H21*(1+$C21)+I5+Modello!AH9*$B21-Modello!AI10 -> 58.940555 | J21: =I21*(1+$C21)+J5+Modello!AH10*$B21-Modello!AI11 -> 73.739667 | K21: =J21*(1+$C21)+K5+Modello!AH11*$B21-Modello!AI12 -> 89.642044 | L21: =K21*(1+$C21)+L5+Modello!AH12*$B21-Modello!AI13 -> 106.69921 | M21: =L21*(1+$C21)+M5+Modello!AH13*$B21-Modello!AI14 -> 124.96484 | N21: =M21*(1+$C21)+N5+Modello!AH14*$B21-Modello!AI15 -> 151.12288 | O21: =N21*(1+$C21)+O5+Modello!AH15*$B21-Modello!AI16 -> 179.05639 | P21: =O21*(1+$C21)+P5+Modello!AH16*$B21-Modello!AI17 -> 208.84557 | Q21: =P21*(1+$C21)+Q5+Modello!AH17*$B21-Modello!AI18 -> 240.57395 | R21: =Q21*(1+$C21)+R5+Modello!AH18*$B21-Modello!AI19 -> 274.32848 | S21: =R21*(1+$C21)+S5+Modello!AH19*$B21-Modello!AI20 -> 313.28353 | T21: =S21*(1+$C21)+T5+Modello!AH20*$B21-Modello!AI21 -> 355.01342 | U21: =T21*(1+$C21)+U5+Modello!AH21*$B21-Modello!AI22 -> 399.6297 | V21: =U21*(1+$C21)+V5+Modello!AH22*$B21-Modello!AI23 -> 447.24843 | W21: =V21*(1+$C21)+W5+Modello!AH23*$B21-Modello!AI24 -> 497.99038 | X21: =W21*(1+$C21)+X5+Modello!AH24*$B21-Modello!AI25 -> 564.84527 | Y21: =X21*(1+$C21)+Y5+Modello!AH25*$B21-Modello!AI26 -> 635.32881 | Z21: =Y21*(1+$C21)+Z5+Modello!AH26*$B21-Modello!AI27 -> 709.59069 | AA21: =Z21*(1+$C21)+AA5+Modello!AH27*$B21-Modello!AI28 -> 787.78667 | AB21: =AA21*(1+$C21)+AB5+Modello!AH28*$B21-Modello!AI29 -> 870.0788 | AC21: =AB21*(1+$C21)+AC5+Modello!AH29*$B21-Modello!AI30 -> 956.63569 | AD21: =AC21*(1+$C21)+AD5+Modello!AH30*$B21-Modello!AI31 -> 1047.6328 | AE21: =AD21*(1+$C21)+AE5+Modello!AH31*$B21-Modello!AI32 -> 1143.2527 | AF21: =AE21*(1+$C21)+AF5+Modello!AH32*$B21-Modello!AI33 -> 1243.6852 | AG21: =AF21*(1+$C21)+AG5+Modello!AH33*$B21-Modello!AI34 -> 1349.1281 | AH21: =AG21*(1+$C21)+AH5+Modello!AH34*$B21-Modello!AI35 -> 1458.998 | AI21: =AH21*(1+$C21)+AI5+Modello!AH35*$B21-Modello!AI36 -> 1573.4706 | AJ21: =AI21*(1+$C21)+AJ5+Modello!AH36*$B21-Modello!AI37 -> 1692.7286 | AK21: =AJ21*(1+$C21)+AK5+Modello!AH37*$B21-Modello!AI38 -> 1816.9619
A22: r_BRDP=3.50%, rf=0.500% | B22: 0.035 | C22: 0.005 | D22: =D5 -> 6.1677 | E22: =D22*(1+$C22)+E5+Modello!AH5*$B22-Modello!AI6 -> 13.509499 | F22: =E22*(1+$C22)+F5+Modello!AH6*$B22-Modello!AI7 -> 22.057007 | G22: =F22*(1+$C22)+G5+Modello!AH7*$B22-Modello!AI8 -> 31.842239 | H22: =G22*(1+$C22)+H5+Modello!AH8*$B22-Modello!AI9 -> 42.897612 | I22: =H22*(1+$C22)+I5+Modello!AH9*$B22-Modello!AI10 -> 55.255955 | J22: =I22*(1+$C22)+J5+Modello!AH10*$B22-Modello!AI11 -> 68.237175 | K22: =J22*(1+$C22)+K5+Modello!AH11*$B22-Modello!AI12 -> 81.853517 | L22: =K22*(1+$C22)+L5+Modello!AH12*$B22-Modello!AI13 -> 96.117373 | M22: =L22*(1+$C22)+M5+Modello!AH13*$B22-Modello!AI14 -> 111.04129 | N22: =M22*(1+$C22)+N5+Modello!AH14*$B22-Modello!AI15 -> 133.26602 | O22: =N22*(1+$C22)+O5+Modello!AH15*$B22-Modello!AI16 -> 156.39731 | P22: =O22*(1+$C22)+P5+Modello!AH16*$B22-Modello!AI17 -> 180.45075 | Q22: =P22*(1+$C22)+Q5+Modello!AH17*$B22-Modello!AI18 -> 205.44214 | R22: =Q22*(1+$C22)+R5+Modello!AH18*$B22-Modello!AI19 -> 231.38746 | S22: =R22*(1+$C22)+S5+Modello!AH19*$B22-Modello!AI20 -> 261.38673 | T22: =S22*(1+$C22)+T5+Modello!AH20*$B22-Modello!AI21 -> 292.79762 | U22: =T22*(1+$C22)+U5+Modello!AH21*$B22-Modello!AI22 -> 325.62452 | V22: =U22*(1+$C22)+V5+Modello!AH22*$B22-Modello!AI23 -> 359.87188 | W22: =V22*(1+$C22)+W5+Modello!AH23*$B22-Modello!AI24 -> 395.54419 | X22: =W22*(1+$C22)+X5+Modello!AH24*$B22-Modello!AI25 -> 445.51009 | Y22: =X22*(1+$C22)+Y5+Modello!AH25*$B22-Modello!AI26 -> 496.62317 | Z22: =Y22*(1+$C22)+Z5+Modello!AH26*$B22-Modello!AI27 -> 548.8919 | AA22: =Z22*(1+$C22)+AA5+Modello!AH27*$B22-Modello!AI28 -> 602.32486 | AB22: =AA22*(1+$C22)+AB5+Modello!AH28*$B22-Modello!AI29 -> 656.93073 | AC22: =AB22*(1+$C22)+AC5+Modello!AH29*$B22-Modello!AI30 -> 712.71829 | AD22: =AC22*(1+$C22)+AD5+Modello!AH30*$B22-Modello!AI31 -> 769.69645 | AE22: =AD22*(1+$C22)+AE5+Modello!AH31*$B22-Modello!AI32 -> 827.87422 | AF22: =AE22*(1+$C22)+AF5+Modello!AH32*$B22-Modello!AI33 -> 887.2607 | AG22: =AF22*(1+$C22)+AG5+Modello!AH33*$B22-Modello!AI34 -> 947.86514 | AH22: =AG22*(1+$C22)+AH5+Modello!AH34*$B22-Modello!AI35 -> 1008.9081 | AI22: =AH22*(1+$C22)+AI5+Modello!AH35*$B22-Modello!AI36 -> 1070.3884 | AJ22: =AI22*(1+$C22)+AJ5+Modello!AH36*$B22-Modello!AI37 -> 1132.3047 | AK22: =AJ22*(1+$C22)+AK5+Modello!AH37*$B22-Modello!AI38 -> 1194.6559
A23: r_BRDP=3.50%, rf=1.250% | B23: 0.035 | C23: 0.0125 | D23: =D5 -> 6.1677 | E23: =D23*(1+$C23)+E5+Modello!AH5*$B23-Modello!AI6 -> 13.555756 | F23: =E23*(1+$C23)+F5+Modello!AH6*$B23-Modello!AI7 -> 22.205165 | G23: =F23*(1+$C23)+G5+Modello!AH7*$B23-Modello!AI8 -> 32.157676 | H23: =G23*(1+$C23)+H5+Modello!AH8*$B23-Modello!AI9 -> 43.455808 | I23: =H23*(1+$C23)+I5+Modello!AH9*$B23-Modello!AI10 -> 56.142861 | J23: =I23*(1+$C23)+J5+Modello!AH10*$B23-Modello!AI11 -> 69.549588 | K23: =J23*(1+$C23)+K5+Modello!AH11*$B23-Modello!AI12 -> 83.694113 | L23: =K23*(1+$C23)+L5+Modello!AH12*$B23-Modello!AI13 -> 98.594878 | M23: =L23*(1+$C23)+M5+Modello!AH13*$B23-Modello!AI14 -> 114.27064 | N23: =M23*(1+$C23)+N5+Modello!AH14*$B23-Modello!AI15 -> 137.36855 | O23: =N23*(1+$C23)+O5+Modello!AH15*$B23-Modello!AI16 -> 161.55062 | P23: =O23*(1+$C23)+P5+Modello!AH16*$B23-Modello!AI17 -> 186.84146 | Q23: =P23*(1+$C23)+Q5+Modello!AH17*$B23-Modello!AI18 -> 213.26611 | R23: =Q23*(1+$C23)+R5+Modello!AH18*$B23-Modello!AI19 -> 240.85004 | S23: =R23*(1+$C23)+S5+Modello!AH19*$B23-Modello!AI20 -> 272.703 | T23: =S23*(1+$C23)+T5+Modello!AH20*$B23-Modello!AI21 -> 306.21575 | U23: =T23*(1+$C23)+U5+Modello!AH21*$B23-Modello!AI22 -> 341.40636 | V23: =U23*(1+$C23)+V5+Modello!AH22*$B23-Modello!AI23 -> 378.29317 | W23: =V23*(1+$C23)+W5+Modello!AH23*$B23-Modello!AI24 -> 416.89479 | X23: =W23*(1+$C23)+X5+Modello!AH24*$B23-Modello!AI25 -> 470.09415 | Y23: =X23*(1+$C23)+Y5+Modello!AH25*$B23-Modello!AI26 -> 524.85586 | Z23: =Y23*(1+$C23)+Z5+Modello!AH26*$B23-Modello!AI27 -> 581.20217 | AA23: =Z23*(1+$C23)+AA5+Modello!AH27*$B23-Modello!AI28 -> 639.1557 | AB23: =AA23*(1+$C23)+AB5+Modello!AH28*$B23-Modello!AI29 -> 698.73939 | AC23: =AB23*(1+$C23)+AC5+Modello!AH29*$B23-Modello!AI30 -> 759.97654 | AD23: =AC23*(1+$C23)+AD5+Modello!AH30*$B23-Modello!AI31 -> 822.89082 | AE23: =AD23*(1+$C23)+AE5+Modello!AH31*$B23-Modello!AI32 -> 887.50623 | AF23: =AE23*(1+$C23)+AF5+Modello!AH32*$B23-Modello!AI33 -> 953.84717 | AG23: =AF23*(1+$C23)+AG5+Modello!AH33*$B23-Modello!AI34 -> 1021.9384 | AH23: =AG23*(1+$C23)+AH5+Modello!AH34*$B23-Modello!AI35 -> 1091.0163 | AI23: =AH23*(1+$C23)+AI5+Modello!AH35*$B23-Modello!AI36 -> 1161.0897 | AJ23: =AI23*(1+$C23)+AJ5+Modello!AH36*$B23-Modello!AI37 -> 1232.1677 | AK23: =AJ23*(1+$C23)+AK5+Modello!AH37*$B23-Modello!AI38 -> 1304.2594
A24: r_BRDP=3.50%, rf=2.500% | B24: 0.035 | C24: 0.025 | D24: =D5 -> 6.1677 | E24: =D24*(1+$C24)+E5+Modello!AH5*$B24-Modello!AI6 -> 13.632853 | F24: =E24*(1+$C24)+F5+Modello!AH6*$B24-Modello!AI7 -> 22.453635 | G24: =F24*(1+$C24)+G5+Modello!AH7*$B24-Modello!AI8 -> 32.689922 | H24: =G24*(1+$C24)+H5+Modello!AH8*$B24-Modello!AI9 -> 44.403332 | I24: =H24*(1+$C24)+I5+Modello!AH9*$B24-Modello!AI10 -> 57.657271 | J24: =I24*(1+$C24)+J5+Modello!AH10*$B24-Modello!AI11 -> 71.803643 | K24: =J24*(1+$C24)+K5+Modello!AH11*$B24-Modello!AI12 -> 86.87389 | L24: =K24*(1+$C24)+L5+Modello!AH12*$B24-Modello!AI13 -> 102.90033 | M24: =L24*(1+$C24)+M5+Modello!AH13*$B24-Modello!AI14 -> 119.91616 | N24: =M24*(1+$C24)+N5+Modello!AH14*$B24-Modello!AI15 -> 144.5836 | O24: =N24*(1+$C24)+O5+Modello!AH15*$B24-Modello!AI16 -> 170.66314 | P24: =O24*(1+$C24)+P5+Modello!AH16*$B24-Modello!AI17 -> 198.20118 | Q24: =P24*(1+$C24)+Q5+Modello!AH17*$B24-Modello!AI18 -> 227.24534 | R24: =Q24*(1+$C24)+R5+Modello!AH18*$B24-Modello!AI19 -> 257.84458 | S24: =R24*(1+$C24)+S5+Modello!AH19*$B24-Modello!AI20 -> 293.13303 | T24: =S24*(1+$C24)+T5+Modello!AH20*$B24-Modello!AI21 -> 330.56531 | U24: =T24*(1+$C24)+U5+Modello!AH21*$B24-Modello!AI22 -> 370.19236 | V24: =U24*(1+$C24)+V5+Modello!AH22*$B24-Modello!AI23 -> 412.0664 | W24: =V24*(1+$C24)+W5+Modello!AH23*$B24-Modello!AI24 -> 456.24102 | X24: =W24*(1+$C24)+X5+Modello!AH24*$B24-Modello!AI25 -> 515.63522 | Y24: =X24*(1+$C24)+Y5+Modello!AH25*$B24-Modello!AI26 -> 577.41163 | Z24: =Y24*(1+$C24)+Z5+Modello!AH26*$B24-Modello!AI27 -> 641.63254 | AA24: =Z24*(1+$C24)+AA5+Modello!AH27*$B24-Modello!AI28 -> 708.36185 | AB24: =AA24*(1+$C24)+AB5+Modello!AH28*$B24-Modello!AI29 -> 777.66514 | AC24: =AB24*(1+$C24)+AC5+Modello!AH29*$B24-Modello!AI30 -> 849.60968 | AD24: =AC24*(1+$C24)+AD5+Modello!AH30*$B24-Modello!AI31 -> 924.26449 | AE24: =AD24*(1+$C24)+AE5+Modello!AH31*$B24-Modello!AI32 -> 1001.7004 | AF24: =AE24*(1+$C24)+AF5+Modello!AH32*$B24-Modello!AI33 -> 1081.99 | AG24: =AF24*(1+$C24)+AG5+Modello!AH33*$B24-Modello!AI34 -> 1165.2079 | AH24: =AG24*(1+$C24)+AH5+Modello!AH34*$B24-Modello!AI35 -> 1250.6417 | AI24: =AH24*(1+$C24)+AI5+Modello!AH35*$B24-Modello!AI36 -> 1338.3435 | AJ24: =AI24*(1+$C24)+AJ5+Modello!AH36*$B24-Modello!AI37 -> 1428.3665 | AK24: =AJ24*(1+$C24)+AK5+Modello!AH37*$B24-Modello!AI38 -> 1520.7653
A25: r_BRDP=3.50%, rf=4.000% | B25: 0.035 | C25: 0.04 | D25: =D5 -> 6.1677 | E25: =D25*(1+$C25)+E5+Modello!AH5*$B25-Modello!AI6 -> 13.725368 | F25: =E25*(1+$C25)+F5+Modello!AH6*$B25-Modello!AI7 -> 22.754344 | G25: =F25*(1+$C25)+G5+Modello!AH7*$B25-Modello!AI8 -> 33.339464 | H25: =G25*(1+$C25)+H5+Modello!AH8*$B25-Modello!AI9 -> 45.569204 | I25: =H25*(1+$C25)+I5+Modello!AH9*$B25-Modello!AI10 -> 59.535828 | J25: =I25*(1+$C25)+J5+Modello!AH10*$B25-Modello!AI11 -> 74.622202 | K25: =J25*(1+$C25)+K5+Modello!AH11*$B25-Modello!AI12 -> 90.882246 | L25: =K25*(1+$C25)+L5+Modello!AH12*$B25-Modello!AI13 -> 108.37212 | M25: =L25*(1+$C25)+M5+Modello!AH13*$B25-Modello!AI14 -> 127.15033 | N25: =M25*(1+$C25)+N5+Modello!AH14*$B25-Modello!AI15 -> 153.90588 | O25: =N25*(1+$C25)+O5+Modello!AH15*$B25-Modello!AI16 -> 182.52707 | P25: =O25*(1+$C25)+P5+Modello!AH16*$B25-Modello!AI17 -> 213.09961 | Q25: =P25*(1+$C25)+Q5+Modello!AH17*$B25-Modello!AI18 -> 245.71273 | R25: =Q25*(1+$C25)+R5+Modello!AH18*$B25-Modello!AI19 -> 280.45935 | S25: =R25*(1+$C25)+S5+Modello!AH19*$B25-Modello!AI20 -> 320.52005 | T25: =S25*(1+$C25)+T5+Modello!AH20*$B25-Modello!AI21 -> 363.44481 | U25: =T25*(1+$C25)+U5+Modello!AH21*$B25-Modello!AI22 -> 409.34552 | V25: =U25*(1+$C25)+V5+Modello!AH22*$B25-Modello!AI23 -> 458.33857 | W25: =V25*(1+$C25)+W5+Modello!AH23*$B25-Modello!AI24 -> 510.54507 | X25: =W25*(1+$C25)+X5+Modello!AH24*$B25-Modello!AI25 -> 578.95505 | Y25: =X25*(1+$C25)+Y5+Modello!AH25*$B25-Modello!AI26 -> 650.99878 | Z25: =Y25*(1+$C25)+Z5+Modello!AH26*$B25-Modello!AI27 -> 726.82435 | AA25: =Z25*(1+$C25)+AA5+Modello!AH27*$B25-Modello!AI28 -> 806.58582 | AB25: =AA25*(1+$C25)+AB5+Modello!AH28*$B25-Modello!AI29 -> 890.4435 | AC25: =AB25*(1+$C25)+AC5+Modello!AH29*$B25-Modello!AI30 -> 978.56415 | AD25: =AC25*(1+$C25)+AD5+Modello!AH30*$B25-Modello!AI31 -> 1071.1213 | AE25: =AD25*(1+$C25)+AE5+Modello!AH31*$B25-Modello!AI32 -> 1168.2954 | AF25: =AE25*(1+$C25)+AF5+Modello!AH32*$B25-Modello!AI33 -> 1270.2743 | AG25: =AF25*(1+$C25)+AG5+Modello!AH33*$B25-Modello!AI34 -> 1377.2535 | AH25: =AG25*(1+$C25)+AH5+Modello!AH34*$B25-Modello!AI35 -> 1488.6472 | AI25: =AH25*(1+$C25)+AI5+Modello!AH35*$B25-Modello!AI36 -> 1604.6289 | AJ25: =AI25*(1+$C25)+AJ5+Modello!AH36*$B25-Modello!AI37 -> 1725.3784 | AK25: =AJ25*(1+$C25)+AK5+Modello!AH37*$B25-Modello!AI38 -> 1851.0832
A27: Ib: Stock BRDP detenuto dai fondi P2 — interno (€mld reali €2027)
A28: Ib: Stock BRDP in circolazione (€mld reali €2027) | B28: r_BRDP_r | C28: rf_r | D28: 2027 | E28: 2028 | F28: 2029 | G28: 2030 | H28: 2031 | I28: 2032 | J28: 2033 | K28: 2034 | L28: 2035 | M28: 2036 | N28: 2037 | O28: 2038 | P28: 2039 | Q28: 2040 | R28: 2041 | S28: 2042 | T28: 2043 | U28: 2044 | V28: 2045 | W28: 2046 | X28: 2047 | Y28: 2048 | Z28: 2049 | AA28: 2050 | AB28: 2051 | AC28: 2052 | AD28: 2053 | AE28: 2054 | AF28: 2055 | AG28: 2056 | AH28: 2057 | AI28: 2058 | AJ28: 2059 | AK28: 2060
A29: Stock BRDP interno (= Modello!AH, esclude esteri) | B29: — | C29: — | D29: =Modello!AH5 -> 3.08385 | E29: =Modello!AH6 -> 6.6853627 | F29: =Modello!AH7 -> 10.80835 | G29: =Modello!AH8 -> 15.456677 | H29: =Modello!AH9 -> 20.634265 | I29: =Modello!AH10 -> 26.345094 | J29: =Modello!AH11 -> 32.236525 | K29: =Modello!AH12 -> 38.309963 | L29: =Modello!AH13 -> 44.566833 | M29: =Modello!AH14 -> 51.008576 | N29: =Modello!AH15 -> 57.636654 | O29: =Modello!AH16 -> 64.452546 | P29: =Modello!AH17 -> 71.457751 | Q29: =Modello!AH18 -> 78.653789 | R29: =Modello!AH19 -> 86.042197 | S29: =Modello!AH20 -> 90.540682 | T29: =Modello!AH21 -> 94.71701 | U29: =Modello!AH22 -> 98.568967 | V29: =Modello!AH23 -> 102.0943 | W29: =Modello!AH24 -> 105.29074 | X29: =Modello!AH25 -> 99.579909 | Y29: =Modello!AH26 -> 93.688478 | Z29: =Modello!AH27 -> 87.615039 | AA29: =Modello!AH28 -> 81.358169 | AB29: =Modello!AH29 -> 74.916426 | AC29: =Modello!AH30 -> 68.288349 | AD29: =Modello!AH31 -> 61.472457 | AE29: =Modello!AH32 -> 54.467251 | AF29: =Modello!AH33 -> 47.271214 | AG29: =Modello!AH34 -> 39.882806 | AH29: =Modello!AH35 -> 32.30047 | AI29: =Modello!AH36 -> 24.522629 | AJ29: =Modello!AH37 -> 16.547686 | AK29: =Modello!AH38 -> 8.374022
A32: Ic: Portafoglio totale P2 = Ia + Ib (€mld reali €2027) | B32: r_BRDP_r | C32: rf_r | D32: 2027 | E32: 2028 | F32: 2029 | G32: 2030 | H32: 2031 | I32: 2032 | J32: 2033 | K32: 2034 | L32: 2035 | M32: 2036 | N32: 2037 | O32: 2038 | P32: 2039 | Q32: 2040 | R32: 2041 | S32: 2042 | T32: 2043 | U32: 2044 | V32: 2045 | W32: 2046 | X32: 2047 | Y32: 2048 | Z32: 2049 | AA32: 2050 | AB32: 2051 | AC32: 2052 | AD32: 2053 | AE32: 2054 | AF32: 2055 | AG32: 2056 | AH32: 2057 | AI32: 2058 | AJ32: 2059 | AK32: 2060
A33: r_BRDP=0.75%, rf=0.500% | B33: 0.0075 | C33: 0.005 | D33: =D10+D29 -> 9.25155 | E33: =E10+E29 -> 20.110056 | F33: =F10+F29 -> 32.59628 | G33: =G10+G29 -> 46.731263 | H33: =H10+H29 -> 62.536328 | I33: =I10+I29 -> 80.03308 | J33: =J10+J29 -> 98.173401 | K33: =K10+K29 -> 116.96518 | ... AK33: =AK10+AK29 -> 1147.476
A34: r_BRDP=0.75%, rf=1.250% | B34: 0.0075 | C34: 0.0125 | D34: =D11+D29 -> 9.25155 | E34: =E11+E29 -> 20.156313 | F34: =F11+F29 -> 32.743801 | G34: =G11+G29 -> 47.044038 | H34: =H11+H29 -> 63.087571 | I34: =I11+I29 -> 80.90548 | J34: =J11+J29 -> 99.459366 | K34: =K11+K29 -> 118.76174 | ... AK34: =AK11+AK29 -> 1250.6815
A35: r_BRDP=0.75%, rf=2.500% | B35: 0.0075 | C35: 0.025 | D35: =D12+D29 -> 9.25155 | E35: =E12+E29 -> 20.23341 | F35: =F12+F29 -> 32.991211 | G35: =G12+G29 -> 47.571827 | H35: =H12+H29 -> 64.023397 | I35: =I12+I29 -> 82.395367 | J35: =J12+J29 -> 101.66851 | K35: =K12+K29 -> 121.86639 | ... AK35: =AK12+AK29 -> 1454.5414
A36: r_BRDP=0.75%, rf=4.000% | B36: 0.0075 | C36: 0.04 | D36: =D13+D29 -> 9.25155 | E36: =E13+E29 -> 20.325925 | F36: =F13+F29 -> 33.290648 | G36: =G13+G29 -> 48.215984 | H36: =H13+H29 -> 65.175048 | I36: =I13+I29 -> 84.243921 | J36: =J13+J29 -> 104.43176 | K36: =K13+K29 -> 125.78165 | ... AK36: =AK13+AK29 -> 1765.6238
A37: r_BRDP=1.50%, rf=0.500% | B37: 0.015 | C37: 0.005 | D37: =D14+D29 -> 9.25155 | E37: =E14+E29 -> 20.133184 | F37: =F14+F29 -> 32.669664 | G37: =G14+G29 -> 46.886077 | H37: =H14+H29 -> 62.807841 | I37: =I14+I29 -> 80.460708 | J37: =J14+J29 -> 98.800755 | K37: =K14+K29 -> 117.83744 | ... AK37: =AK14+AK29 -> 1162.6271
A38: r_BRDP=1.50%, rf=1.250% | B38: 0.015 | C38: 0.0125 | D38: =D15+D29 -> 9.25155 | E38: =E15+E29 -> 20.179442 | F38: =F15+F29 -> 32.817359 | G38: =G15+G29 -> 47.199578 | H38: =H15+H29 -> 63.360981 | I38: =I15+I29 -> 81.337064 | J38: =J15+J29 -> 100.09393 | K38: =K15+K29 -> 119.64601 | ... AK38: =AK15+AK29 -> 1267.5775
A39: r_BRDP=1.50%, rf=2.500% | B39: 0.015 | C39: 0.025 | D39: =D16+D29 -> 9.25155 | E39: =E16+E29 -> 20.256538 | F39: =F16+F29 -> 33.065059 | G39: =G16+G29 -> 47.728583 | H39: =H16+H29 -> 64.299997 | I39: =I16+I29 -> 82.833639 | J39: =J16+J29 -> 102.31532 | K39: =K16+K29 -> 122.77116 | ... AK39: =AK16+AK29 -> 1474.8863
A40: r_BRDP=1.50%, rf=4.000% | B40: 0.015 | C40: 0.04 | D40: =D17+D29 -> 9.25155 | E40: =E17+E29 -> 20.349054 | F40: =F17+F29 -> 33.364842 | G40: =G17+G29 -> 48.374208 | H40: =H17+H29 -> 65.455527 | I40: =I17+I29 -> 84.690376 | J40: =J17+J29 -> 105.09366 | K40: =K17+K29 -> 126.71181 | ... AK40: =AK17+AK29 -> 1791.2147
A41: r_BRDP=2.50%, rf=0.500% | B41: 0.025 | C41: 0.005 | D41: =D18+D29 -> 9.25155 | E41: =E18+E29 -> 20.164023 | F41: =F18+F29 -> 32.767511 | G41: =G18+G29 -> 47.092496 | H41: =H18+H29 -> 63.169859 | I41: =I18+I29 -> 81.030879 | J41: =J18+J29 -> 99.637228 | K41: =K18+K29 -> 119.00046 | ... AK41: =AK18+AK29 -> 1182.8285
A42: r_BRDP=2.50%, rf=1.250% | B42: 0.025 | C42: 0.0125 | D42: =D19+D29 -> 9.25155 | E42: =E19+E29 -> 20.210281 | F42: =F19+F29 -> 32.915437 | G42: =G19+G29 -> 47.406965 | H42: =H19+H29 -> 63.725527 | I42: =I19+I29 -> 81.91251 | J42: =J19+J29 -> 100.94002 | K42: =K19+K29 -> 120.82505 | ... AK42: =AK19+AK29 -> 1290.1055
A43: r_BRDP=2.50%, rf=2.500% | B43: 0.025 | C43: 0.025 | D43: =D20+D29 -> 9.25155 | E43: =E20+E29 -> 20.287377 | F43: =F20+F29 -> 33.163522 | G43: =G20+G29 -> 47.937591 | H43: =H20+H29 -> 64.668797 | I43: =I20+I29 -> 83.418002 | J43: =J20+J29 -> 103.17775 | K43: =K20+K29 -> 123.9775 | ... AK43: =AK20+AK29 -> 1502.0128
A44: r_BRDP=2.50%, rf=4.000% | B44: 0.025 | C44: 0.04 | D44: =D21+D29 -> 9.25155 | E44: =E21+E29 -> 20.379892 | F44: =F21+F29 -> 33.463768 | G44: =G21+G29 -> 48.585175 | H44: =H21+H29 -> 65.829498 | I44: =I21+I29 -> 85.285649 | J44: =J21+J29 -> 105.97619 | K44: =K21+K29 -> 127.95201 | ... AK44: =AK21+AK29 -> 1825.3359
A45: r_BRDP=3.50%, rf=0.500% | B45: 0.035 | C45: 0.005 | D45: =D22+D29 -> 9.25155 | E45: =E22+E29 -> 20.194861 | F45: =F22+F29 -> 32.865357 | G45: =G22+G29 -> 47.298915 | H45: =H22+H29 -> 63.531877 | I45: =I22+I29 -> 81.601049 | J45: =J22+J29 -> 100.4737 | K45: =K22+K29 -> 120.16348 | ... AK45: =AK22+AK29 -> 1203.0299
A46: r_BRDP=3.50%, rf=1.250% | B46: 0.035 | C46: 0.0125 | D46: =D23+D29 -> 9.25155 | E46: =E23+E29 -> 20.241119 | F46: =F23+F29 -> 33.013514 | G46: =G23+G29 -> 47.614352 | H46: =H23+H29 -> 64.090073 | I46: =I23+I29 -> 82.487955 | J46: =J23+J29 -> 101.78611 | K46: =K23+K29 -> 122.00408 | ... AK46: =AK23+AK29 -> 1312.6335
A47: r_BRDP=3.50%, rf=2.500% | B47: 0.035 | C47: 0.025 | D47: =D24+D29 -> 9.25155 | E47: =E24+E29 -> 20.318215 | F47: =F24+F29 -> 33.261985 | G47: =G24+G29 -> 48.146599 | H47: =H24+H29 -> 65.037598 | I47: =I24+I29 -> 84.002365 | J47: =J24+J29 -> 104.04017 | K47: =K24+K29 -> 125.18385 | ... AK47: =AK24+AK29 -> 1529.1393
A48: r_BRDP=3.50%, rf=4.000% | B48: 0.035 | C48: 0.04 | D48: =D25+D29 -> 9.25155 | E48: =E25+E29 -> 20.410731 | F48: =F25+F29 -> 33.562694 | G48: =G25+G29 -> 48.796141 | H48: =H25+H29 -> 66.20347 | I48: =I25+I29 -> 85.880922 | J48: =J25+J29 -> 106.85873 | K48: =K25+K29 -> 129.19221 | ... AK48: =AK25+AK29 -> 1859.4572
A52: SEZIONE II — Flussi BRDP (€mld reali €2027) | B52: r_BRDP_r | C52: rf_r | D52: 2027 | E52: 2028 | F52: 2029 | G52: 2030 | H52: 2031 | I52: 2032 | J52: 2033 | K52: 2034 | L52: 2035 | M52: 2036 | N52: 2037 | O52: 2038 | P52: 2039 | Q52: 2040 | R52: 2041 | S52: 2042 | T52: 2043 | U52: 2044 | V52: 2045 | W52: 2046 | X52: 2047 | Y52: 2048 | Z52: 2049 | AA52: 2050 | AB52: 2051 | AC52: 2052 | AD52: 2053 | AE52: 2054 | AF52: 2055 | AG52: 2056 | AH52: 2057 | AI52: 2058 | AJ52: 2059 | AK52: 2060
A53: Stock BRDP | B53: — | C53: — | D53: =D29 -> 3.08385 | E53: =E29 -> 6.6853627 | F53: =F29 -> 10.80835 | G53: =G29 -> 15.456677 | H53: =H29 -> 20.634265 | I53: =I29 -> 26.345094 | J53: =J29 -> 32.236525 | K53: =K29 -> 38.309963 | ... AK53: =AK29 -> 8.374022
A56: IIb: Cedole BRDP ai fondi P2 = stock INTERNO(t-1) × r_BRDP_r (€mld reali €2027) | B56: r_BRDP_r | C56: rf_r | D56: 2027 | E56: 2028 | F56: 2029 | G56: 2030 | H56: 2031 | I56: 2032 | J56: 2033 | K56: 2034 | L56: 2035 | M56: 2036 | N56: 2037 | O56: 2038 | P56: 2039 | Q56: 2040 | R56: 2041 | S56: 2042 | T56: 2043 | U56: 2044 | V56: 2045 | W56: 2046 | X56: 2047 | Y56: 2048 | Z56: 2049 | AA56: 2050 | AB56: 2051 | AC56: 2052 | AD56: 2053 | AE56: 2054 | AF56: 2055 | AG56: 2056 | AH56: 2057 | AI56: 2058 | AJ56: 2059 | AK56: 2060
A57: r_BRDP=0.75% | B57: 0.0075 | C57: — | D57: 0 | E57: =Modello!AH5*$B57 -> 0.023128875 | F57: =Modello!AH6*$B57 -> 0.050140221 | G57: =Modello!AH7*$B57 -> 0.081062621 | H57: =Modello!AH8*$B57 -> 0.11592507 | I57: =Modello!AH9*$B57 -> 0.15475699 | J57: =Modello!AH10*$B57 -> 0.1975882 | K57: =Modello!AH11*$B57 -> 0.24177394 | L57: =Modello!AH12*$B57 -> 0.28732473 | M57: =Modello!AH13*$B57 -> 0.33425125 | N57: =Modello!AH14*$B57 -> 0.38256432 | O57: =Modello!AH15*$B57 -> 0.4322749 | P57: =Modello!AH16*$B57 -> 0.48339409 | Q57: =Modello!AH17*$B57 -> 0.53593313 | R57: =Modello!AH18*$B57 -> 0.58990342 | S57: =Modello!AH19*$B57 -> 0.64531647 | T57: =Modello!AH20*$B57 -> 0.67905512 | U57: =Modello!AH21*$B57 -> 0.71037758 | V57: =Modello!AH22*$B57 -> 0.73926725 | W57: =Modello!AH23*$B57 -> 0.76570728 | X57: =Modello!AH24*$B57 -> 0.78968053 | Y57: =Modello!AH25*$B57 -> 0.74684931 | Z57: =Modello!AH26*$B57 -> 0.70266358 | AA57: =Modello!AH27*$B57 -> 0.65711279 | AB57: =Modello!AH28*$B57 -> 0.61018627 | AC57: =Modello!AH29*$B57 -> 0.5618732 | AD57: =Modello!AH30*$B57 -> 0.51216261 | AE57: =Modello!AH31*$B57 -> 0.46104343 | AF57: =Modello!AH32*$B57 -> 0.40850438 | AG57: =Modello!AH33*$B57 -> 0.3545341 | AH57: =Modello!AH34*$B57 -> 0.29912104 | AI57: =Modello!AH35*$B57 -> 0.24225353 | AJ57: =Modello!AH36*$B57 -> 0.18391972 | AK57: =Modello!AH37*$B57 -> 0.12410764
A58: r_BRDP=1.50% | B58: 0.015 | C58: — | D58: 0 | E58: =Modello!AH5*$B58 -> 0.04625775 | F58: =Modello!AH6*$B58 -> 0.10028044 | G58: =Modello!AH7*$B58 -> 0.16212524 | H58: =Modello!AH8*$B58 -> 0.23185015 | I58: =Modello!AH9*$B58 -> 0.30951398 | J58: =Modello!AH10*$B58 -> 0.39517641 | K58: =Modello!AH11*$B58 -> 0.48354787 | L58: =Modello!AH12*$B58 -> 0.57464945 | M58: =Modello!AH13*$B58 -> 0.6685025 | N58: =Modello!AH14*$B58 -> 0.76512864 | O58: =Modello!AH15*$B58 -> 0.86454981 | P58: =Modello!AH16*$B58 -> 0.96678818 | Q58: =Modello!AH17*$B58 -> 1.0718663 | R58: =Modello!AH18*$B58 -> 1.1798068 | S58: =Modello!AH19*$B58 -> 1.2906329 | T58: =Modello!AH20*$B58 -> 1.3581102 | U58: =Modello!AH21*$B58 -> 1.4207552 | V58: =Modello!AH22*$B58 -> 1.4785345 | W58: =Modello!AH23*$B58 -> 1.5314146 | X58: =Modello!AH24*$B58 -> 1.5793611 | Y58: =Modello!AH25*$B58 -> 1.4936986 | Z58: =Modello!AH26*$B58 -> 1.4053272 | AA58: =Modello!AH27*$B58 -> 1.3142256 | AB58: =Modello!AH28*$B58 -> 1.2203725 | AC58: =Modello!AH29*$B58 -> 1.1237464 | AD58: =Modello!AH30*$B58 -> 1.0243252 | AE58: =Modello!AH31*$B58 -> 0.92208685 | AF58: =Modello!AH32*$B58 -> 0.81700877 | AG58: =Modello!AH33*$B58 -> 0.7090682 | AH58: =Modello!AH34*$B58 -> 0.59824209 | AI58: =Modello!AH35*$B58 -> 0.48450705 | AJ58: =Modello!AH36*$B58 -> 0.36783944 | AK58: =Modello!AH37*$B58 -> 0.24821529
A59: r_BRDP=2.50% | B59: 0.025 | C59: — | D59: 0 | E59: =Modello!AH5*$B59 -> 0.07709625 | F59: =Modello!AH6*$B59 -> 0.16713407 | G59: =Modello!AH7*$B59 -> 0.27020874 | H59: =Modello!AH8*$B59 -> 0.38641691 | I59: =Modello!AH9*$B59 -> 0.51585664 | J59: =Modello!AH10*$B59 -> 0.65862734 | K59: =Modello!AH11*$B59 -> 0.80591312 | L59: =Modello!AH12*$B59 -> 0.95774908 | M59: =Modello!AH13*$B59 -> 1.1141708 | N59: =Modello!AH14*$B59 -> 1.2752144 | O59: =Modello!AH15*$B59 -> 1.4409163 | P59: =Modello!AH16*$B59 -> 1.6113136 | Q59: =Modello!AH17*$B59 -> 1.7864438 | R59: =Modello!AH18*$B59 -> 1.9663447 | S59: =Modello!AH19*$B59 -> 2.1510549 | T59: =Modello!AH20*$B59 -> 2.2635171 | U59: =Modello!AH21*$B59 -> 2.3679253 | V59: =Modello!AH22*$B59 -> 2.4642242 | W59: =Modello!AH23*$B59 -> 2.5523576 | X59: =Modello!AH24*$B59 -> 2.6322684 | Y59: =Modello!AH25*$B59 -> 2.4894977 | Z59: =Modello!AH26*$B59 -> 2.3422119 | AA59: =Modello!AH27*$B59 -> 2.190376 | AB59: =Modello!AH28*$B59 -> 2.0339542 | AC59: =Modello!AH29*$B59 -> 1.8729107 | AD59: =Modello!AH30*$B59 -> 1.7072087 | AE59: =Modello!AH31*$B59 -> 1.5368114 | AF59: =Modello!AH32*$B59 -> 1.3616813 | AG59: =Modello!AH33*$B59 -> 1.1817803 | AH59: =Modello!AH34*$B59 -> 0.99707015 | AI59: =Modello!AH35*$B59 -> 0.80751176 | AJ59: =Modello!AH36*$B59 -> 0.61306573 | AK59: =Modello!AH37*$B59 -> 0.41369214
A60: r_BRDP=3.50% | B60: 0.035 | C60: — | D60: 0 | E60: =Modello!AH5*$B60 -> 0.10793475 | F60: =Modello!AH6*$B60 -> 0.2339877 | G60: =Modello!AH7*$B60 -> 0.37829223 | H60: =Modello!AH8*$B60 -> 0.54098368 | I60: =Modello!AH9*$B60 -> 0.72219929 | J60: =Modello!AH10*$B60 -> 0.92207828 | K60: =Modello!AH11*$B60 -> 1.1282784 | L60: =Modello!AH12*$B60 -> 1.3408487 | M60: =Modello!AH13*$B60 -> 1.5598392 | N60: =Modello!AH14*$B60 -> 1.7853002 | O60: =Modello!AH15*$B60 -> 2.0172829 | P60: =Modello!AH16*$B60 -> 2.2558391 | Q60: =Modello!AH17*$B60 -> 2.5010213 | R60: =Modello!AH18*$B60 -> 2.7528826 | S60: =Modello!AH19*$B60 -> 3.0114769 | T60: =Modello!AH20*$B60 -> 3.1689239 | U60: =Modello!AH21*$B60 -> 3.3150954 | V60: =Modello!AH22*$B60 -> 3.4499138 | W60: =Modello!AH23*$B60 -> 3.5733006 | X60: =Modello!AH24*$B60 -> 3.6851758 | Y60: =Modello!AH25*$B60 -> 3.4852968 | Z60: =Modello!AH26*$B60 -> 3.2790967 | AA60: =Modello!AH27*$B60 -> 3.0665264 | AB60: =Modello!AH28*$B60 -> 2.8475359 | AC60: =Modello!AH29*$B60 -> 2.6220749 | AD60: =Modello!AH30*$B60 -> 2.3900922 | AE60: =Modello!AH31*$B60 -> 2.151536 | AF60: =Modello!AH32*$B60 -> 1.9063538 | AG60: =Modello!AH33*$B60 -> 1.6544925 | AH60: =Modello!AH34*$B60 -> 1.3958982 | AI60: =Modello!AH35*$B60 -> 1.1305165 | AJ60: =Modello!AH36*$B60 -> 0.85829203 | AK60: =Modello!AH37*$B60 -> 0.579169
A63: IIc: Rimborsi capitale BRDP INTERNO (inflow a P2, €mld reali €2027) | B63: r_BRDP_r | C63: rf_r | D63: 2027 | E63: 2028 | F63: 2029 | G63: 2030 | H63: 2031 | I63: 2032 | J63: 2033 | K63: 2034 | L63: 2035 | M63: 2036 | N63: 2037 | O63: 2038 | P63: 2039 | Q63: 2040 | R63: 2041 | S63: 2042 | T63: 2043 | U63: 2044 | V63: 2045 | W63: 2046 | X63: 2047 | Y63: 2048 | Z63: 2049 | AA63: 2050 | AB63: 2051 | AC63: 2052 | AD63: 2053 | AE63: 2054 | AF63: 2055 | AG63: 2056 | AH63: 2057 | AI63: 2058 | AJ63: 2059 | AK63: 2060
A64: Rimborsi | B64: — | C64: — | D64: =-Modello!AI5 -> 0 | E64: =-Modello!AI6 -> 0 | F64: =-Modello!AI7 -> 0 | G64: =-Modello!AI8 -> 0 | H64: =-Modello!AI9 -> 0 | I64: =-Modello!AI10 -> 0 | J64: =-Modello!AI11 -> 0 | K64: =-Modello!AI12 -> 0 | L64: =-Modello!AI13 -> 0 | M64: =-Modello!AI14 -> 0 | N64: =-Modello!AI15 -> 0 | O64: =-Modello!AI16 -> 0 | P64: =-Modello!AI17 -> 0 | Q64: =-Modello!AI18 -> 0 | R64: =-Modello!AI19 -> 0 | S64: =-Modello!AI20 -> 3.08385 | T64: =-Modello!AI21 -> 3.6015127 | U64: =-Modello!AI22 -> 4.1229868 | V64: =-Modello!AI23 -> 4.648327 | W64: =-Modello!AI24 -> 5.1775889 | X64: =-Modello!AI25 -> 5.7108283 | Y64: =-Modello!AI26 -> 5.891431 | Z64: =-Modello!AI27 -> 6.0734387 | AA64: =-Modello!AI28 -> 6.2568698 | AB64: =-Modello!AI29 -> 6.4417431 | AC64: =-Modello!AI30 -> 6.6280775 | AD64: =-Modello!AI31 -> 6.8158919 | AE64: =-Modello!AI32 -> 7.0052055 | AF64: =-Modello!AI33 -> 7.1960376 | AG64: =-Modello!AI34 -> 7.3884078 | AH64: =-Modello!AI35 -> 7.5823356 | AI64: =-Modello!AI36 -> 7.7778409 | AJ64: =-Modello!AI37 -> 7.9749436 | AK64: =-Modello!AI38 -> 8.1736638
A67: IId: Flusso BRDP totale verso P2 = Cedole + Rimborsi (€mld reali €2027) | B67: r_BRDP_r | C67: rf_r | D67: 2027 | E67: 2028 | F67: 2029 | G67: 2030 | H67: 2031 | I67: 2032 | J67: 2033 | K67: 2034 | L67: 2035 | M67: 2036 | N67: 2037 | O67: 2038 | P67: 2039 | Q67: 2040 | R67: 2041 | S67: 2042 | T67: 2043 | U67: 2044 | V67: 2045 | W67: 2046 | X67: 2047 | Y67: 2048 | Z67: 2049 | AA67: 2050 | AB67: 2051 | AC67: 2052 | AD67: 2053 | AE67: 2054 | AF67: 2055 | AG67: 2056 | AH67: 2057 | AI67: 2058 | AJ67: 2059 | AK67: 2060
A68: r_BRDP=0.75% | B68: 0.0075 | C68: — | D68: =D57+D64 -> 0 | E68: =E57+E64 -> 0.023128875 | F68: =F57+F64 -> 0.050140221 | G68: =G57+G64 -> 0.081062621 | H68: =H57+H64 -> 0.11592507 | I68: =I57+I64 -> 0.15475699 | J68: =J57+J64 -> 0.1975882 | K68: =K57+K64 -> 0.24177394 | ... AK68: =AK57+AK64 -> 8.2977715
A69: r_BRDP=1.50% | B69: 0.015 | C69: — | D69: =D58+D64 -> 0 | E69: =E58+E64 -> 0.04625775 | F69: =F58+F64 -> 0.10028044 | G69: =G58+G64 -> 0.16212524 | H69: =H58+H64 -> 0.23185015 | I69: =I58+I64 -> 0.30951398 | J69: =J58+J64 -> 0.39517641 | K69: =K58+K64 -> 0.48354787 | ... AK69: =AK58+AK64 -> 8.4218791
A70: r_BRDP=2.50% | B70: 0.025 | C70: — | D70: =D59+D64 -> 0 | E70: =E59+E64 -> 0.07709625 | F70: =F59+F64 -> 0.16713407 | G70: =G59+G64 -> 0.27020874 | H70: =H59+H64 -> 0.38641691 | I70: =I59+I64 -> 0.51585664 | J70: =J59+J64 -> 0.65862734 | K70: =K59+K64 -> 0.80591312 | ... AK70: =AK59+AK64 -> 8.587356
A71: r_BRDP=3.50% | B71: 0.035 | C71: — | D71: =D60+D64 -> 0 | E71: =E60+E64 -> 0.10793475 | F71: =F60+F64 -> 0.2339877 | G71: =G60+G64 -> 0.37829223 | H71: =H60+H64 -> 0.54098368 | I71: =I60+I64 -> 0.72219929 | J71: =J60+J64 -> 0.92207828 | K71: =K60+K64 -> 1.1282784 | ... AK71: =AK60+AK64 -> 8.7528328
A74: IIe: Cedole cumulate BRDP (€mld reali €2027) | B74: r_BRDP_r | C74: rf_r | D74: 2027 | E74: 2028 | F74: 2029 | G74: 2030 | H74: 2031 | I74: 2032 | J74: 2033 | K74: 2034 | L74: 2035 | M74: 2036 | N74: 2037 | O74: 2038 | P74: 2039 | Q74: 2040 | R74: 2041 | S74: 2042 | T74: 2043 | U74: 2044 | V74: 2045 | W74: 2046 | X74: 2047 | Y74: 2048 | Z74: 2049 | AA74: 2050 | AB74: 2051 | AC74: 2052 | AD74: 2053 | AE74: 2054 | AF74: 2055 | AG74: 2056 | AH74: 2057 | AI74: 2058 | AJ74: 2059 | AK74: 2060
A75: r_BRDP=0.75% | B75: 0.0075 | C75: — | D75: =D57 -> 0 | E75: =D75+E57 -> 0.023128875 | F75: =E75+F57 -> 0.073269096 | G75: =F75+G57 -> 0.15433172 | H75: =G75+H57 -> 0.27025679 | I75: =H75+I57 -> 0.42501378 | J75: =I75+J57 -> 0.62260199 | K75: =J75+K57 -> 0.86437592 | L75: =K75+L57 -> 1.1517006 | ... AK75: =AJ75+AK57 -> 14.103758
A76: r_BRDP=1.50% | B76: 0.015 | C76: — | D76: =D58 -> 0 | E76: =D76+E58 -> 0.04625775 | F76: =E76+F58 -> 0.14653819 | G76: =F76+G58 -> 0.30866343 | H76: =G76+H58 -> 0.54051358 | I76: =H76+I58 -> 0.85002756 | J76: =I76+J58 -> 1.245204 | K76: =J76+K58 -> 1.7287518 | L76: =K76+L58 -> 2.3034013 | ... AK76: =AJ76+AK58 -> 28.207515
A77: r_BRDP=2.50% | B77: 0.025 | C77: — | D77: =D59 -> 0 | E77: =D77+E59 -> 0.07709625 | F77: =E77+F59 -> 0.24423032 | G77: =F77+G59 -> 0.51443906 | H77: =G77+H59 -> 0.90085597 | I77: =H77+I59 -> 1.4167126 | J77: =I77+J59 -> 2.07534 | K77: =J77+K59 -> 2.8812531 | L77: =K77+L59 -> 3.8390022 | ... AK77: =AJ77+AK59 -> 47.012525
A78: r_BRDP=3.50% | B78: 0.035 | C78: — | D78: =D60 -> 0 | E78: =D78+E60 -> 0.10793475 | F78: =E78+F60 -> 0.34192245 | G78: =F78+G60 -> 0.72021468 | H78: =G78+H60 -> 1.2611984 | I78: =H78+I60 -> 1.9833977 | J78: =I78+J60 -> 2.9054759 | K78: =J78+K60 -> 4.0337543 | L78: =K78+L60 -> 5.374603 | ... AK78: =AJ78+AK60 -> 65.817535
A82: SEZIONE III — RENDIMENTO IMPLICITO PAYG: DECOMPOSIZIONE CONTRIBUTIVA/FISCALE (€mld reali €2027)
A83: Spesa_contrib(t) = quota_contrib_0 × H(0) × (1+g_w)^t × (1+g_occ)^t — cresce col monte salari (Aaron-Samuelson). Spesa_fiscale = H(t) − spesa_contrib(t). Indipendente da r_BRDP e rf.
A84: Scenario | B84: — | C84: — | D84: 2027 | E84: 2028 | F84: 2029 | G84: 2030 | H84: 2031 | I84: 2032 | J84: 2033 | K84: 2034 | L84: 2035 | M84: 2036 | N84: 2037 | O84: 2038 | P84: 2039 | Q84: 2040 | R84: 2041 | S84: 2042 | T84: 2043 | U84: 2044 | V84: 2045 | W84: 2046 | X84: 2047 | Y84: 2048 | Z84: 2049 | AA84: 2050 | AB84: 2051 | AC84: 2052 | AD84: 2053 | AE84: 2054 | AF84: 2055 | AG84: 2056 | AH84: 2057 | AI84: 2058 | AJ84: 2059 | AK84: 2060
A85: IIIa: Spesa PAYG coperta da contributi (€mld reali €2027)
A86: BASE (g=0.8%, g_w=0.2%) | B86: — | C86: — | D86: =Parametri!$B$136*Modello!H5 -> 260.56576 | E86: =D86*(1+Parametri!$B$22)*(1+Parametri!$B$15) -> 259.78146 | F86: =E86*(1+Parametri!$B$22)*(1+Parametri!$B$15) -> 258.99951 | G86: =F86*(1+Parametri!$B$22)*(1+Parametri!$B$15) -> 258.21993 | H86: =G86*(1+Parametri!$B$22)*(1+Parametri!$B$15) -> 257.44268 | I86: =H86*(1+Parametri!$B$22)*(1+Parametri!$B$15) -> 256.66778 | J86: =I86*(1+Parametri!$B$22)*(1+Parametri!$B$15) -> 255.89521 | K86: =J86*(1+Parametri!$B$22)*(1+Parametri!$B$15) -> 255.12497 | L86: =K86*(1+Parametri!$B$22)*(1+Parametri!$B$15) -> 254.35704 | ... AK86: =AJ86*(1+Parametri!$B$22)*(1+Parametri!$B$15) -> 235.89233
A87: PESSIMISTA (g=0.3%, g_w=0.0%) | B87: — | C87: — | D87: =Parametri!$B$136*Modello!H5 -> 260.56576 | E87: =D87*(1+Parametri!$B$130)*(1+Parametri!$B$15) -> 259.26293 | F87: =E87*(1+Parametri!$B$130)*(1+Parametri!$B$15) -> 257.96662 | G87: =F87*(1+Parametri!$B$130)*(1+Parametri!$B$15) -> 256.67678 | H87: =G87*(1+Parametri!$B$130)*(1+Parametri!$B$15) -> 255.3934 | I87: =H87*(1+Parametri!$B$130)*(1+Parametri!$B$15) -> 254.11643 | J87: =I87*(1+Parametri!$B$130)*(1+Parametri!$B$15) -> 252.84585 | K87: =J87*(1+Parametri!$B$130)*(1+Parametri!$B$15) -> 251.58162 | L87: =K87*(1+Parametri!$B$130)*(1+Parametri!$B$15) -> 250.32371 | ... AK87: =AJ87*(1+Parametri!$B$130)*(1+Parametri!$B$15) -> 220.84065
A88: IIIb: Spesa PAYG coperta da fiscalità generale (€mld reali €2027)
A89: BASE (g=0.8%, g_w=0.2%) | B89: — | C89: — | D89: =Modello!H5-D86 -> 97.35424 | E89: =Modello!H6-E86 -> 102.90989 | F89: =Modello!H7-F86 -> 108.51662 | G89: =Modello!H8-G86 -> 114.17497 | H89: =Modello!H9-H86 -> 119.88552 | I89: =Modello!H10-I86 -> 125.64883 | J89: =Modello!H11-J86 -> 131.46547 | K89: =Modello!H12-K86 -> 137.33603 | L89: =Modello!H13-L86 -> 143.26108 | M89: =Modello!H14-M86 -> 149.24121 | N89: =Modello!H15-N86 -> 155.27703 | O89: =Modello!H16-O86 -> 161.36912 | P89: =Modello!H17-P86 -> 167.51811 | Q89: =Modello!H18-Q86 -> 173.72459 | R89: =Modello!H19-R86 -> 174.12147 | S89: =Modello!H20-S86 -> 174.4832 | T89: =Modello!H21-T86 -> 174.8093 | U89: =Modello!H22-U86 -> 175.09926 | V89: =Modello!H23-V86 -> 175.35257 | W89: =Modello!H24-W86 -> 175.56873 | X89: =Modello!H25-X86 -> 175.7472 | Y89: =Modello!H26-Y86 -> 175.88746 | Z89: =Modello!H27-Z86 -> 175.98898 | AA89: =Modello!H28-AA86 -> 176.05122 | AB89: =Modello!H29-AB86 -> 176.07363 | AC89: =Modello!H30-AC86 -> 176.05567 | AD89: =Modello!H31-AD86 -> 175.99677 | AE89: =Modello!H32-AE86 -> 175.89636 | AF89: =Modello!H33-AF86 -> 175.75388 | AG89: =Modello!H34-AG86 -> 175.56875 | AH89: =Modello!H35-AH86 -> 175.34037 | AI89: =Modello!H36-AI86 -> 175.06817 | AJ89: =Modello!H37-AJ86 -> 174.75153 | AK89: =Modello!H38-AK86 -> 174.38985
A90: PESSIMISTA (g=0.3%, g_w=0.0%) | B90: — | C90: — | D90: =Modello_Pess!H5-D87 -> 97.35424 | E90: =Modello_Pess!H6-E87 -> 101.62935 | F90: =Modello_Pess!H7-F87 -> 105.91257 | G90: =Modello_Pess!H8-G87 -> 110.20397 | H90: =Modello_Pess!H9-H87 -> 114.50366 | I90: =Modello_Pess!H10-I87 -> 118.81173 | J90: =Modello_Pess!H11-J87 -> 123.12827 | K90: =Modello_Pess!H12-K87 -> 127.45337 | L90: =Modello_Pess!H13-L87 -> 131.78714 | M90: =Modello_Pess!H14-M87 -> 136.12966 | N90: =Modello_Pess!H15-N87 -> 140.48103 | O90: =Modello_Pess!H16-O87 -> 144.84134 | P90: =Modello_Pess!H17-P87 -> 149.21069 | Q90: =Modello_Pess!H18-Q87 -> 153.58917 | R90: =Modello_Pess!H19-R87 -> 152.50375 | S90: =Modello_Pess!H20-S87 -> 151.39481 | T90: =Modello_Pess!H21-T87 -> 150.2623 | U90: =Modello_Pess!H22-U87 -> 149.10616 | V90: =Modello_Pess!H23-V87 -> 147.92634 | W90: =Modello_Pess!H24-W87 -> 146.72279 | X90: =Modello_Pess!H25-X87 -> 145.49544 | Y90: =Modello_Pess!H26-Y87 -> 144.24425 | Z90: =Modello_Pess!H27-Z87 -> 142.96916 | AA90: =Modello_Pess!H28-AA87 -> 141.67011 | AB90: =Modello_Pess!H29-AB87 -> 140.34704 | AC90: =Modello_Pess!H30-AC87 -> 138.9999 | AD90: =Modello_Pess!H31-AD87 -> 137.62863 | AE90: =Modello_Pess!H32-AE87 -> 136.23317 | AF90: =Modello_Pess!H33-AF87 -> 134.81345 | AG90: =Modello_Pess!H34-AG87 -> 133.36943 | AH90: =Modello_Pess!H35-AH87 -> 131.90104 | AI90: =Modello_Pess!H36-AI87 -> 130.40821 | AJ90: =Modello_Pess!H37-AJ87 -> 128.8909 | AK90: =Modello_Pess!H38-AK87 -> 127.34903
A91: IIIc: Quota spesa PAYG coperta da contributi — dinamica (%)
A92: BASE (g=0.8%, g_w=0.2%) | B92: — | C92: — | D92: =D86/Modello!H5 -> 0.728 | E92: =E86/Modello!H6 -> 0.71626042 | F92: =F86/Modello!H7 -> 0.70472965 | G92: =G86/Modello!H8 -> 0.6934035 | H92: =H86/Modello!H9 -> 0.68227787 | I92: =I86/Modello!H10 -> 0.67134875 | J92: =J86/Modello!H11 -> 0.66061224 | K92: =K86/Modello!H12 -> 0.65006452 | L92: =L86/Modello!H13 -> 0.63970184 | M92: =M86/Modello!H14 -> 0.62952056 | N92: =N86/Modello!H15 -> 0.6195171 | O92: =O86/Modello!H16 -> 0.60968799 | P92: =P86/Modello!H17 -> 0.60002982 | Q92: =Q86/Modello!H18 -> 0.59053924 | R92: =R86/Modello!H19 -> 0.58925794 | S92: =S86/Modello!H20 -> 0.58802546 | T92: =T86/Modello!H21 -> 0.58684235 | U92: =U86/Modello!H22 -> 0.58570915 | V92: =V86/Modello!H23 -> 0.58462646 | W92: =W86/Modello!H24 -> 0.58359489 | X92: =X86/Modello!H25 -> 0.58261509 | Y92: =Y86/Modello!H26 -> 0.58168774 | Z92: =Z86/Modello!H27 -> 0.58081356 | AA92: =AA86/Modello!H28 -> 0.5799933 | AB92: =AB86/Modello!H29 -> 0.57922775 | AC92: =AC86/Modello!H30 -> 0.57851775 | AD92: =AD86/Modello!H31 -> 0.57786415 | AE92: =AE86/Modello!H32 -> 0.57726789 | AF92: =AF86/Modello!H33 -> 0.57672991 | AG92: =AG86/Modello!H34 -> 0.57625123 | AH92: =AH86/Modello!H35 -> 0.5758329 | AI92: =AI86/Modello!H36 -> 0.57547604 | AJ92: =AJ86/Modello!H37 -> 0.57518181 | AK92: =AK86/Modello!H38 -> 0.57495144
A93: PESSIMISTA (g=0.3%, g_w=0.0%) | B93: — | C93: — | D93: =D87/Modello_Pess!H5 -> 0.728 | E93: =E87/Modello_Pess!H6 -> 0.71839422 | F93: =F87/Modello_Pess!H7 -> 0.7089348 | G93: =G87/Modello_Pess!H8 -> 0.6996191 | H93: =H87/Modello_Pess!H9 -> 0.69044453 | I93: =I87/Modello_Pess!H10 -> 0.68140854 | J93: =J87/Modello_Pess!H11 -> 0.67250866 | K93: =K87/Modello_Pess!H12 -> 0.66374246 | L93: =L87/Modello_Pess!H13 -> 0.65510757 | M93: =M87/Modello_Pess!H14 -> 0.64660166 | N93: =N87/Modello_Pess!H15 -> 0.63822245 | O93: =O87/Modello_Pess!H16 -> 0.62996772 | P93: =P87/Modello_Pess!H17 -> 0.62183529 | Q93: =Q87/Modello_Pess!H18 -> 0.61382302 | R93: =R87/Modello_Pess!H19 -> 0.61431586 | S93: =S87/Modello_Pess!H20 -> 0.61485725 | T93: =T87/Modello_Pess!H21 -> 0.61544817 | U93: =U87/Modello_Pess!H22 -> 0.61608967 | V93: =V87/Modello_Pess!H23 -> 0.61678281 | W93: =W87/Modello_Pess!H24 -> 0.61752871 | X93: =X87/Modello_Pess!H25 -> 0.61832852 | Y93: =Y87/Modello_Pess!H26 -> 0.61918345 | Z93: =Z87/Modello_Pess!H27 -> 0.62009475 | AA93: =AA87/Modello_Pess!H28 -> 0.62106372 | AB93: =AB87/Modello_Pess!H29 -> 0.62209172 | AC93: =AC87/Modello_Pess!H30 -> 0.62318017 | AD93: =AD87/Modello_Pess!H31 -> 0.62433053 | AE93: =AE87/Modello_Pess!H32 -> 0.62554433 | AF93: =AF87/Modello_Pess!H33 -> 0.62682317 | AG93: =AG87/Modello_Pess!H34 -> 0.62816873 | AH93: =AH87/Modello_Pess!H35 -> 0.62958272 | AI93: =AI87/Modello_Pess!H36 -> 0.63106697 | AJ93: =AJ87/Modello_Pess!H37 -> 0.63262336 | AK93: =AK87/Modello_Pess!H38 -> 0.63425387
A94: IIId: Rendimento implicito PAYG — tasso Aaron (g_w+g_occ, % p.a.)
A95: BASE | B95: — | C95: — | D95: =Parametri!$B$22+Parametri!$B$15 -> -0.003 | E95: =Parametri!$B$22+Parametri!$B$15 -> -0.003 | F95: =Parametri!$B$22+Parametri!$B$15 -> -0.003 | G95: =Parametri!$B$22+Parametri!$B$15 -> -0.003 | H95: =Parametri!$B$22+Parametri!$B$15 -> -0.003 | I95: =Parametri!$B$22+Parametri!$B$15 -> -0.003 | J95: =Parametri!$B$22+Parametri!$B$15 -> -0.003 | K95: =Parametri!$B$22+Parametri!$B$15 -> -0.003 | ... AK95: =Parametri!$B$22+Parametri!$B$15 -> -0.003
A96: PESSIMISTA | B96: — | C96: — | D96: =Parametri!$B$130+Parametri!$B$15 -> -0.005 | E96: =Parametri!$B$130+Parametri!$B$15 -> -0.005 | F96: =Parametri!$B$130+Parametri!$B$15 -> -0.005 | G96: =Parametri!$B$130+Parametri!$B$15 -> -0.005 | H96: =Parametri!$B$130+Parametri!$B$15 -> -0.005 | I96: =Parametri!$B$130+Parametri!$B$15 -> -0.005 | J96: =Parametri!$B$130+Parametri!$B$15 -> -0.005 | K96: =Parametri!$B$130+Parametri!$B$15 -> -0.005 | ... AK96: =Parametri!$B$130+Parametri!$B$15 -> -0.005
A98: SEZIONE IV — BRDP ESTERI (dettaglio forecasting, switch Parametri!B159, importo Parametri!B160, spread Parametri!B161)
A99: Scenario | B99: spread_BRDP_est | C99: — | D99: 2027 | E99: 2028 | F99: 2029 | G99: 2030 | H99: 2031 | I99: 2032 | J99: 2033 | K99: 2034 | L99: 2035 | M99: 2036 | N99: 2037 | O99: 2038 | P99: 2039 | Q99: 2040 | R99: 2041 | S99: 2042 | T99: 2043 | U99: 2044 | V99: 2045 | W99: 2046 | X99: 2047 | Y99: 2048 | Z99: 2049 | AA99: 2050 | AB99: 2051 | AC99: 2052 | AD99: 2053 | AE99: 2054 | AF99: 2055 | AG99: 2056 | AH99: 2057 | AI99: 2058 | AJ99: 2059 | AK99: 2060
A100: IVa: BRDP esteri emessi annui (= Modello!AA) | B100: — | C100: — | D100: =Modello!AA5 -> 0 | E100: =Modello!AA6 -> 0 | F100: =Modello!AA7 -> 0 | G100: =Modello!AA8 -> 0 | H100: =Modello!AA9 -> 0 | I100: =Modello!AA10 -> 0 | J100: =Modello!AA11 -> 0 | K100: =Modello!AA12 -> 0 | L100: =Modello!AA13 -> 0 | M100: =Modello!AA14 -> 0 | N100: =Modello!AA15 -> 0 | O100: =Modello!AA16 -> 0 | P100: =Modello!AA17 -> 0 | Q100: =Modello!AA18 -> 0 | R100: =Modello!AA19 -> 0 | S100: =Modello!AA20 -> 0 | T100: =Modello!AA21 -> 0 | U100: =Modello!AA22 -> 0 | V100: =Modello!AA23 -> 0 | W100: =Modello!AA24 -> 0 | X100: =Modello!AA25 -> 0 | Y100: =Modello!AA26 -> 0 | Z100: =Modello!AA27 -> 0 | AA100: =Modello!AA28 -> 0 | AB100: =Modello!AA29 -> 0 | AC100: =Modello!AA30 -> 0 | AD100: =Modello!AA31 -> 0 | AE100: =Modello!AA32 -> 0 | AF100: =Modello!AA33 -> 0 | AG100: =Modello!AA34 -> 0 | AH100: =Modello!AA35 -> 0 | AI100: =Modello!AA36 -> 0 | AJ100: =Modello!AA37 -> 0 | AK100: =Modello!AA38 -> 0
A101: IVb: Stock BRDP esteri cumulato | B101: — | C101: — | D101: =SUM(Modello!AA$5:AA5) -> 0 | E101: =SUM(Modello!AA$5:AA6) -> 0 | F101: =SUM(Modello!AA$5:AA7) -> 0 | G101: =SUM(Modello!AA$5:AA8) -> 0 | H101: =SUM(Modello!AA$5:AA9) -> 0 | I101: =SUM(Modello!AA$5:AA10) -> 0 | J101: =SUM(Modello!AA$5:AA11) -> 0 | K101: =SUM(Modello!AA$5:AA12) -> 0 | L101: =SUM(Modello!AA$5:AA13) -> 0 | M101: =SUM(Modello!AA$5:AA14) -> 0 | N101: =SUM(Modello!AA$5:AA15) -> 0 | O101: =SUM(Modello!AA$5:AA16) -> 0 | P101: =SUM(Modello!AA$5:AA17) -> 0 | Q101: =SUM(Modello!AA$5:AA18) -> 0 | R101: =SUM(Modello!AA$5:AA19) -> 0 | S101: =SUM(Modello!AA$5:AA20) -> 0 | T101: =SUM(Modello!AA$5:AA21) -> 0 | U101: =SUM(Modello!AA$5:AA22) -> 0 | V101: =SUM(Modello!AA$5:AA23) -> 0 | W101: =SUM(Modello!AA$5:AA24) -> 0 | X101: =SUM(Modello!AA$5:AA25) -> 0 | Y101: =SUM(Modello!AA$5:AA26) -> 0 | Z101: =SUM(Modello!AA$5:AA27) -> 0 | AA101: =SUM(Modello!AA$5:AA28) -> 0 | AB101: =SUM(Modello!AA$5:AA29) -> 0 | AC101: =SUM(Modello!AA$5:AA30) -> 0 | AD101: =SUM(Modello!AA$5:AA31) -> 0 | AE101: =SUM(Modello!AA$5:AA32) -> 0 | AF101: =SUM(Modello!AA$5:AA33) -> 0 | AG101: =SUM(Modello!AA$5:AA34) -> 0 | AH101: =SUM(Modello!AA$5:AA35) -> 0 | AI101: =SUM(Modello!AA$5:AA36) -> 0 | AJ101: =SUM(Modello!AA$5:AA37) -> 0 | AK101: =SUM(Modello!AA$5:AA38) -> 0
A102: IVc: Cedole BRDP esteri annue (= Parametri!B161 × stock esteri) | B102: =Parametri!$B$161 -> 0.02 | C102: — | D102: =Parametri!$B$161*D101 -> 0 | E102: =Parametri!$B$161*E101 -> 0 | F102: =Parametri!$B$161*F101 -> 0 | G102: =Parametri!$B$161*G101 -> 0 | H102: =Parametri!$B$161*H101 -> 0 | I102: =Parametri!$B$161*I101 -> 0 | J102: =Parametri!$B$161*J101 -> 0 | K102: =Parametri!$B$161*K101 -> 0 | ... AK102: =Parametri!$B$161*AK101 -> 0
A103: IVd: Rimborsi BRDP esteri (capitale, a investitori esteri) | B103: — | C103: — | D103: 0 | E103: 0 | F103: 0 | G103: 0 | H103: 0 | I103: 0 | J103: 0 | K103: 0 | L103: 0 | M103: 0 | N103: 0 | O103: 0 | P103: 0 | Q103: 0 | R103: 0 | S103: =Modello!AA5 -> 0 | T103: =Modello!AA6 -> 0 | U103: =Modello!AA7 -> 0 | V103: =Modello!AA8 -> 0 | W103: =Modello!AA9 -> 0 | X103: =Modello!AA10 -> 0 | Y103: =Modello!AA11 -> 0 | Z103: =Modello!AA12 -> 0 | AA103: =Modello!AA13 -> 0 | AB103: =Modello!AA14 -> 0 | AC103: =Modello!AA15 -> 0 | AD103: =Modello!AA16 -> 0 | AE103: =Modello!AA17 -> 0 | AF103: =Modello!AA18 -> 0 | AG103: =Modello!AA19 -> 0 | AH103: =Modello!AA20 -> 0 | AI103: =Modello!AA21 -> 0 | AJ103: =Modello!AA22 -> 0 | AK103: =Modello!AA23 -> 0
A104: IVe: Cedole BRDP esteri cumulate | B104: — | C104: — | D104: =D102 -> 0 | E104: =D104+E102 -> 0 | F104: =E104+F102 -> 0 | G104: =F104+G102 -> 0 | H104: =G104+H102 -> 0 | I104: =H104+I102 -> 0 | J104: =I104+J102 -> 0 | K104: =J104+K102 -> 0 | L104: =K104+L102 -> 0 | ... AK104: =AJ104+AK102 -> 0
A105: IVf: Flusso BRDP esteri totale verso investitori esteri (cedole + rimborsi) | B105: — | C105: — | D105: =D102+D103 -> 0 | E105: =E102+E103 -> 0 | F105: =F102+F103 -> 0 | G105: =G102+G103 -> 0 | H105: =H102+H103 -> 0 | I105: =I102+I103 -> 0 | J105: =J102+J103 -> 0 | K105: =K102+K103 -> 0 | ... AK105: =AK102+AK103 -> 0
A106: IVg: Stock BRDP interni cumulato (= Modello!AB − stock esteri) | B106: — | C106: — | D106: =Modello!AB5-D101 -> 3.08385 | E106: =Modello!AB6-E101 -> 6.6853627 | F106: =Modello!AB7-F101 -> 10.80835 | G106: =Modello!AB8-G101 -> 15.456677 | H106: =Modello!AB9-H101 -> 20.634265 | I106: =Modello!AB10-I101 -> 26.345094 | J106: =Modello!AB11-J101 -> 32.236525 | K106: =Modello!AB12-K101 -> 38.309963 | L106: =Modello!AB13-L101 -> 44.566833 | M106: =Modello!AB14-M101 -> 51.008576 | N106: =Modello!AB15-N101 -> 57.636654 | O106: =Modello!AB16-O101 -> 64.452546 | P106: =Modello!AB17-P101 -> 71.457751 | Q106: =Modello!AB18-Q101 -> 78.653789 | R106: =Modello!AB19-R101 -> 86.042197 | S106: =Modello!AB20-S101 -> 90.540682 | T106: =Modello!AB21-T101 -> 94.71701 | U106: =Modello!AB22-U101 -> 98.568967 | V106: =Modello!AB23-V101 -> 102.0943 | W106: =Modello!AB24-W101 -> 105.29074 | X106: =Modello!AB25-X101 -> 99.579909 | Y106: =Modello!AB26-Y101 -> 93.688478 | Z106: =Modello!AB27-Z101 -> 87.615039 | AA106: =Modello!AB28-AA101 -> 81.358169 | AB106: =Modello!AB29-AB101 -> 74.916426 | AC106: =Modello!AB30-AC101 -> 68.288349 | AD106: =Modello!AB31-AD101 -> 61.472457 | AE106: =Modello!AB32-AE101 -> 54.467251 | AF106: =Modello!AB33-AF101 -> 47.271214 | AG106: =Modello!AB34-AG101 -> 39.882806 | AH106: =Modello!AB35-AH101 -> 32.30047 | AI106: =Modello!AB36-AI101 -> 24.522629 | AJ106: =Modello!AB37-AJ101 -> 16.547686 | AK106: =Modello!AB38-AK101 -> 8.374022
A107: IVh: Quota BRDP esteri su totale (stock) | B107: — | C107: — | D107: =IFERROR(D101/Modello!AB5,0) -> 0 | E107: =IFERROR(E101/Modello!AB6,0) -> 0 | F107: =IFERROR(F101/Modello!AB7,0) -> 0 | G107: =IFERROR(G101/Modello!AB8,0) -> 0 | H107: =IFERROR(H101/Modello!AB9,0) -> 0 | I107: =IFERROR(I101/Modello!AB10,0) -> 0 | J107: =IFERROR(J101/Modello!AB11,0) -> 0 | K107: =IFERROR(K101/Modello!AB12,0) -> 0 | L107: =IFERROR(L101/Modello!AB13,0) -> 0 | M107: =IFERROR(M101/Modello!AB14,0) -> 0 | N107: =IFERROR(N101/Modello!AB15,0) -> 0 | O107: =IFERROR(O101/Modello!AB16,0) -> 0 | P107: =IFERROR(P101/Modello!AB17,0) -> 0 | Q107: =IFERROR(Q101/Modello!AB18,0) -> 0 | R107: =IFERROR(R101/Modello!AB19,0) -> 0 | S107: =IFERROR(S101/Modello!AB20,0) -> 0 | T107: =IFERROR(T101/Modello!AB21,0) -> 0 | U107: =IFERROR(U101/Modello!AB22,0) -> 0 | V107: =IFERROR(V101/Modello!AB23,0) -> 0 | W107: =IFERROR(W101/Modello!AB24,0) -> 0 | X107: =IFERROR(X101/Modello!AB25,0) -> 0 | Y107: =IFERROR(Y101/Modello!AB26,0) -> 0 | Z107: =IFERROR(Z101/Modello!AB27,0) -> 0 | AA107: =IFERROR(AA101/Modello!AB28,0) -> 0 | AB107: =IFERROR(AB101/Modello!AB29,0) -> 0 | AC107: =IFERROR(AC101/Modello!AB30,0) -> 0 | AD107: =IFERROR(AD101/Modello!AB31,0) -> 0 | AE107: =IFERROR(AE101/Modello!AB32,0) -> 0 | AF107: =IFERROR(AF101/Modello!AB33,0) -> 0 | AG107: =IFERROR(AG101/Modello!AB34,0) -> 0 | AH107: =IFERROR(AH101/Modello!AB35,0) -> 0 | AI107: =IFERROR(AI101/Modello!AB36,0) -> 0 | AJ107: =IFERROR(AJ101/Modello!AB37,0) -> 0 | AK107: =IFERROR(AK101/Modello!AB38,0) -> 0
A108: IVi: Cedole TOTALI annue (raccordo = -Modello!AC) | B108: — | C108: — | D108: =-Modello!AC5 -> 0.04625775 | E108: =-Modello!AC6 -> 0.10028044 | F108: =-Modello!AC7 -> 0.16212524 | G108: =-Modello!AC8 -> 0.23185015 | H108: =-Modello!AC9 -> 0.30951398 | I108: =-Modello!AC10 -> 0.39517641 | J108: =-Modello!AC11 -> 0.48354787 | K108: =-Modello!AC12 -> 0.57464945 | L108: =-Modello!AC13 -> 0.6685025 | M108: =-Modello!AC14 -> 0.76512864 | N108: =-Modello!AC15 -> 0.86454981 | O108: =-Modello!AC16 -> 0.96678818 | P108: =-Modello!AC17 -> 1.0718663 | Q108: =-Modello!AC18 -> 1.1798068 | R108: =-Modello!AC19 -> 1.2906329 | S108: =-Modello!AC20 -> 1.404368 | T108: =-Modello!AC21 -> 1.5210356 | U108: =-Modello!AC22 -> 1.6406597 | V108: =-Modello!AC23 -> 1.7632647 | W108: =-Modello!AC24 -> 1.888875 | X108: =-Modello!AC25 -> 1.888875 | Y108: =-Modello!AC26 -> 1.888875 | Z108: =-Modello!AC27 -> 1.888875 | AA108: =-Modello!AC28 -> 1.888875 | AB108: =-Modello!AC29 -> 1.888875 | AC108: =-Modello!AC30 -> 1.888875 | AD108: =-Modello!AC31 -> 1.888875 | AE108: =-Modello!AC32 -> 1.888875 | AF108: =-Modello!AC33 -> 1.888875 | AG108: =-Modello!AC34 -> 1.888875 | AH108: =-Modello!AC35 -> 1.888875 | AI108: =-Modello!AC36 -> 1.888875 | AJ108: =-Modello!AC37 -> 1.888875 | AK108: =-Modello!AC38 -> 1.888875

Sheet Modello_Pess
A1: MODELLO_PESS — SCENARIO PESSIMISTA (g=0.3%, g_w=0.0%) — 34 anni 2027-2060
A2: Tutti i valori in termini reali (prezzi 2027). SCENARIO PESSIMISTA: crescita PIL 0.3%/a, salari 0.0%/a (stagnazione demografica, ISTAT scenario basso).
W3: Stock BRDP vivo — formula aggregata (interno+esterno) =SUM(Z)+SUM(AA). Rimborso AD include sia Z(t-15) sia AA(t-15) — v9.
A4: Anno | B4: t | C4: Pensioni vigenti (mln) | D4: Occupati L1 (mln) | E4: Att/Pens | F4: PIL reale (€mld) | G4: Salario medio (€) | H4: Spesa PAYG SQ (€mld) | I4: Spesa PAYG %PIL (RGS) | J4: Spesa rif. (€mld) | K4: Spesa rif./PIL | L4: %Lav in P2 | M4: Lav. in P2 (mln) | N4: Leva A (€mld) | O4: Leva B (€mld) | P4: Leva C (€mld) | Q4: Leva D gap (€mld) | R4: Leva D ai fondi | S4: Leva D fondi cum | T4: Leva E (€mld) | U4: Leva F CORRETTA | V4: Leva G (€mld) | W4: Leva H (€mld) | X4: Leva I (€mld) | Y4: Leva J (€mld) | Z4: BRDP emessi (€mld) | AA4: BRDP esterni (€mld) | AB4: Stock BRDP totale (€mld) | AC4: Interessi BRDP (€mld) | AD4: Rimborso cap. BRDP (€mld) | AE4: Saldo annuo (€mld) | AF4: Saldo cum. (€mld) | AG4: Debito tr./PIL | AH4: Stock BRDP interno (€mld) | AI4: Rimborso cap. BRDP interno (€mld)
A5: =Parametri!$B$6+B5 -> 2027 | B5: 0 | C5: =Parametri!$B$9 -> 22.3 | D5: =CHOOSE(Parametri!$B$143,Parametri!$B$13,Parametri!$B$13+Parametri!$B$146,Parametri!$B$13+Parametri!$B$146) -> 17.5 | E5: =D5/C5 -> 0.78475336 | F5: =Parametri!$B$19 -> 2237 | G5: =CHOOSE(Parametri!$B$143,Parametri!$B$21,Parametri!$B$155,Parametri!$B$155) -> 26700 | H5: =F5*I5 -> 357.92 | I5: =IF(B5<=(Parametri!$B$35-Parametri!$B$6),Parametri!$B$32+(Parametri!$B$33-Parametri!$B$32)*B5/(Parametri!$B$35-Parametri!$B$6),Parametri!$B$33+(Parametri!$B$34-Parametri!$B$33)*(B5-(Parametri!$B$35-Parametri!$B$6))/(Parametri!$B$36-Parametri!$B$35)) -> 0.16 | J5: =H5-AE5 -> 348.56105 | K5: =J5/F5 -> 0.1558163 | L5: =IF(B5<=5,Parametri!$B$58+(Parametri!$B$59-Parametri!$B$58)/5*B5,MIN(Parametri!$B$60,Parametri!$B$59+(Parametri!$B$60-Parametri!$B$59)/24*(B5-5))) -> 0.33 | M5: =L5*D5 -> 5.775 | N5: =IF(B5<Parametri!$B$76,Parametri!$B$75*Parametri!$B$74*Parametri!$B$73/Parametri!$B$76,0) -> 2.44 | O5: =IF(B5<10,Parametri!$B$53,IF(B5<20,Parametri!$B$56,Parametri!$B$57))*M5*G5*Parametri!$B$72/1000 -> 1.665279 | P5: =MIN(Parametri!$B$81+Parametri!$B$82, Parametri!$B$81+Parametri!$B$82*(B5+1)/Parametri!$B$83) -> 4.1 | Q5: =-IF(B5<10,Parametri!$B$51,IF(B5<20,Parametri!$B$54,Parametri!$B$57))*M5*G5/1000 -> -9.25155 | R5: =-Q5-Z5 -> 6.1677 | S5: =R5 -> 6.1677 | T5: =-(Parametri!$B$86*(Parametri!$B$87*Parametri!$B$90+Parametri!$B$88*Parametri!$B$91+Parametri!$B$89*Parametri!$B$92)/1000000000)*MIN(B5+1,Parametri!$B$93) -> -0.57195 | U5: =IF(B5<Parametri!$B$125,Parametri!$B$46,IF(B5<Parametri!$B$126,Parametri!$B$47,Parametri!$B$48))*Parametri!$B$96*13/1000000000*((B5+1)*Parametri!$B$121+B5*(B5+1)/2*Parametri!$B$122) -> 0.93957435 | V5: =IF(B5>=Parametri!$B$103-1,Parametri!$B$102*(1-Parametri!$B$127)^(B5-(Parametri!$B$103-1)),0) -> 6 | W5: =IF(B5>=Parametri!$B$105-1,Parametri!$B$104,0) -> 0 | X5: =IF(B5>=Parametri!$B$107-1,Parametri!$B$106+Parametri!$B$128*INT((B5-(Parametri!$B$107-1))/2),0) -> 0 | Y5: =IF(AND(B5>=Parametri!$B$109-1,B5<Parametri!$B$109-1+Parametri!$B$140),Parametri!$B$108,0) -> 1 | Z5: =IF(B5<10,Parametri!$B$52,IF(B5<20,Parametri!$B$55,0))*M5*G5/1000 -> 3.08385 | AA5: =Parametri!$B$159*Parametri!$B$160 -> 0 | AB5: =SUM(Z$5:Z5)+SUM(AA$5:AA5) -> 3.08385 | AC5: =-(Parametri!$B$67*SUM(Z$5:Z5)+Parametri!$B$161*SUM(AA$5:AA5)) -> -0.04625775 | AD5: =0 -> 0 | AE5: =Z5+AA5+N5+O5+P5+Q5+T5+U5+V5+W5+X5+Y5+AC5+AD5 -> 9.3589456 | AF5: =AE5 -> 9.3589456 | AG5: =-AF5/F5 -> -0.0041837039 | AH5: =SUM(Z$5:Z5) -> 3.08385 | AI5: 0
A6: =Parametri!$B$6+B6 -> 2028 | B6: 1 | C6: =C5*(1+Parametri!$B$14) -> 22.4338 | D6: =D5*(1+Parametri!$B$15)+Parametri!$B$145*(1-Parametri!$B$15)^B5 -> 17.5285 | E6: =D6/C6 -> 0.78134333 | F6: =F5*(1+Parametri!$B$129) -> 2243.711 | G6: =G5*(1+Parametri!$B$130) -> 26700 | H6: =F6*I6 -> 360.89228 | I6: =IF(B6<=(Parametri!$B$35-Parametri!$B$6),Parametri!$B$32+(Parametri!$B$33-Parametri!$B$32)*B6/(Parametri!$B$35-Parametri!$B$6),Parametri!$B$33+(Parametri!$B$34-Parametri!$B$33)*(B6-(Parametri!$B$35-Parametri!$B$6))/(Parametri!$B$36-Parametri!$B$35)) -> 0.16084615 | J6: =H6-AE6 -> 343.52896 | K6: =J6/F6 -> 0.15310749 | L6: =IF(B6<=5,Parametri!$B$58+(Parametri!$B$59-Parametri!$B$58)/5*B6,MIN(Parametri!$B$60,Parametri!$B$59+(Parametri!$B$60-Parametri!$B$59)/24*(B6-5))) -> 0.384 | M6: =L6*D6 -> 6.730944 | N6: =IF(B6<Parametri!$B$76,Parametri!$B$75*Parametri!$B$74*Parametri!$B$73/Parametri!$B$76,0) -> 2.44 | O6: =IF(B6<10,Parametri!$B$53,IF(B6<20,Parametri!$B$56,Parametri!$B$57))*M6*G6*Parametri!$B$72/1000 -> 1.940935 | P6: =MIN(Parametri!$B$81+Parametri!$B$82, Parametri!$B$81+Parametri!$B$82*(B6+1)/Parametri!$B$83) -> 4.7 | Q6: =-IF(B6<10,Parametri!$B$51,IF(B6<20,Parametri!$B$54,Parametri!$B$57))*M6*G6/1000 -> -10.782972 | R6: =-Q6-Z6 -> 7.1886482 | S6: =S5+R6 -> 13.356348 | T6: =-(Parametri!$B$86*(Parametri!$B$87*Parametri!$B$90+Parametri!$B$88*Parametri!$B$91+Parametri!$B$89*Parametri!$B$92)/1000000000)*MIN(B6+1,Parametri!$B$93) -> -1.1439 | U6: =IF(B6<Parametri!$B$125,Parametri!$B$46,IF(B6<Parametri!$B$126,Parametri!$B$47,Parametri!$B$48))*Parametri!$B$96*13/1000000000*((B6+1)*Parametri!$B$121+B6*(B6+1)/2*Parametri!$B$122) -> 2.0551138 | V6: =IF(B6>=Parametri!$B$103-1,Parametri!$B$102*(1-Parametri!$B$127)^(B6-(Parametri!$B$103-1)),0) -> 5.91 | W6: =IF(B6>=Parametri!$B$105-1,Parametri!$B$104,0) -> 5 | X6: =IF(B6>=Parametri!$B$107-1,Parametri!$B$106+Parametri!$B$128*INT((B6-(Parametri!$B$107-1))/2),0) -> 2.75 | Y6: =IF(AND(B6>=Parametri!$B$109-1,B6<Parametri!$B$109-1+Parametri!$B$140),Parametri!$B$108,0) -> 1 | Z6: =IF(B6<10,Parametri!$B$52,IF(B6<20,Parametri!$B$55,0))*M6*G6/1000 -> 3.5943241 | AA6: =Parametri!$B$159*Parametri!$B$160 -> 0 | AB6: =SUM(Z$5:Z6)+SUM(AA$5:AA6) -> 6.6781741 | AC6: =-(Parametri!$B$67*SUM(Z$5:Z6)+Parametri!$B$161*SUM(AA$5:AA6)) -> -0.10017261 | AD6: =0 -> 0 | AE6: =Z6+AA6+N6+O6+P6+Q6+T6+U6+V6+W6+X6+Y6+AC6+AD6 -> 17.363328 | AF6: =AF5+AE6 -> 26.722274 | AG6: =-AF6/F6 -> -0.011909855 | AH6: =SUM(Z$5:Z6) -> 6.6781741 | AI6: 0
A7: =Parametri!$B$6+B7 -> 2029 | B7: 2 | C7: =C6*(1+Parametri!$B$14) -> 22.568403 | D7: =D6*(1+Parametri!$B$15)+Parametri!$B$145*(1-Parametri!$B$15)^B6 -> 17.557437 | E7: =D7/C7 -> 0.77796544 | F7: =F6*(1+Parametri!$B$129) -> 2250.4421 | G7: =G6*(1+Parametri!$B$130) -> 26700 | H7: =F7*I7 -> 363.87918 | I7: =IF(B7<=(Parametri!$B$35-Parametri!$B$6),Parametri!$B$32+(Parametri!$B$33-Parametri!$B$32)*B7/(Parametri!$B$35-Parametri!$B$6),Parametri!$B$33+(Parametri!$B$34-Parametri!$B$33)*(B7-(Parametri!$B$35-Parametri!$B$6))/(Parametri!$B$36-Parametri!$B$35)) -> 0.16169231 | J7: =H7-AE7 -> 346.09439 | K7: =J7/F7 -> 0.15378951 | L7: =IF(B7<=5,Parametri!$B$58+(Parametri!$B$59-Parametri!$B$58)/5*B7,MIN(Parametri!$B$60,Parametri!$B$59+(Parametri!$B$60-Parametri!$B$59)/24*(B7-5))) -> 0.438 | M7: =L7*D7 -> 7.6901576 | N7: =IF(B7<Parametri!$B$76,Parametri!$B$75*Parametri!$B$74*Parametri!$B$73/Parametri!$B$76,0) -> 2.44 | O7: =IF(B7<10,Parametri!$B$53,IF(B7<20,Parametri!$B$56,Parametri!$B$57))*M7*G7*Parametri!$B$72/1000 -> 2.2175339 | P7: =MIN(Parametri!$B$81+Parametri!$B$82, Parametri!$B$81+Parametri!$B$82*(B7+1)/Parametri!$B$83) -> 5.3 | Q7: =-IF(B7<10,Parametri!$B$51,IF(B7<20,Parametri!$B$54,Parametri!$B$57))*M7*G7/1000 -> -12.319633 | R7: =-Q7-Z7 -> 8.2130883 | S7: =S6+R7 -> 21.569437 | T7: =-(Parametri!$B$86*(Parametri!$B$87*Parametri!$B$90+Parametri!$B$88*Parametri!$B$91+Parametri!$B$89*Parametri!$B$92)/1000000000)*MIN(B7+1,Parametri!$B$93) -> -1.71585 | U7: =IF(B7<Parametri!$B$125,Parametri!$B$46,IF(B7<Parametri!$B$126,Parametri!$B$47,Parametri!$B$48))*Parametri!$B$96*13/1000000000*((B7+1)*Parametri!$B$121+B7*(B7+1)/2*Parametri!$B$122) -> 3.3466183 | V7: =IF(B7>=Parametri!$B$103-1,Parametri!$B$102*(1-Parametri!$B$127)^(B7-(Parametri!$B$103-1)),0) -> 5.82135 | W7: =IF(B7>=Parametri!$B$105-1,Parametri!$B$104,0) -> 5 | X7: =IF(B7>=Parametri!$B$107-1,Parametri!$B$106+Parametri!$B$128*INT((B7-(Parametri!$B$107-1))/2),0) -> 2.75 | Y7: =IF(AND(B7>=Parametri!$B$109-1,B7<Parametri!$B$109-1+Parametri!$B$140),Parametri!$B$108,0) -> 1 | Z7: =IF(B7<10,Parametri!$B$52,IF(B7<20,Parametri!$B$55,0))*M7*G7/1000 -> 4.1065442 | AA7: =Parametri!$B$159*Parametri!$B$160 -> 0 | AB7: =SUM(Z$5:Z7)+SUM(AA$5:AA7) -> 10.784718 | AC7: =-(Parametri!$B$67*SUM(Z$5:Z7)+Parametri!$B$161*SUM(AA$5:AA7)) -> -0.16177077 | AD7: =0 -> 0 | AE7: =Z7+AA7+N7+O7+P7+Q7+T7+U7+V7+W7+X7+Y7+AC7+AD7 -> 17.784793 | AF7: =AF6+AE7 -> 44.507067 | AG7: =-AF7/F7 -> -0.019777032 | AH7: =SUM(Z$5:Z7) -> 10.784718 | AI7: 0
A8: =Parametri!$B$6+B8 -> 2030 | B8: 3 | C8: =C7*(1+Parametri!$B$14) -> 22.703813 | D8: =D7*(1+Parametri!$B$15)+Parametri!$B$145*(1-Parametri!$B$15)^B7 -> 17.586813 | E8: =D8/C8 -> 0.77461936 | F8: =F7*(1+Parametri!$B$129) -> 2257.1935 | G8: =G7*(1+Parametri!$B$130) -> 26700 | H8: =F8*I8 -> 366.88075 | I8: =IF(B8<=(Parametri!$B$35-Parametri!$B$6),Parametri!$B$32+(Parametri!$B$33-Parametri!$B$32)*B8/(Parametri!$B$35-Parametri!$B$6),Parametri!$B$33+(Parametri!$B$34-Parametri!$B$33)*(B8-(Parametri!$B$35-Parametri!$B$6))/(Parametri!$B$36-Parametri!$B$35)) -> 0.16253846 | J8: =H8-AE8 -> 351.80751 | K8: =J8/F8 -> 0.15586059 | L8: =IF(B8<=5,Parametri!$B$58+(Parametri!$B$59-Parametri!$B$58)/5*B8,MIN(Parametri!$B$60,Parametri!$B$59+(Parametri!$B$60-Parametri!$B$59)/24*(B8-5))) -> 0.492 | M8: =L8*D8 -> 8.6527121 | N8: =IF(B8<Parametri!$B$76,Parametri!$B$75*Parametri!$B$74*Parametri!$B$73/Parametri!$B$76,0) -> 0 | O8: =IF(B8<10,Parametri!$B$53,IF(B8<20,Parametri!$B$56,Parametri!$B$57))*M8*G8*Parametri!$B$72/1000 -> 2.4950961 | P8: =MIN(Parametri!$B$81+Parametri!$B$82, Parametri!$B$81+Parametri!$B$82*(B8+1)/Parametri!$B$83) -> 5.9 | Q8: =-IF(B8<10,Parametri!$B$51,IF(B8<20,Parametri!$B$54,Parametri!$B$57))*M8*G8/1000 -> -13.861645 | R8: =-Q8-Z8 -> 9.2410965 | S8: =S7+R8 -> 30.810533 | T8: =-(Parametri!$B$86*(Parametri!$B$87*Parametri!$B$90+Parametri!$B$88*Parametri!$B$91+Parametri!$B$89*Parametri!$B$92)/1000000000)*MIN(B8+1,Parametri!$B$93) -> -2.2878 | U8: =IF(B8<Parametri!$B$125,Parametri!$B$46,IF(B8<Parametri!$B$126,Parametri!$B$47,Parametri!$B$48))*Parametri!$B$96*13/1000000000*((B8+1)*Parametri!$B$121+B8*(B8+1)/2*Parametri!$B$122) -> 4.8140878 | V8: =IF(B8>=Parametri!$B$103-1,Parametri!$B$102*(1-Parametri!$B$127)^(B8-(Parametri!$B$103-1)),0) -> 5.7340298 | W8: =IF(B8>=Parametri!$B$105-1,Parametri!$B$104,0) -> 5 | X8: =IF(B8>=Parametri!$B$107-1,Parametri!$B$106+Parametri!$B$128*INT((B8-(Parametri!$B$107-1))/2),0) -> 2.89 | Y8: =IF(AND(B8>=Parametri!$B$109-1,B8<Parametri!$B$109-1+Parametri!$B$140),Parametri!$B$108,0) -> 0 | Z8: =IF(B8<10,Parametri!$B$52,IF(B8<20,Parametri!$B$55,0))*M8*G8/1000 -> 4.6205483 | AA8: =Parametri!$B$159*Parametri!$B$160 -> 0 | AB8: =SUM(Z$5:Z8)+SUM(AA$5:AA8) -> 15.405267 | AC8: =-(Parametri!$B$67*SUM(Z$5:Z8)+Parametri!$B$161*SUM(AA$5:AA8)) -> -0.231079 | AD8: =0 -> 0 | AE8: =Z8+AA8+N8+O8+P8+Q8+T8+U8+V8+W8+X8+Y8+AC8+AD8 -> 15.073238 | AF8: =AF7+AE8 -> 59.580305 | AG8: =-AF8/F8 -> -0.026395746 | AH8: =SUM(Z$5:Z8) -> 15.405267 | AI8: 0
A9: =Parametri!$B$6+B9 -> 2031 | B9: 4 | C9: =C8*(1+Parametri!$B$14) -> 22.840036 | D9: =D8*(1+Parametri!$B$15)+Parametri!$B$145*(1-Parametri!$B$15)^B8 -> 17.616628 | E9: =D9/C9 -> 0.77130473 | F9: =F8*(1+Parametri!$B$129) -> 2263.965 | G9: =G8*(1+Parametri!$B$130) -> 26700 | H9: =F9*I9 -> 369.89706 | I9: =IF(B9<=(Parametri!$B$35-Parametri!$B$6),Parametri!$B$32+(Parametri!$B$33-Parametri!$B$32)*B9/(Parametri!$B$35-Parametri!$B$6),Parametri!$B$33+(Parametri!$B$34-Parametri!$B$33)*(B9-(Parametri!$B$35-Parametri!$B$6))/(Parametri!$B$36-Parametri!$B$35)) -> 0.16338462 | J9: =H9-AE9 -> 353.48145 | K9: =J9/F9 -> 0.15613379 | L9: =IF(B9<=5,Parametri!$B$58+(Parametri!$B$59-Parametri!$B$58)/5*B9,MIN(Parametri!$B$60,Parametri!$B$59+(Parametri!$B$60-Parametri!$B$59)/24*(B9-5))) -> 0.546 | M9: =L9*D9 -> 9.6186788 | N9: =IF(B9<Parametri!$B$76,Parametri!$B$75*Parametri!$B$74*Parametri!$B$73/Parametri!$B$76,0) -> 0 | O9: =IF(B9<10,Parametri!$B$53,IF(B9<20,Parametri!$B$56,Parametri!$B$57))*M9*G9*Parametri!$B$72/1000 -> 2.7736422 | P9: =MIN(Parametri!$B$81+Parametri!$B$82, Parametri!$B$81+Parametri!$B$82*(B9+1)/Parametri!$B$83) -> 6.5 | Q9: =-IF(B9<10,Parametri!$B$51,IF(B9<20,Parametri!$B$54,Parametri!$B$57))*M9*G9/1000 -> -15.409123 | R9: =-Q9-Z9 -> 10.272749 | S9: =S8+R9 -> 41.083282 | T9: =-(Parametri!$B$86*(Parametri!$B$87*Parametri!$B$90+Parametri!$B$88*Parametri!$B$91+Parametri!$B$89*Parametri!$B$92)/1000000000)*MIN(B9+1,Parametri!$B$93) -> -2.85975 | U9: =IF(B9<Parametri!$B$125,Parametri!$B$46,IF(B9<Parametri!$B$126,Parametri!$B$47,Parametri!$B$48))*Parametri!$B$96*13/1000000000*((B9+1)*Parametri!$B$121+B9*(B9+1)/2*Parametri!$B$122) -> 7.04457 | V9: =IF(B9>=Parametri!$B$103-1,Parametri!$B$102*(1-Parametri!$B$127)^(B9-(Parametri!$B$103-1)),0) -> 5.6480193 | W9: =IF(B9>=Parametri!$B$105-1,Parametri!$B$104,0) -> 5 | X9: =IF(B9>=Parametri!$B$107-1,Parametri!$B$106+Parametri!$B$128*INT((B9-(Parametri!$B$107-1))/2),0) -> 2.89 | Y9: =IF(AND(B9>=Parametri!$B$109-1,B9<Parametri!$B$109-1+Parametri!$B$140),Parametri!$B$108,0) -> 0 | Z9: =IF(B9<10,Parametri!$B$52,IF(B9<20,Parametri!$B$55,0))*M9*G9/1000 -> 5.1363745 | AA9: =Parametri!$B$159*Parametri!$B$160 -> 0 | AB9: =SUM(Z$5:Z9)+SUM(AA$5:AA9) -> 20.541641 | AC9: =-(Parametri!$B$67*SUM(Z$5:Z9)+Parametri!$B$161*SUM(AA$5:AA9)) -> -0.30812462 | AD9: =0 -> 0 | AE9: =Z9+AA9+N9+O9+P9+Q9+T9+U9+V9+W9+X9+Y9+AC9+AD9 -> 16.415608 | AF9: =AF8+AE9 -> 75.995913 | AG9: =-AF9/F9 -> -0.033567618 | AH9: =SUM(Z$5:Z9) -> 20.541641 | AI9: 0
A10: =Parametri!$B$6+B10 -> 2032 | B10: 5 | C10: =C9*(1+Parametri!$B$14) -> 22.977076 | D10: =D9*(1+Parametri!$B$15)+Parametri!$B$145*(1-Parametri!$B$15)^B9 -> 17.646882 | E10: =D10/C10 -> 0.76802122 | F10: =F9*(1+Parametri!$B$129) -> 2270.7569 | G10: =G9*(1+Parametri!$B$130) -> 26700 | H10: =F10*I10 -> 372.92816 | I10: =IF(B10<=(Parametri!$B$35-Parametri!$B$6),Parametri!$B$32+(Parametri!$B$33-Parametri!$B$32)*B10/(Parametri!$B$35-Parametri!$B$6),Parametri!$B$33+(Parametri!$B$34-Parametri!$B$33)*(B10-(Parametri!$B$35-Parametri!$B$6))/(Parametri!$B$36-Parametri!$B$35)) -> 0.16423077 | J10: =H10-AE10 -> 354.7131 | K10: =J10/F10 -> 0.15620919 | L10: =IF(B10<=5,Parametri!$B$58+(Parametri!$B$59-Parametri!$B$58)/5*B10,MIN(Parametri!$B$60,Parametri!$B$59+(Parametri!$B$60-Parametri!$B$59)/24*(B10-5))) -> 0.6 | M10: =L10*D10 -> 10.588129 | N10: =IF(B10<Parametri!$B$76,Parametri!$B$75*Parametri!$B$74*Parametri!$B$73/Parametri!$B$76,0) -> 0 | O10: =IF(B10<10,Parametri!$B$53,IF(B10<20,Parametri!$B$56,Parametri!$B$57))*M10*G10*Parametri!$B$72/1000 -> 3.053193 | P10: =MIN(Parametri!$B$81+Parametri!$B$82, Parametri!$B$81+Parametri!$B$82*(B10+1)/Parametri!$B$83) -> 7.1 | Q10: =-IF(B10<10,Parametri!$B$51,IF(B10<20,Parametri!$B$54,Parametri!$B$57))*M10*G10/1000 -> -16.962183 | R10: =-Q10-Z10 -> 11.308122 | S10: =S9+R10 -> 52.391404 | T10: =-(Parametri!$B$86*(Parametri!$B$87*Parametri!$B$90+Parametri!$B$88*Parametri!$B$91+Parametri!$B$89*Parametri!$B$92)/1000000000)*MIN(B10+1,Parametri!$B$93) -> -2.85975 | U10: =IF(B10<Parametri!$B$125,Parametri!$B$46,IF(B10<Parametri!$B$126,Parametri!$B$47,Parametri!$B$48))*Parametri!$B$96*13/1000000000*((B10+1)*Parametri!$B$121+B10*(B10+1)/2*Parametri!$B$122) -> 9.0293697 | V10: =IF(B10>=Parametri!$B$103-1,Parametri!$B$102*(1-Parametri!$B$127)^(B10-(Parametri!$B$103-1)),0) -> 5.563299 | W10: =IF(B10>=Parametri!$B$105-1,Parametri!$B$104,0) -> 5 | X10: =IF(B10>=Parametri!$B$107-1,Parametri!$B$106+Parametri!$B$128*INT((B10-(Parametri!$B$107-1))/2),0) -> 3.03 | Y10: =IF(AND(B10>=Parametri!$B$109-1,B10<Parametri!$B$109-1+Parametri!$B$140),Parametri!$B$108,0) -> 0 | Z10: =IF(B10<10,Parametri!$B$52,IF(B10<20,Parametri!$B$55,0))*M10*G10/1000 -> 5.6540611 | AA10: =Parametri!$B$159*Parametri!$B$160 -> 0 | AB10: =SUM(Z$5:Z10)+SUM(AA$5:AA10) -> 26.195702 | AC10: =-(Parametri!$B$67*SUM(Z$5:Z10)+Parametri!$B$161*SUM(AA$5:AA10)) -> -0.39293553 | AD10: =0 -> 0 | AE10: =Z10+AA10+N10+O10+P10+Q10+T10+U10+V10+W10+X10+Y10+AC10+AD10 -> 18.215054 | AF10: =AF9+AE10 -> 94.210967 | AG10: =-AF10/F10 -> -0.041488794 | AH10: =SUM(Z$5:Z10) -> 26.195702 | AI10: 0
A11: =Parametri!$B$6+B11 -> 2033 | B11: 6 | C11: =C10*(1+Parametri!$B$14) -> 23.114939 | D11: =D10*(1+Parametri!$B$15)+Parametri!$B$145*(1-Parametri!$B$15)^B10 -> 17.677577 | E11: =D11/C11 -> 0.76476849 | F11: =F10*(1+Parametri!$B$129) -> 2277.5692 | G11: =G10*(1+Parametri!$B$130) -> 26700 | H11: =F11*I11 -> 375.97412 | I11: =IF(B11<=(Parametri!$B$35-Parametri!$B$6),Parametri!$B$32+(Parametri!$B$33-Parametri!$B$32)*B11/(Parametri!$B$35-Parametri!$B$6),Parametri!$B$33+(Parametri!$B$34-Parametri!$B$33)*(B11-(Parametri!$B$35-Parametri!$B$6))/(Parametri!$B$36-Parametri!$B$35)) -> 0.16507692 | J11: =H11-AE11 -> 355.39713 | K11: =J11/F11 -> 0.1560423 | L11: =IF(B11<=5,Parametri!$B$58+(Parametri!$B$59-Parametri!$B$58)/5*B11,MIN(Parametri!$B$60,Parametri!$B$59+(Parametri!$B$60-Parametri!$B$59)/24*(B11-5))) -> 0.61666667 | M11: =L11*D11 -> 10.901172 | N11: =IF(B11<Parametri!$B$76,Parametri!$B$75*Parametri!$B$74*Parametri!$B$73/Parametri!$B$76,0) -> 0 | O11: =IF(B11<10,Parametri!$B$53,IF(B11<20,Parametri!$B$56,Parametri!$B$57))*M11*G11*Parametri!$B$72/1000 -> 3.1434621 | P11: =MIN(Parametri!$B$81+Parametri!$B$82, Parametri!$B$81+Parametri!$B$82*(B11+1)/Parametri!$B$83) -> 7.7 | Q11: =-IF(B11<10,Parametri!$B$51,IF(B11<20,Parametri!$B$54,Parametri!$B$57))*M11*G11/1000 -> -17.463678 | R11: =-Q11-Z11 -> 11.642452 | S11: =S10+R11 -> 64.033856 | T11: =-(Parametri!$B$86*(Parametri!$B$87*Parametri!$B$90+Parametri!$B$88*Parametri!$B$91+Parametri!$B$89*Parametri!$B$92)/1000000000)*MIN(B11+1,Parametri!$B$93) -> -2.85975 | U11: =IF(B11<Parametri!$B$125,Parametri!$B$46,IF(B11<Parametri!$B$126,Parametri!$B$47,Parametri!$B$48))*Parametri!$B$96*13/1000000000*((B11+1)*Parametri!$B$121+B11*(B11+1)/2*Parametri!$B$122) -> 11.206131 | V11: =IF(B11>=Parametri!$B$103-1,Parametri!$B$102*(1-Parametri!$B$127)^(B11-(Parametri!$B$103-1)),0) -> 5.4798495 | W11: =IF(B11>=Parametri!$B$105-1,Parametri!$B$104,0) -> 5 | X11: =IF(B11>=Parametri!$B$107-1,Parametri!$B$106+Parametri!$B$128*INT((B11-(Parametri!$B$107-1))/2),0) -> 3.03 | Y11: =IF(AND(B11>=Parametri!$B$109-1,B11<Parametri!$B$109-1+Parametri!$B$140),Parametri!$B$108,0) -> 0 | Z11: =IF(B11<10,Parametri!$B$52,IF(B11<20,Parametri!$B$55,0))*M11*G11/1000 -> 5.8212261 | AA11: =Parametri!$B$159*Parametri!$B$160 -> 0 | AB11: =SUM(Z$5:Z11)+SUM(AA$5:AA11) -> 32.016928 | AC11: =-(Parametri!$B$67*SUM(Z$5:Z11)+Parametri!$B$161*SUM(AA$5:AA11)) -> -0.48025392 | AD11: =0 -> 0 | AE11: =Z11+AA11+N11+O11+P11+Q11+T11+U11+V11+W11+X11+Y11+AC11+AD11 -> 20.576987 | AF11: =AF10+AE11 -> 114.78795 | AG11: =-AF11/F11 -> -0.050399326 | AH11: =SUM(Z$5:Z11) -> 32.016928 | AI11: 0
A12: =Parametri!$B$6+B12 -> 2034 | B12: 7 | C12: =C11*(1+Parametri!$B$14) -> 23.253628 | D12: =D11*(1+Parametri!$B$15)+Parametri!$B$145*(1-Parametri!$B$15)^B11 -> 17.708713 | E12: =D12/C12 -> 0.76154622 | F12: =F11*(1+Parametri!$B$129) -> 2284.4019 | G12: =G11*(1+Parametri!$B$130) -> 26700 | H12: =F12*I12 -> 379.03499 | I12: =IF(B12<=(Parametri!$B$35-Parametri!$B$6),Parametri!$B$32+(Parametri!$B$33-Parametri!$B$32)*B12/(Parametri!$B$35-Parametri!$B$6),Parametri!$B$33+(Parametri!$B$34-Parametri!$B$33)*(B12-(Parametri!$B$35-Parametri!$B$6))/(Parametri!$B$36-Parametri!$B$35)) -> 0.16592308 | J12: =H12-AE12 -> 355.76639 | K12: =J12/F12 -> 0.15573722 | L12: =IF(B12<=5,Parametri!$B$58+(Parametri!$B$59-Parametri!$B$58)/5*B12,MIN(Parametri!$B$60,Parametri!$B$59+(Parametri!$B$60-Parametri!$B$59)/24*(B12-5))) -> 0.63333333 | M12: =L12*D12 -> 11.215518 | N12: =IF(B12<Parametri!$B$76,Parametri!$B$75*Parametri!$B$74*Parametri!$B$73/Parametri!$B$76,0) -> 0 | O12: =IF(B12<10,Parametri!$B$53,IF(B12<20,Parametri!$B$56,Parametri!$B$57))*M12*G12*Parametri!$B$72/1000 -> 3.2341068 | P12: =MIN(Parametri!$B$81+Parametri!$B$82, Parametri!$B$81+Parametri!$B$82*(B12+1)/Parametri!$B$83) -> 8.3 | Q12: =-IF(B12<10,Parametri!$B$51,IF(B12<20,Parametri!$B$54,Parametri!$B$57))*M12*G12/1000 -> -17.96726 | R12: =-Q12-Z12 -> 11.978173 | S12: =S11+R12 -> 76.01203 | T12: =-(Parametri!$B$86*(Parametri!$B$87*Parametri!$B$90+Parametri!$B$88*Parametri!$B$91+Parametri!$B$89*Parametri!$B$92)/1000000000)*MIN(B12+1,Parametri!$B$93) -> -2.85975 | U12: =IF(B12<Parametri!$B$125,Parametri!$B$46,IF(B12<Parametri!$B$126,Parametri!$B$47,Parametri!$B$48))*Parametri!$B$96*13/1000000000*((B12+1)*Parametri!$B$121+B12*(B12+1)/2*Parametri!$B$122) -> 13.574855 | V12: =IF(B12>=Parametri!$B$103-1,Parametri!$B$102*(1-Parametri!$B$127)^(B12-(Parametri!$B$103-1)),0) -> 5.3976518 | W12: =IF(B12>=Parametri!$B$105-1,Parametri!$B$104,0) -> 5 | X12: =IF(B12>=Parametri!$B$107-1,Parametri!$B$106+Parametri!$B$128*INT((B12-(Parametri!$B$107-1))/2),0) -> 3.17 | Y12: =IF(AND(B12>=Parametri!$B$109-1,B12<Parametri!$B$109-1+Parametri!$B$140),Parametri!$B$108,0) -> 0 | Z12: =IF(B12<10,Parametri!$B$52,IF(B12<20,Parametri!$B$55,0))*M12*G12/1000 -> 5.9890867 | AA12: =Parametri!$B$159*Parametri!$B$160 -> 0 | AB12: =SUM(Z$5:Z12)+SUM(AA$5:AA12) -> 38.006015 | AC12: =-(Parametri!$B$67*SUM(Z$5:Z12)+Parametri!$B$161*SUM(AA$5:AA12)) -> -0.57009022 | AD12: =0 -> 0 | AE12: =Z12+AA12+N12+O12+P12+Q12+T12+U12+V12+W12+X12+Y12+AC12+AD12 -> 23.2686 | AF12: =AF11+AE12 -> 138.05655 | AG12: =-AF12/F12 -> -0.060434441 | AH12: =SUM(Z$5:Z12) -> 38.006015 | AI12: 0
A13: =Parametri!$B$6+B13 -> 2035 | B13: 8 | C13: =C12*(1+Parametri!$B$14) -> 23.39315 | D13: =D12*(1+Parametri!$B$15)+Parametri!$B$145*(1-Parametri!$B$15)^B12 -> 17.740291 | E13: =D13/C13 -> 0.75835407 | F13: =F12*(1+Parametri!$B$129) -> 2291.2551 | G13: =G12*(1+Parametri!$B$130) -> 26700 | H13: =F13*I13 -> 382.11085 | I13: =IF(B13<=(Parametri!$B$35-Parametri!$B$6),Parametri!$B$32+(Parametri!$B$33-Parametri!$B$32)*B13/(Parametri!$B$35-Parametri!$B$6),Parametri!$B$33+(Parametri!$B$34-Parametri!$B$33)*(B13-(Parametri!$B$35-Parametri!$B$6))/(Parametri!$B$36-Parametri!$B$35)) -> 0.16676923 | J13: =H13-AE13 -> 356.10101 | K13: =J13/F13 -> 0.15541744 | L13: =IF(B13<=5,Parametri!$B$58+(Parametri!$B$59-Parametri!$B$58)/5*B13,MIN(Parametri!$B$60,Parametri!$B$59+(Parametri!$B$60-Parametri!$B$59)/24*(B13-5))) -> 0.65 | M13: =L13*D13 -> 11.531189 | N13: =IF(B13<Parametri!$B$76,Parametri!$B$75*Parametri!$B$74*Parametri!$B$73/Parametri!$B$76,0) -> 0 | O13: =IF(B13<10,Parametri!$B$53,IF(B13<20,Parametri!$B$56,Parametri!$B$57))*M13*G13*Parametri!$B$72/1000 -> 3.3251336 | P13: =MIN(Parametri!$B$81+Parametri!$B$82, Parametri!$B$81+Parametri!$B$82*(B13+1)/Parametri!$B$83) -> 8.9 | Q13: =-IF(B13<10,Parametri!$B$51,IF(B13<20,Parametri!$B$54,Parametri!$B$57))*M13*G13/1000 -> -18.472965 | R13: =-Q13-Z13 -> 12.31531 | S13: =S12+R13 -> 88.327339 | T13: =-(Parametri!$B$86*(Parametri!$B$87*Parametri!$B$90+Parametri!$B$88*Parametri!$B$91+Parametri!$B$89*Parametri!$B$92)/1000000000)*MIN(B13+1,Parametri!$B$93) -> -2.85975 | U13: =IF(B13<Parametri!$B$125,Parametri!$B$46,IF(B13<Parametri!$B$126,Parametri!$B$47,Parametri!$B$48))*Parametri!$B$96*13/1000000000*((B13+1)*Parametri!$B$121+B13*(B13+1)/2*Parametri!$B$122) -> 16.13554 | V13: =IF(B13>=Parametri!$B$103-1,Parametri!$B$102*(1-Parametri!$B$127)^(B13-(Parametri!$B$103-1)),0) -> 5.316687 | W13: =IF(B13>=Parametri!$B$105-1,Parametri!$B$104,0) -> 5 | X13: =IF(B13>=Parametri!$B$107-1,Parametri!$B$106+Parametri!$B$128*INT((B13-(Parametri!$B$107-1))/2),0) -> 3.17 | Y13: =IF(AND(B13>=Parametri!$B$109-1,B13<Parametri!$B$109-1+Parametri!$B$140),Parametri!$B$108,0) -> 0 | Z13: =IF(B13<10,Parametri!$B$52,IF(B13<20,Parametri!$B$55,0))*M13*G13/1000 -> 6.1576549 | AA13: =Parametri!$B$159*Parametri!$B$160 -> 0 | AB13: =SUM(Z$5:Z13)+SUM(AA$5:AA13) -> 44.16367 | AC13: =-(Parametri!$B$67*SUM(Z$5:Z13)+Parametri!$B$161*SUM(AA$5:AA13)) -> -0.66245505 | AD13: =0 -> 0 | AE13: =Z13+AA13+N13+O13+P13+Q13+T13+U13+V13+W13+X13+Y13+AC13+AD13 -> 26.009846 | AF13: =AF12+AE13 -> 164.0664 | AG13: =-AF13/F13 -> -0.07160547 | AH13: =SUM(Z$5:Z13) -> 44.16367 | AI13: 0
A14: =Parametri!$B$6+B14 -> 2036 | B14: 9 | C14: =C13*(1+Parametri!$B$14) -> 23.533509 | D14: =D13*(1+Parametri!$B$15)+Parametri!$B$145*(1-Parametri!$B$15)^B13 -> 17.772311 | E14: =D14/C14 -> 0.75519172 | F14: =F13*(1+Parametri!$B$129) -> 2298.1289 | G14: =G13*(1+Parametri!$B$130) -> 26700 | H14: =F14*I14 -> 385.20176 | I14: =IF(B14<=(Parametri!$B$35-Parametri!$B$6),Parametri!$B$32+(Parametri!$B$33-Parametri!$B$32)*B14/(Parametri!$B$35-Parametri!$B$6),Parametri!$B$33+(Parametri!$B$34-Parametri!$B$33)*(B14-(Parametri!$B$35-Parametri!$B$6))/(Parametri!$B$36-Parametri!$B$35)) -> 0.16761538 | J14: =H14-AE14 -> 356.12108 | K14: =J14/F14 -> 0.15496132 | L14: =IF(B14<=5,Parametri!$B$58+(Parametri!$B$59-Parametri!$B$58)/5*B14,MIN(Parametri!$B$60,Parametri!$B$59+(Parametri!$B$60-Parametri!$B$59)/24*(B14-5))) -> 0.66666667 | M14: =L14*D14 -> 11.848207 | N14: =IF(B14<Parametri!$B$76,Parametri!$B$75*Parametri!$B$74*Parametri!$B$73/Parametri!$B$76,0) -> 0 | O14: =IF(B14<10,Parametri!$B$53,IF(B14<20,Parametri!$B$56,Parametri!$B$57))*M14*G14*Parametri!$B$72/1000 -> 3.4165491 | P14: =MIN(Parametri!$B$81+Parametri!$B$82, Parametri!$B$81+Parametri!$B$82*(B14+1)/Parametri!$B$83) -> 9.5 | Q14: =-IF(B14<10,Parametri!$B$51,IF(B14<20,Parametri!$B$54,Parametri!$B$57))*M14*G14/1000 -> -18.980828 | R14: =-Q14-Z14 -> 12.653886 | S14: =S13+R14 -> 100.98123 | T14: =-(Parametri!$B$86*(Parametri!$B$87*Parametri!$B$90+Parametri!$B$88*Parametri!$B$91+Parametri!$B$89*Parametri!$B$92)/1000000000)*MIN(B14+1,Parametri!$B$93) -> -2.85975 | U14: =IF(B14<Parametri!$B$125,Parametri!$B$46,IF(B14<Parametri!$B$126,Parametri!$B$47,Parametri!$B$48))*Parametri!$B$96*13/1000000000*((B14+1)*Parametri!$B$121+B14*(B14+1)/2*Parametri!$B$122) -> 18.888187 | V14: =IF(B14>=Parametri!$B$103-1,Parametri!$B$102*(1-Parametri!$B$127)^(B14-(Parametri!$B$103-1)),0) -> 5.2369367 | W14: =IF(B14>=Parametri!$B$105-1,Parametri!$B$104,0) -> 5 | X14: =IF(B14>=Parametri!$B$107-1,Parametri!$B$106+Parametri!$B$128*INT((B14-(Parametri!$B$107-1))/2),0) -> 3.31 | Y14: =IF(AND(B14>=Parametri!$B$109-1,B14<Parametri!$B$109-1+Parametri!$B$140),Parametri!$B$108,0) -> 0 | Z14: =IF(B14<10,Parametri!$B$52,IF(B14<20,Parametri!$B$55,0))*M14*G14/1000 -> 6.3269428 | AA14: =Parametri!$B$159*Parametri!$B$160 -> 0 | AB14: =SUM(Z$5:Z14)+SUM(AA$5:AA14) -> 50.490613 | AC14: =-(Parametri!$B$67*SUM(Z$5:Z14)+Parametri!$B$161*SUM(AA$5:AA14)) -> -0.75735919 | AD14: =0 -> 0 | AE14: =Z14+AA14+N14+O14+P14+Q14+T14+U14+V14+W14+X14+Y14+AC14+AD14 -> 29.080679 | AF14: =AF13+AE14 -> 193.14708 | AG14: =-AF14/F14 -> -0.084045364 | AH14: =SUM(Z$5:Z14) -> 50.490613 | AI14: 0
A15: =Parametri!$B$6+B15 -> 2037 | B15: 10 | C15: =C14*(1+Parametri!$B$14) -> 23.67471 | D15: =D14*(1+Parametri!$B$15)+Parametri!$B$145*(1-Parametri!$B$15)^B14 -> 17.804775 | E15: =D15/C15 -> 0.75205885 | F15: =F14*(1+Parametri!$B$129) -> 2305.0233 | G15: =G14*(1+Parametri!$B$130) -> 26700 | H15: =F15*I15 -> 388.30777 | I15: =IF(B15<=(Parametri!$B$35-Parametri!$B$6),Parametri!$B$32+(Parametri!$B$33-Parametri!$B$32)*B15/(Parametri!$B$35-Parametri!$B$6),Parametri!$B$33+(Parametri!$B$34-Parametri!$B$33)*(B15-(Parametri!$B$35-Parametri!$B$6))/(Parametri!$B$36-Parametri!$B$35)) -> 0.16846154 | J15: =H15-AE15 -> 360.8495 | K15: =J15/F15 -> 0.15654918 | L15: =IF(B15<=5,Parametri!$B$58+(Parametri!$B$59-Parametri!$B$58)/5*B15,MIN(Parametri!$B$60,Parametri!$B$59+(Parametri!$B$60-Parametri!$B$59)/24*(B15-5))) -> 0.68333333 | M15: =L15*D15 -> 12.166596 | N15: =IF(B15<Parametri!$B$76,Parametri!$B$75*Parametri!$B$74*Parametri!$B$73/Parametri!$B$76,0) -> 0 | O15: =IF(B15<10,Parametri!$B$53,IF(B15<20,Parametri!$B$56,Parametri!$B$57))*M15*G15*Parametri!$B$72/1000 -> 5.2625396 | P15: =MIN(Parametri!$B$81+Parametri!$B$82, Parametri!$B$81+Parametri!$B$82*(B15+1)/Parametri!$B$83) -> 10.1 | Q15: =-IF(B15<10,Parametri!$B$51,IF(B15<20,Parametri!$B$54,Parametri!$B$57))*M15*G15/1000 -> -25.98785 | R15: =-Q15-Z15 -> 19.490888 | S15: =S14+R15 -> 120.47211 | T15: =-(Parametri!$B$86*(Parametri!$B$87*Parametri!$B$90+Parametri!$B$88*Parametri!$B$91+Parametri!$B$89*Parametri!$B$92)/1000000000)*MIN(B15+1,Parametri!$B$93) -> -2.85975 | U15: =IF(B15<Parametri!$B$125,Parametri!$B$46,IF(B15<Parametri!$B$126,Parametri!$B$47,Parametri!$B$48))*Parametri!$B$96*13/1000000000*((B15+1)*Parametri!$B$121+B15*(B15+1)/2*Parametri!$B$122) -> 21.832797 | V15: =IF(B15>=Parametri!$B$103-1,Parametri!$B$102*(1-Parametri!$B$127)^(B15-(Parametri!$B$103-1)),0) -> 5.1583827 | W15: =IF(B15>=Parametri!$B$105-1,Parametri!$B$104,0) -> 5 | X15: =IF(B15>=Parametri!$B$107-1,Parametri!$B$106+Parametri!$B$128*INT((B15-(Parametri!$B$107-1))/2),0) -> 3.31 | Y15: =IF(AND(B15>=Parametri!$B$109-1,B15<Parametri!$B$109-1+Parametri!$B$140),Parametri!$B$108,0) -> 0 | Z15: =IF(B15<10,Parametri!$B$52,IF(B15<20,Parametri!$B$55,0))*M15*G15/1000 -> 6.4969625 | AA15: =Parametri!$B$159*Parametri!$B$160 -> 0 | AB15: =SUM(Z$5:Z15)+SUM(AA$5:AA15) -> 56.987575 | AC15: =-(Parametri!$B$67*SUM(Z$5:Z15)+Parametri!$B$161*SUM(AA$5:AA15)) -> -0.85481363 | AD15: =0 -> 0 | AE15: =Z15+AA15+N15+O15+P15+Q15+T15+U15+V15+W15+X15+Y15+AC15+AD15 -> 27.458268 | AF15: =AF14+AE15 -> 220.60535 | AG15: =-AF15/F15 -> -0.095706342 | AH15: =SUM(Z$5:Z15) -> 56.987575 | AI15: 0
A16: =Parametri!$B$6+B16 -> 2038 | B16: 11 | C16: =C15*(1+Parametri!$B$14) -> 23.816758 | D16: =D15*(1+Parametri!$B$15)+Parametri!$B$145*(1-Parametri!$B$15)^B15 -> 17.837684 | E16: =D16/C16 -> 0.74895514 | F16: =F15*(1+Parametri!$B$129) -> 2311.9383 | G16: =G15*(1+Parametri!$B$130) -> 26700 | H16: =F16*I16 -> 391.42895 | I16: =IF(B16<=(Parametri!$B$35-Parametri!$B$6),Parametri!$B$32+(Parametri!$B$33-Parametri!$B$32)*B16/(Parametri!$B$35-Parametri!$B$6),Parametri!$B$33+(Parametri!$B$34-Parametri!$B$33)*(B16-(Parametri!$B$35-Parametri!$B$6))/(Parametri!$B$36-Parametri!$B$35)) -> 0.16930769 | J16: =H16-AE16 -> 365.63934 | K16: =J16/F16 -> 0.15815272 | L16: =IF(B16<=5,Parametri!$B$58+(Parametri!$B$59-Parametri!$B$58)/5*B16,MIN(Parametri!$B$60,Parametri!$B$59+(Parametri!$B$60-Parametri!$B$59)/24*(B16-5))) -> 0.7 | M16: =L16*D16 -> 12.486379 | N16: =IF(B16<Parametri!$B$76,Parametri!$B$75*Parametri!$B$74*Parametri!$B$73/Parametri!$B$76,0) -> 0 | O16: =IF(B16<10,Parametri!$B$53,IF(B16<20,Parametri!$B$56,Parametri!$B$57))*M16*G16*Parametri!$B$72/1000 -> 5.4008582 | P16: =MIN(Parametri!$B$81+Parametri!$B$82, Parametri!$B$81+Parametri!$B$82*(B16+1)/Parametri!$B$83) -> 10.7 | Q16: =-IF(B16<10,Parametri!$B$51,IF(B16<20,Parametri!$B$54,Parametri!$B$57))*M16*G16/1000 -> -26.670905 | R16: =-Q16-Z16 -> 20.003178 | S16: =S15+R16 -> 140.47529 | T16: =-(Parametri!$B$86*(Parametri!$B$87*Parametri!$B$90+Parametri!$B$88*Parametri!$B$91+Parametri!$B$89*Parametri!$B$92)/1000000000)*MIN(B16+1,Parametri!$B$93) -> -2.85975 | U16: =IF(B16<Parametri!$B$125,Parametri!$B$46,IF(B16<Parametri!$B$126,Parametri!$B$47,Parametri!$B$48))*Parametri!$B$96*13/1000000000*((B16+1)*Parametri!$B$121+B16*(B16+1)/2*Parametri!$B$122) -> 19.975494 | V16: =IF(B16>=Parametri!$B$103-1,Parametri!$B$102*(1-Parametri!$B$127)^(B16-(Parametri!$B$103-1)),0) -> 5.0810069 | W16: =IF(B16>=Parametri!$B$105-1,Parametri!$B$104,0) -> 5 | X16: =IF(B16>=Parametri!$B$107-1,Parametri!$B$106+Parametri!$B$128*INT((B16-(Parametri!$B$107-1))/2),0) -> 3.45 | Y16: =IF(AND(B16>=Parametri!$B$109-1,B16<Parametri!$B$109-1+Parametri!$B$140),Parametri!$B$108,0) -> 0 | Z16: =IF(B16<10,Parametri!$B$52,IF(B16<20,Parametri!$B$55,0))*M16*G16/1000 -> 6.6677262 | AA16: =Parametri!$B$159*Parametri!$B$160 -> 0 | AB16: =SUM(Z$5:Z16)+SUM(AA$5:AA16) -> 63.655301 | AC16: =-(Parametri!$B$67*SUM(Z$5:Z16)+Parametri!$B$161*SUM(AA$5:AA16)) -> -0.95482952 | AD16: =0 -> 0 | AE16: =Z16+AA16+N16+O16+P16+Q16+T16+U16+V16+W16+X16+Y16+AC16+AD16 -> 25.789601 | AF16: =AF15+AE16 -> 246.39495 | AG16: =-AF16/F16 -> -0.10657505 | AH16: =SUM(Z$5:Z16) -> 63.655301 | AI16: 0
A17: =Parametri!$B$6+B17 -> 2039 | B17: 12 | C17: =C16*(1+Parametri!$B$14) -> 23.959659 | D17: =D16*(1+Parametri!$B$15)+Parametri!$B$145*(1-Parametri!$B$15)^B16 -> 17.871037 | E17: =D17/C17 -> 0.74588028 | F17: =F16*(1+Parametri!$B$129) -> 2318.8742 | G17: =G16*(1+Parametri!$B$130) -> 26700 | H17: =F17*I17 -> 394.56536 | I17: =IF(B17<=(Parametri!$B$35-Parametri!$B$6),Parametri!$B$32+(Parametri!$B$33-Parametri!$B$32)*B17/(Parametri!$B$35-Parametri!$B$6),Parametri!$B$33+(Parametri!$B$34-Parametri!$B$33)*(B17-(Parametri!$B$35-Parametri!$B$6))/(Parametri!$B$36-Parametri!$B$35)) -> 0.17015385 | J17: =H17-AE17 -> 366.06736 | K17: =J17/F17 -> 0.15786426 | L17: =IF(B17<=5,Parametri!$B$58+(Parametri!$B$59-Parametri!$B$58)/5*B17,MIN(Parametri!$B$60,Parametri!$B$59+(Parametri!$B$60-Parametri!$B$59)/24*(B17-5))) -> 0.71666667 | M17: =L17*D17 -> 12.807577 | N17: =IF(B17<Parametri!$B$76,Parametri!$B$75*Parametri!$B$74*Parametri!$B$73/Parametri!$B$76,0) -> 0 | O17: =IF(B17<10,Parametri!$B$53,IF(B17<20,Parametri!$B$56,Parametri!$B$57))*M17*G17*Parametri!$B$72/1000 -> 5.5397892 | P17: =MIN(Parametri!$B$81+Parametri!$B$82, Parametri!$B$81+Parametri!$B$82*(B17+1)/Parametri!$B$83) -> 11.3 | Q17: =-IF(B17<10,Parametri!$B$51,IF(B17<20,Parametri!$B$54,Parametri!$B$57))*M17*G17/1000 -> -27.356984 | R17: =-Q17-Z17 -> 20.517738 | S17: =S16+R17 -> 160.99303 | T17: =-(Parametri!$B$86*(Parametri!$B$87*Parametri!$B$90+Parametri!$B$88*Parametri!$B$91+Parametri!$B$89*Parametri!$B$92)/1000000000)*MIN(B17+1,Parametri!$B$93) -> -2.85975 | U17: =IF(B17<Parametri!$B$125,Parametri!$B$46,IF(B17<Parametri!$B$126,Parametri!$B$47,Parametri!$B$48))*Parametri!$B$96*13/1000000000*((B17+1)*Parametri!$B$121+B17*(B17+1)/2*Parametri!$B$122) -> 22.638321 | V17: =IF(B17>=Parametri!$B$103-1,Parametri!$B$102*(1-Parametri!$B$127)^(B17-(Parametri!$B$103-1)),0) -> 5.0047918 | W17: =IF(B17>=Parametri!$B$105-1,Parametri!$B$104,0) -> 5 | X17: =IF(B17>=Parametri!$B$107-1,Parametri!$B$106+Parametri!$B$128*INT((B17-(Parametri!$B$107-1))/2),0) -> 3.45 | Y17: =IF(AND(B17>=Parametri!$B$109-1,B17<Parametri!$B$109-1+Parametri!$B$140),Parametri!$B$108,0) -> 0 | Z17: =IF(B17<10,Parametri!$B$52,IF(B17<20,Parametri!$B$55,0))*M17*G17/1000 -> 6.8392459 | AA17: =Parametri!$B$159*Parametri!$B$160 -> 0 | AB17: =SUM(Z$5:Z17)+SUM(AA$5:AA17) -> 70.494547 | AC17: =-(Parametri!$B$67*SUM(Z$5:Z17)+Parametri!$B$161*SUM(AA$5:AA17)) -> -1.0574182 | AD17: =0 -> 0 | AE17: =Z17+AA17+N17+O17+P17+Q17+T17+U17+V17+W17+X17+Y17+AC17+AD17 -> 28.497996 | AF17: =AF16+AE17 -> 274.89294 | AG17: =-AF17/F17 -> -0.11854587 | AH17: =SUM(Z$5:Z17) -> 70.494547 | AI17: 0
